Workbook

Sheet BM MORRO DA CRUZ
A1: BM - PLANILHA DE MEDIÇÃO - JUNTADA | P1: CONTRATO: | R1: MED. Nº.: | T1: MED. Nº.: | V1: MED. Nº.: | X1: MED. Nº.: | Z1: MED. Nº.: | AB1: MED. Nº.: | AD1: MED. Nº.: | AF1: MED. Nº.: | AH1: MED. Nº.: | AJ1: MED. Nº.: | AL1: MED. Nº.: | AN1: MED. Nº.: | AP1: MED. Nº.: | AR1: MED. Nº.: | AT1: MED. Nº.: | AV1: MED. Nº.: | AX1: MED. Nº.: | AZ1: MED. Nº.: | BB1: DATA:
P2: _____ / | Q2: 2026 | R2: ='BM MORRO DA CRUZ - VERTICAL'!V$2 -> 1ª MEDIÇÃO | T2: ='BM MORRO DA CRUZ - VERTICAL'!X$2 -> 2ª MEDIÇÃO | V2: ='BM MORRO DA CRUZ - VERTICAL'!Z$2 -> 3ª MEDIÇÃO | X2: ='BM MORRO DA CRUZ - VERTICAL'!AB$2 -> 4ª MEDIÇÃO | Z2: ='BM MORRO DA CRUZ - VERTICAL'!AD$2 -> 5ª MEDIÇÃO | AB2: ='BM MORRO DA CRUZ - VERTICAL'!AF$2 -> 6ª MEDIÇÃO | AD2: ='BM MORRO DA CRUZ - VERTICAL'!AH$2 -> 7ª MEDIÇÃO | AF2: ='BM MORRO DA CRUZ - VERTICAL'!AJ$2 -> 8ª MEDIÇÃO | AH2: ='BM MORRO DA CRUZ - VERTICAL'!AL$2 -> 9ª MEDIÇÃO | AJ2: ='BM MORRO DA CRUZ - VERTICAL'!AN$2 -> 10ª MEDIÇÃO | AL2: ='BM MORRO DA CRUZ - VERTICAL'!AP$2 -> 11ª MEDIÇÃO | AN2: ='BM MORRO DA CRUZ - VERTICAL'!AR$2 -> 12ª MEDIÇÃO | AP2: ='BM MORRO DA CRUZ - VERTICAL'!AT$2 -> 13ª MEDIÇÃO | AR2: ='BM MORRO DA CRUZ - VERTICAL'!AV$2 -> 14ª MEDIÇÃO | AT2: ='BM MORRO DA CRUZ - VERTICAL'!AX$2 -> 15ª MEDIÇÃO | AV2: ='BM MORRO DA CRUZ - VERTICAL'!AZ$2 -> 16ª MEDIÇÃO | AX2: ='BM MORRO DA CRUZ - VERTICAL'!BB$2 -> 17ª MEDIÇÃO | AZ2: ='BM MORRO DA CRUZ - VERTICAL'!BD$2 -> 18ª MEDIÇÃO | BB2: =IF('BM MORRO DA CRUZ - VERTICAL'!$BF$2="","",'BM MORRO DA CRUZ - VERTICAL'!$BF$2)
A3: OBRA: | N3: DATA BASE - ORÇAMENTO: | P3: ORIGINAL - P0 (CAESB) - PV | R3: PERÍODO: | T3: PERÍODO: | V3: PERÍODO: | X3: PERÍODO: | Z3: PERÍODO: | AB3: PERÍODO: | AD3: PERÍODO: | AF3: PERÍODO: | AH3: PERÍODO: | AJ3: PERÍODO: | AL3: PERÍODO: | AN3: PERÍODO: | AP3: PERÍODO: | AR3: PERÍODO: | AT3: PERÍODO: | AV3: PERÍODO: | AX3: PERÍODO: | AZ3: PERÍODO: | BB3: ELAB. POR: | BD3: STATUS DO CONTRATO
A4: IMPLANTAÇÃO DE REDES DE DISTRIBUIÇÃO NO MORRO DA CRUZ, SÃO SEBASTIÃO/DF - LC 014/2026 - JUNTADA 1426 (RED.SSB-D014) | N4: 01/2025 | R4: ='BM MORRO DA CRUZ - VERTICAL'!V$4 -> 01-10-26 A 31-10-26 | T4: ='BM MORRO DA CRUZ - VERTICAL'!X$4 -> 01-11-26 A 30-11-26 | V4: ='BM MORRO DA CRUZ - VERTICAL'!Z$4 -> 01-12-26 A 31-12-26 | X4: ='BM MORRO DA CRUZ - VERTICAL'!AB$4 -> 01-01-27 A 31-01-27 | Z4: ='BM MORRO DA CRUZ - VERTICAL'!AD$4 -> 01-02-27 A 28-02-27 | AB4: ='BM MORRO DA CRUZ - VERTICAL'!AF$4 -> 01-03-27 A 31-03-27 | AD4: ='BM MORRO DA CRUZ - VERTICAL'!AH$4 -> 01-04-27 A 30-04-27 | AF4: ='BM MORRO DA CRUZ - VERTICAL'!AJ$4 -> 01-05-27 A 31-05-27 | AH4: ='BM MORRO DA CRUZ - VERTICAL'!AL$4 -> 01-06-27 A 30-06-27 | AJ4: ='BM MORRO DA CRUZ - VERTICAL'!AN$4 -> 01-07-27 A 31-07-27 | AL4: ='BM MORRO DA CRUZ - VERTICAL'!AP$4 -> 01-08-27 A 31-08-27 | AN4: ='BM MORRO DA CRUZ - VERTICAL'!AR$4 -> 01-09-27 A 30-09-27 | AP4: ='BM MORRO DA CRUZ - VERTICAL'!AT$4 -> 01-10-27 A 31-10-27 | AR4: ='BM MORRO DA CRUZ - VERTICAL'!AV$4 -> 01-11-27 A 30-11-27 | AT4: ='BM MORRO DA CRUZ - VERTICAL'!AX$4 -> 01-12-27 A 31-12-27 | AV4: ='BM MORRO DA CRUZ - VERTICAL'!AZ$4 -> 01-01-28 A 31-01-28 | AX4: ='BM MORRO DA CRUZ - VERTICAL'!BB$4 -> 01-02-28 A 29-02-28 | AZ4: ='BM MORRO DA CRUZ - VERTICAL'!BD$4 -> 01-03-28 A 23-03-28 | BB4: ANKARA ENGENHARIA LTDA
A5: ITEM - BM | B5: DESCRIÇÃO | C5: PRESSÃO | D5: RESINA | E5: TIPO_CONEXÃO | F5: SOLDA | G5: DIÂMETRO | H5: MATERIAL | I5: GRUPO | J5: GRUPO ORÇAMENTO ANKARA | K5: CÓDIGO CAESB | L5: CLASSIFICAÇÃO | M5: DESCRIÇÃO | N5: UNID. | O5: QUANT. | P5: VALOR UNITÁRIO | Q5: TOTAL | R5: QUANT. | S5: TOTAL | T5: QUANT. | U5: TOTAL | V5: QUANT. | W5: TOTAL | X5: QUANT. | Y5: TOTAL | Z5: QUANT. | AA5: TOTAL | AB5: QUANT. | AC5: TOTAL | AD5: QUANT. | AE5: TOTAL | AF5: QUANT. | AG5: TOTAL | AH5: QUANT. | AI5: TOTAL | AJ5: QUANT. | AK5: TOTAL | AL5: QUANT. | AM5: TOTAL | AN5: QUANT. | AO5: TOTAL | AP5: QUANT. | AQ5: TOTAL | AR5: QUANT. | AS5: TOTAL | AT5: QUANT. | AU5: TOTAL | AV5: QUANT. | AW5: TOTAL | AX5: QUANT. | AY5: TOTAL | AZ5: QUANT. | BA5: TOTAL | BB5: QUANT. | BC5: TOTAL ACUMULADO | BD5: % MEDIDO | BE5: % SALDO
A6: 1 | K6: 03 | M6: MATERIAL | Q6: =SUM(Q7,Q9,Q12,Q14,Q16,Q18,Q20,Q22,Q24,Q26,Q45,Q48,Q57,Q59,Q137,Q184,Q186,Q188) -> 14442997 | S6: =SUM(S7,S9,S12,S14,S16,S18,S20,S22,S24,S26,S45,S48,S57,S59,S137,S184,S186,S188) -> 0 | U6: =SUM(U7,U9,U12,U14,U16,U18,U20,U22,U24,U26,U45,U48,U57,U59,U137,U184,U186,U188) -> 0 | W6: =SUM(W7,W9,W12,W14,W16,W18,W20,W22,W24,W26,W45,W48,W57,W59,W137,W184,W186,W188) -> 0 | Y6: =SUM(Y7,Y9,Y12,Y14,Y16,Y18,Y20,Y22,Y24,Y26,Y45,Y48,Y57,Y59,Y137,Y184,Y186,Y188) -> 0 | AA6: =SUM(AA7,AA9,AA12,AA14,AA16,AA18,AA20,AA22,AA24,AA26,AA45,AA48,AA57,AA59,AA137,AA184,AA186,AA188) -> 0 | AC6: =SUM(AC7,AC9,AC12,AC14,AC16,AC18,AC20,AC22,AC24,AC26,AC45,AC48,AC57,AC59,AC137,AC184,AC186,AC188) -> 0 | AE6: =SUM(AE7,AE9,AE12,AE14,AE16,AE18,AE20,AE22,AE24,AE26,AE45,AE48,AE57,AE59,AE137,AE184,AE186,AE188) -> 0 | AG6: =SUM(AG7,AG9,AG12,AG14,AG16,AG18,AG20,AG22,AG24,AG26,AG45,AG48,AG57,AG59,AG137,AG184,AG186,AG188) -> 0 | AI6: =SUM(AI7,AI9,AI12,AI14,AI16,AI18,AI20,AI22,AI24,AI26,AI45,AI48,AI57,AI59,AI137,AI184,AI186,AI188) -> 0 | AK6: =SUM(AK7,AK9,AK12,AK14,AK16,AK18,AK20,AK22,AK24,AK26,AK45,AK48,AK57,AK59,AK137,AK184,AK186,AK188) -> 0 | AM6: =SUM(AM7,AM9,AM12,AM14,AM16,AM18,AM20,AM22,AM24,AM26,AM45,AM48,AM57,AM59,AM137,AM184,AM186,AM188) -> 0 | AO6: =SUM(AO7,AO9,AO12,AO14,AO16,AO18,AO20,AO22,AO24,AO26,AO45,AO48,AO57,AO59,AO137,AO184,AO186,AO188) -> 0 | AQ6: =SUM(AQ7,AQ9,AQ12,AQ14,AQ16,AQ18,AQ20,AQ22,AQ24,AQ26,AQ45,AQ48,AQ57,AQ59,AQ137,AQ184,AQ186,AQ188) -> 0 | AS6: =SUM(AS7,AS9,AS12,AS14,AS16,AS18,AS20,AS22,AS24,AS26,AS45,AS48,AS57,AS59,AS137,AS184,AS186,AS188) -> 0 | AU6: =SUM(AU7,AU9,AU12,AU14,AU16,AU18,AU20,AU22,AU24,AU26,AU45,AU48,AU57,AU59,AU137,AU184,AU186,AU188) -> 0 | AW6: =SUM(AW7,AW9,AW12,AW14,AW16,AW18,AW20,AW22,AW24,AW26,AW45,AW48,AW57,AW59,AW137,AW184,AW186,AW188) -> 0 | AY6: =SUM(AY7,AY9,AY12,AY14,AY16,AY18,AY20,AY22,AY24,AY26,AY45,AY48,AY57,AY59,AY137,AY184,AY186,AY188) -> 0 | BA6: =SUM(BA7,BA9,BA12,BA14,BA16,BA18,BA20,BA22,BA24,BA26,BA45,BA48,BA57,BA59,BA137,BA184,BA186,BA188) -> 0 | BC6: =SUM(BC7,BC9,BC12,BC14,BC16,BC18,BC20,BC22,BC24,BC26,BC45,BC48,BC57,BC59,BC137,BC184,BC186,BC188) -> 0
A7: 1.1 | K7: 01730 | M7: ADMINISTRAÇÃO LOCAL | Q7: =SUM(Q8:Q8) -> 28416.96 | S7: =SUM(S8:S8) -> 0 | U7: =SUM(U8:U8) -> 0 | W7: =SUM(W8:W8) -> 0 | Y7: =SUM(Y8:Y8) -> 0 | AA7: =SUM(AA8:AA8) -> 0 | AC7: =SUM(AC8:AC8) -> 0 | AE7: =SUM(AE8:AE8) -> 0 | AG7: =SUM(AG8:AG8) -> 0 | AI7: =SUM(AI8:AI8) -> 0 | AK7: =SUM(AK8:AK8) -> 0 | AM7: =SUM(AM8:AM8) -> 0 | AO7: =SUM(AO8:AO8) -> 0 | AQ7: =SUM(AQ8:AQ8) -> 0 | AS7: =SUM(AS8:AS8) -> 0 | AU7: =SUM(AU8:AU8) -> 0 | AW7: =SUM(AW8:AW8) -> 0 | AY7: =SUM(AY8:AY8) -> 0 | BA7: =SUM(BA8:BA8) -> 0 | BC7: =SUM(BC8:BC8) -> 0
A8: 1.1.1 | B8: RECURSOS MATERIAIS PARA ADMINISTRAÇÃO LOCAL | C8: N/A | D8: N/A | E8: N/A | F8: N/A | G8: N/A | H8: N/A | I8: CANTEIRO | J8: OUTROS | K8: 0173003001001 | L8: MATERIAL | M8: RECURSOS MATERIAIS PARA ADMINISTRAÇÃO LOCAL (MATERIAIS DE CONSUMO, ÁGUA, ENERGIA ELÉTRICA E COMUNICAÇÃO) - TIPO 2 | N8: MES | O8: 18 | P8: 1578.72 | Q8: =ROUND(P8*$O8,2) -> 28416.96 | R8: =IFERROR(SUMIFS('BM MORRO DA CRUZ - VERTICAL'!V$6:V$546,'BM MORRO DA CRUZ - VERTICAL'!$O$6:$O$546,'BM MORRO DA CRUZ'!$K8),0) -> 0 | S8: =ROUND(R8*$P8,2) -> 0 | T8: =IFERROR(SUMIFS('BM MORRO DA CRUZ - VERTICAL'!X$6:X$546,'BM MORRO DA CRUZ - VERTICAL'!$O$6:$O$546,'BM MORRO DA CRUZ'!$K8),0) -> 0 | U8: =ROUND(T8*$P8,2) -> 0 | V8: =IFERROR(SUMIFS('BM MORRO DA CRUZ - VERTICAL'!Z$6:Z$546,'BM MORRO DA CRUZ - VERTICAL'!$O$6:$O$546,'BM MORRO DA CRUZ'!$K8),0) -> 0 | W8: =ROUND(V8*$P8,2) -> 0 | X8: =IFERROR(SUMIFS('BM MORRO DA CRUZ - VERTICAL'!AB$6:AB$546,'BM MORRO DA CRUZ - VERTICAL'!$O$6:$O$546,'BM MORRO DA CRUZ'!$K8),0) -> 0 | Y8: =ROUND(X8*$P8,2) -> 0 | Z8: =IFERROR(SUMIFS('BM MORRO DA CRUZ - VERTICAL'!AD$6:AD$546,'BM MORRO DA CRUZ - VERTICAL'!$O$6:$O$546,'BM MORRO DA CRUZ'!$K8),0) -> 0 | AA8: =ROUND(Z8*$P8,2) -> 0 | AB8: =IFERROR(SUMIFS('BM MORRO DA CRUZ - VERTICAL'!AF$6:AF$546,'BM MORRO DA CRUZ - VERTICAL'!$O$6:$O$546,'BM MORRO DA CRUZ'!$K8),0) -> 0 | AC8: =ROUND(AB8*$P8,2) -> 0 | AD8: =IFERROR(SUMIFS('BM MORRO DA CRUZ - VERTICAL'!AH$6:AH$546,'BM MORRO DA CRUZ - VERTICAL'!$O$6:$O$546,'BM MORRO DA CRUZ'!$K8),0) -> 0 | AE8: =ROUND(AD8*$P8,2) -> 0 | AF8: =IFERROR(SUMIFS('BM MORRO DA CRUZ - VERTICAL'!AJ$6:AJ$546,'BM MORRO DA CRUZ - VERTICAL'!$O$6:$O$546,'BM MORRO DA CRUZ'!$K8),0) -> 0 | AG8: =ROUND(AF8*$P8,2) -> 0 | AH8: =IFERROR(SUMIFS('BM MORRO DA CRUZ - VERTICAL'!AL$6:AL$546,'BM MORRO DA CRUZ - VERTICAL'!$O$6:$O$546,'BM MORRO DA CRUZ'!$K8),0) -> 0 | AI8: =ROUND(AH8*$P8,2) -> 0 | AJ8: =IFERROR(SUMIFS('BM MORRO DA CRUZ - VERTICAL'!AN$6:AN$546,'BM MORRO DA CRUZ - VERTICAL'!$O$6:$O$546,'BM MORRO DA CRUZ'!$K8),0) -> 0 | AK8: =ROUND(AJ8*$P8,2) -> 0 | AL8: =IFERROR(SUMIFS('BM MORRO DA CRUZ - VERTICAL'!AP$6:AP$546,'BM MORRO DA CRUZ - VERTICAL'!$O$6:$O$546,'BM MORRO DA CRUZ'!$K8),0) -> 0 | AM8: =ROUND(AL8*$P8,2) -> 0 | AN8: =IFERROR(SUMIFS('BM MORRO DA CRUZ - VERTICAL'!AR$6:AR$546,'BM MORRO DA CRUZ - VERTICAL'!$O$6:$O$546,'BM MORRO DA CRUZ'!$K8),0) -> 0 | AO8: =ROUND(AN8*$P8,2) -> 0 | AP8: =IFERROR(SUMIFS('BM MORRO DA CRUZ - VERTICAL'!AT$6:AT$546,'BM MORRO DA CRUZ - VERTICAL'!$O$6:$O$546,'BM MORRO DA CRUZ'!$K8),0) -> 0 | AQ8: =ROUND(AP8*$P8,2) -> 0 | AR8: =IFERROR(SUMIFS('BM MORRO DA CRUZ - VERTICAL'!AV$6:AV$546,'BM MORRO DA CRUZ - VERTICAL'!$O$6:$O$546,'BM MORRO DA CRUZ'!$K8),0) -> 0 | AS8: =ROUND(AR8*$P8,2) -> 0 | AT8: =IFERROR(SUMIFS('BM MORRO DA CRUZ - VERTICAL'!AX$6:AX$546,'BM MORRO DA CRUZ - VERTICAL'!$O$6:$O$546,'BM MORRO DA CRUZ'!$K8),0) -> 0 | AU8: =ROUND(AT8*$P8,2) -> 0 | AV8: =IFERROR(SUMIFS('BM MORRO DA CRUZ - VERTICAL'!AZ$6:AZ$546,'BM MORRO DA CRUZ - VERTICAL'!$O$6:$O$546,'BM MORRO DA CRUZ'!$K8),0) -> 0 | AW8: =ROUND(AV8*$P8,2) -> 0 | AX8: =IFERROR(SUMIFS('BM MORRO DA CRUZ - VERTICAL'!BB$6:BB$546,'BM MORRO DA CRUZ - VERTICAL'!$O$6:$O$546,'BM MORRO DA CRUZ'!$K8),0) -> 0 | AY8: =ROUND(AX8*$P8,2) -> 0 | AZ8: =IFERROR(SUMIFS('BM MORRO DA CRUZ - VERTICAL'!BD$6:BD$546,'BM MORRO DA CRUZ - VERTICAL'!$O$6:$O$546,'BM MORRO DA CRUZ'!$K8),0) -> 0 | BA8: =ROUND(AZ8*$P8,2) -> 0 | BB8: =IFERROR(SUMIFS($R8:$BA8,$R$5:$BA$5,$BB$5),0) -> 0 | BC8: =SUMIFS($R8:$BA8,$R$5:$BA$5,$S$5) -> 0 | BD8: =IFERROR(BB8/O8,0) -> 0 | BE8: =IFERROR((O8-BB8)/O8,0) -> 1
A9: 1.2 | K9: 01741 | M9: CONSERVAÇÃO E LIMPEZA | Q9: =SUM(Q10:Q11) -> 1105693.9 | S9: =SUM(S10:S11) -> 0 | U9: =SUM(U10:U11) -> 0 | W9: =SUM(W10:W11) -> 0 | Y9: =SUM(Y10:Y11) -> 0 | AA9: =SUM(AA10:AA11) -> 0 | AC9: =SUM(AC10:AC11) -> 0 | AE9: =SUM(AE10:AE11) -> 0 | AG9: =SUM(AG10:AG11) -> 0 | AI9: =SUM(AI10:AI11) -> 0 | AK9: =SUM(AK10:AK11) -> 0 | AM9: =SUM(AM10:AM11) -> 0 | AO9: =SUM(AO10:AO11) -> 0 | AQ9: =SUM(AQ10:AQ11) -> 0 | AS9: =SUM(AS10:AS11) -> 0 | AU9: =SUM(AU10:AU11) -> 0 | AW9: =SUM(AW10:AW11) -> 0 | AY9: =SUM(AY10:AY11) -> 0 | BA9: =SUM(BA10:BA11) -> 0 | BC9: =SUM(BC10:BC11) -> 0
A10: 1.2.1 | B10: TAXA DISPOSIÇÃO FINAL RCC - NÃO SEGREGADOS | C10: N/A | D10: N/A | E10: N/A | F10: N/A | G10: N/A | H10: N/A | I10: REDES/LIGAÇÕES | J10: DESCARTE | K10: 0174103006001 | L10: MATERIAL | M10: TAXA PARA DISPOSIÇÃO FINAL DE RESÍDUOS DA CONSTRUÇÃO CIVIL NÃO SEGREGADOS, CONFORME RESOLUÇÃO ADASA N° 45/2024, A PARTIR DE 01/01/2025. | N10: T | O10: 204.27 | P10: 28.42 | Q10: =ROUND(P10*$O10,2) -> 5805.35 | R10: =IFERROR(SUMIFS('BM MORRO DA CRUZ - VERTICAL'!V$6:V$546,'BM MORRO DA CRUZ - VERTICAL'!$O$6:$O$546,'BM MORRO DA CRUZ'!$K10),0) -> 0 | S10: =ROUND(R10*$P10,2) -> 0 | T10: =IFERROR(SUMIFS('BM MORRO DA CRUZ - VERTICAL'!X$6:X$546,'BM MORRO DA CRUZ - VERTICAL'!$O$6:$O$546,'BM MORRO DA CRUZ'!$K10),0) -> 0 | U10: =ROUND(T10*$P10,2) -> 0 | V10: =IFERROR(SUMIFS('BM MORRO DA CRUZ - VERTICAL'!Z$6:Z$546,'BM MORRO DA CRUZ - VERTICAL'!$O$6:$O$546,'BM MORRO DA CRUZ'!$K10),0) -> 0 | W10: =ROUND(V10*$P10,2) -> 0 | X10: =IFERROR(SUMIFS('BM MORRO DA CRUZ - VERTICAL'!AB$6:AB$546,'BM MORRO DA CRUZ - VERTICAL'!$O$6:$O$546,'BM MORRO DA CRUZ'!$K10),0) -> 0 | Y10: =ROUND(X10*$P10,2) -> 0 | Z10: =IFERROR(SUMIFS('BM MORRO DA CRUZ - VERTICAL'!AD$6:AD$546,'BM MORRO DA CRUZ - VERTICAL'!$O$6:$O$546,'BM MORRO DA CRUZ'!$K10),0) -> 0 | AA10: =ROUND(Z10*$P10,2) -> 0 | AB10: =IFERROR(SUMIFS('BM MORRO DA CRUZ - VERTICAL'!AF$6:AF$546,'BM MORRO DA CRUZ - VERTICAL'!$O$6:$O$546,'BM MORRO DA CRUZ'!$K10),0) -> 0 | AC10: =ROUND(AB10*$P10,2) -> 0 | AD10: =IFERROR(SUMIFS('BM MORRO DA CRUZ - VERTICAL'!AH$6:AH$546,'BM MORRO DA CRUZ - VERTICAL'!$O$6:$O$546,'BM MORRO DA CRUZ'!$K10),0) -> 0 | AE10: =ROUND(AD10*$P10,2) -> 0 | AF10: =IFERROR(SUMIFS('BM MORRO DA CRUZ - VERTICAL'!AJ$6:AJ$546,'BM MORRO DA CRUZ - VERTICAL'!$O$6:$O$546,'BM MORRO DA CRUZ'!$K10),0) -> 0 | AG10: =ROUND(AF10*$P10,2) -> 0 | AH10: =IFERROR(SUMIFS('BM MORRO DA CRUZ - VERTICAL'!AL$6:AL$546,'BM MORRO DA CRUZ - VERTICAL'!$O$6:$O$546,'BM MORRO DA CRUZ'!$K10),0) -> 0 | AI10: =ROUND(AH10*$P10,2) -> 0 | AJ10: =IFERROR(SUMIFS('BM MORRO DA CRUZ - VERTICAL'!AN$6:AN$546,'BM MORRO DA CRUZ - VERTICAL'!$O$6:$O$546,'BM MORRO DA CRUZ'!$K10),0) -> 0 | AK10: =ROUND(AJ10*$P10,2) -> 0 | AL10: =IFERROR(SUMIFS('BM MORRO DA CRUZ - VERTICAL'!AP$6:AP$546,'BM MORRO DA CRUZ - VERTICAL'!$O$6:$O$546,'BM MORRO DA CRUZ'!$K10),0) -> 0 | AM10: =ROUND(AL10*$P10,2) -> 0 | AN10: =IFERROR(SUMIFS('BM MORRO DA CRUZ - VERTICAL'!AR$6:AR$546,'BM MORRO DA CRUZ - VERTICAL'!$O$6:$O$546,'BM MORRO DA CRUZ'!$K10),0) -> 0 | AO10: =ROUND(AN10*$P10,2) -> 0 | AP10: =IFERROR(SUMIFS('BM MORRO DA CRUZ - VERTICAL'!AT$6:AT$546,'BM MORRO DA CRUZ - VERTICAL'!$O$6:$O$546,'BM MORRO DA CRUZ'!$K10),0) -> 0 | AQ10: =ROUND(AP10*$P10,2) -> 0 | AR10: =IFERROR(SUMIFS('BM MORRO DA CRUZ - VERTICAL'!AV$6:AV$546,'BM MORRO DA CRUZ - VERTICAL'!$O$6:$O$546,'BM MORRO DA CRUZ'!$K10),0) -> 0 | AS10: =ROUND(AR10*$P10,2) -> 0 | AT10: =IFERROR(SUMIFS('BM MORRO DA CRUZ - VERTICAL'!AX$6:AX$546,'BM MORRO DA CRUZ - VERTICAL'!$O$6:$O$546,'BM MORRO DA CRUZ'!$K10),0) -> 0 | AU10: =ROUND(AT10*$P10,2) -> 0 | AV10: =IFERROR(SUMIFS('BM MORRO DA CRUZ - VERTICAL'!AZ$6:AZ$546,'BM MORRO DA CRUZ - VERTICAL'!$O$6:$O$546,'BM MORRO DA CRUZ'!$K10),0) -> 0 | AW10: =ROUND(AV10*$P10,2) -> 0 | AX10: =IFERROR(SUMIFS('BM MORRO DA CRUZ - VERTICAL'!BB$6:BB$546,'BM MORRO DA CRUZ - VERTICAL'!$O$6:$O$546,'BM MORRO DA CRUZ'!$K10),0) -> 0 | AY10: =ROUND(AX10*$P10,2) -> 0 | AZ10: =IFERROR(SUMIFS('BM MORRO DA CRUZ - VERTICAL'!BD$6:BD$546,'BM MORRO DA CRUZ - VERTICAL'!$O$6:$O$546,'BM MORRO DA CRUZ'!$K10),0) -> 0 | BA10: =ROUND(AZ10*$P10,2) -> 0 | BB10: =IFERROR(SUMIFS($R10:$BA10,$R$5:$BA$5,$BB$5),0) -> 0 | BC10: =SUMIFS($R10:$BA10,$R$5:$BA$5,$S$5) -> 0 | BD10: =IFERROR(BB10/O10,0) -> 0 | BE10: =IFERROR((O10-BB10)/O10,0) -> 1
A11: 1.2.2 | B11: TAXA DISPOSIÇÃO FINAL RCC - SEGREGADOS | C11: N/A | D11: N/A | E11: N/A | F11: N/A | G11: N/A | H11: N/A | I11: CANTEIRO/REDES/CAIXAS/INTERLIGAÇÃO | J11: DESCARTE | K11: 0174103006002 | L11: MATERIAL | M11: TAXA PARA DISPOSIÇÃO FINAL DE RESÍDUOS DA CONSTRUÇÃO CIVIL SEGREGADOS, CONFORME RESOLUÇÃO ADASA N° 45/2024, A PARTIR DE 01/01/2025. | N11: T | O11: 64208.32 | P11: 17.13 | Q11: =ROUND(P11*$O11,2) -> 1099888.5 | R11: =IFERROR(SUMIFS('BM MORRO DA CRUZ - VERTICAL'!V$6:V$546,'BM MORRO DA CRUZ - VERTICAL'!$O$6:$O$546,'BM MORRO DA CRUZ'!$K11),0) -> 0 | S11: =ROUND(R11*$P11,2) -> 0 | T11: =IFERROR(SUMIFS('BM MORRO DA CRUZ - VERTICAL'!X$6:X$546,'BM MORRO DA CRUZ - VERTICAL'!$O$6:$O$546,'BM MORRO DA CRUZ'!$K11),0) -> 0 | U11: =ROUND(T11*$P11,2) -> 0 | V11: =IFERROR(SUMIFS('BM MORRO DA CRUZ - VERTICAL'!Z$6:Z$546,'BM MORRO DA CRUZ - VERTICAL'!$O$6:$O$546,'BM MORRO DA CRUZ'!$K11),0) -> 0 | W11: =ROUND(V11*$P11,2) -> 0 | X11: =IFERROR(SUMIFS('BM MORRO DA CRUZ - VERTICAL'!AB$6:AB$546,'BM MORRO DA CRUZ - VERTICAL'!$O$6:$O$546,'BM MORRO DA CRUZ'!$K11),0) -> 0 | Y11: =ROUND(X11*$P11,2) -> 0 | Z11: =IFERROR(SUMIFS('BM MORRO DA CRUZ - VERTICAL'!AD$6:AD$546,'BM MORRO DA CRUZ - VERTICAL'!$O$6:$O$546,'BM MORRO DA CRUZ'!$K11),0) -> 0 | AA11: =ROUND(Z11*$P11,2) -> 0 | AB11: =IFERROR(SUMIFS('BM MORRO DA CRUZ - VERTICAL'!AF$6:AF$546,'BM MORRO DA CRUZ - VERTICAL'!$O$6:$O$546,'BM MORRO DA CRUZ'!$K11),0) -> 0 | AC11: =ROUND(AB11*$P11,2) -> 0 | AD11: =IFERROR(SUMIFS('BM MORRO DA CRUZ - VERTICAL'!AH$6:AH$546,'BM MORRO DA CRUZ - VERTICAL'!$O$6:$O$546,'BM MORRO DA CRUZ'!$K11),0) -> 0 | AE11: =ROUND(AD11*$P11,2) -> 0 | AF11: =IFERROR(SUMIFS('BM MORRO DA CRUZ - VERTICAL'!AJ$6:AJ$546,'BM MORRO DA CRUZ - VERTICAL'!$O$6:$O$546,'BM MORRO DA CRUZ'!$K11),0) -> 0 | AG11: =ROUND(AF11*$P11,2) -> 0 | AH11: =IFERROR(SUMIFS('BM MORRO DA CRUZ - VERTICAL'!AL$6:AL$546,'BM MORRO DA CRUZ - VERTICAL'!$O$6:$O$546,'BM MORRO DA CRUZ'!$K11),0) -> 0 | AI11: =ROUND(AH11*$P11,2) -> 0 | AJ11: =IFERROR(SUMIFS('BM MORRO DA CRUZ - VERTICAL'!AN$6:AN$546,'BM MORRO DA CRUZ - VERTICAL'!$O$6:$O$546,'BM MORRO DA CRUZ'!$K11),0) -> 0 | AK11: =ROUND(AJ11*$P11,2) -> 0 | AL11: =IFERROR(SUMIFS('BM MORRO DA CRUZ - VERTICAL'!AP$6:AP$546,'BM MORRO DA CRUZ - VERTICAL'!$O$6:$O$546,'BM MORRO DA CRUZ'!$K11),0) -> 0 | AM11: =ROUND(AL11*$P11,2) -> 0 | AN11: =IFERROR(SUMIFS('BM MORRO DA CRUZ - VERTICAL'!AR$6:AR$546,'BM MORRO DA CRUZ - VERTICAL'!$O$6:$O$546,'BM MORRO DA CRUZ'!$K11),0) -> 0 | AO11: =ROUND(AN11*$P11,2) -> 0 | AP11: =IFERROR(SUMIFS('BM MORRO DA CRUZ - VERTICAL'!AT$6:AT$546,'BM MORRO DA CRUZ - VERTICAL'!$O$6:$O$546,'BM MORRO DA CRUZ'!$K11),0) -> 0 | AQ11: =ROUND(AP11*$P11,2) -> 0 | AR11: =IFERROR(SUMIFS('BM MORRO DA CRUZ - VERTICAL'!AV$6:AV$546,'BM MORRO DA CRUZ - VERTICAL'!$O$6:$O$546,'BM MORRO DA CRUZ'!$K11),0) -> 0 | AS11: =ROUND(AR11*$P11,2) -> 0 | AT11: =IFERROR(SUMIFS('BM MORRO DA CRUZ - VERTICAL'!AX$6:AX$546,'BM MORRO DA CRUZ - VERTICAL'!$O$6:$O$546,'BM MORRO DA CRUZ'!$K11),0) -> 0 | AU11: =ROUND(AT11*$P11,2) -> 0 | AV11: =IFERROR(SUMIFS('BM MORRO DA CRUZ - VERTICAL'!AZ$6:AZ$546,'BM MORRO DA CRUZ - VERTICAL'!$O$6:$O$546,'BM MORRO DA CRUZ'!$K11),0) -> 0 | AW11: =ROUND(AV11*$P11,2) -> 0 | AX11: =IFERROR(SUMIFS('BM MORRO DA CRUZ - VERTICAL'!BB$6:BB$546,'BM MORRO DA CRUZ - VERTICAL'!$O$6:$O$546,'BM MORRO DA CRUZ'!$K11),0) -> 0 | AY11: =ROUND(AX11*$P11,2) -> 0 | AZ11: =IFERROR(SUMIFS('BM MORRO DA CRUZ - VERTICAL'!BD$6:BD$546,'BM MORRO DA CRUZ - VERTICAL'!$O$6:$O$546,'BM MORRO DA CRUZ'!$K11),0) -> 0 | BA11: =ROUND(AZ11*$P11,2) -> 0 | BB11: =IFERROR(SUMIFS($R11:$BA11,$R$5:$BA$5,$BB$5),0) -> 0 | BC11: =SUMIFS($R11:$BA11,$R$5:$BA$5,$S$5) -> 0 | BD11: =IFERROR(BB11/O11,0) -> 0 | BE11: =IFERROR((O11-BB11)/O11,0) -> 1
A12: 1.3 | K12: 02510 | M12: FORNECIMENTO DE ÁGUA | Q12: =SUM(Q13:Q13) -> 2080260.6 | S12: =SUM(S13:S13) -> 0 | U12: =SUM(U13:U13) -> 0 | W12: =SUM(W13:W13) -> 0 | Y12: =SUM(Y13:Y13) -> 0 | AA12: =SUM(AA13:AA13) -> 0 | AC12: =SUM(AC13:AC13) -> 0 | AE12: =SUM(AE13:AE13) -> 0 | AG12: =SUM(AG13:AG13) -> 0 | AI12: =SUM(AI13:AI13) -> 0 | AK12: =SUM(AK13:AK13) -> 0 | AM12: =SUM(AM13:AM13) -> 0 | AO12: =SUM(AO13:AO13) -> 0 | AQ12: =SUM(AQ13:AQ13) -> 0 | AS12: =SUM(AS13:AS13) -> 0 | AU12: =SUM(AU13:AU13) -> 0 | AW12: =SUM(AW13:AW13) -> 0 | AY12: =SUM(AY13:AY13) -> 0 | BA12: =SUM(BA13:BA13) -> 0 | BC12: =SUM(BC13:BC13) -> 0
A13: 1.3.1 | B13: KIT CAVALETE 3/4" UNIVERSAL | C13: N/A | D13: N/A | E13: KIT CAVALETE | F13: N/A | G13: 3/4" | H13: LATÃO | I13: LIGAÇÕES | J13: OUTROS | K13: 0251003002006 | L13: MATERIAL | M13: KIT CAVALETE 3/4" UNIVERSAL, HÍBRIDO PADRÃO CAESB EM LATÃO FORJADO COM BASE PARA FIXAÇÃO, EXCLUSIVE HIDRÔMETRO. | N13: UN | O13: 11894 | P13: 174.9 | Q13: =ROUND(P13*$O13,2) -> 2080260.6 | R13: =IFERROR(SUMIFS('BM MORRO DA CRUZ - VERTICAL'!V$6:V$546,'BM MORRO DA CRUZ - VERTICAL'!$O$6:$O$546,'BM MORRO DA CRUZ'!$K13),0) -> 0 | S13: =ROUND(R13*$P13,2) -> 0 | T13: =IFERROR(SUMIFS('BM MORRO DA CRUZ - VERTICAL'!X$6:X$546,'BM MORRO DA CRUZ - VERTICAL'!$O$6:$O$546,'BM MORRO DA CRUZ'!$K13),0) -> 0 | U13: =ROUND(T13*$P13,2) -> 0 | V13: =IFERROR(SUMIFS('BM MORRO DA CRUZ - VERTICAL'!Z$6:Z$546,'BM MORRO DA CRUZ - VERTICAL'!$O$6:$O$546,'BM MORRO DA CRUZ'!$K13),0) -> 0 | W13: =ROUND(V13*$P13,2) -> 0 | X13: =IFERROR(SUMIFS('BM MORRO DA CRUZ - VERTICAL'!AB$6:AB$546,'BM MORRO DA CRUZ - VERTICAL'!$O$6:$O$546,'BM MORRO DA CRUZ'!$K13),0) -> 0 | Y13: =ROUND(X13*$P13,2) -> 0 | Z13: =IFERROR(SUMIFS('BM MORRO DA CRUZ - VERTICAL'!AD$6:AD$546,'BM MORRO DA CRUZ - VERTICAL'!$O$6:$O$546,'BM MORRO DA CRUZ'!$K13),0) -> 0 | AA13: =ROUND(Z13*$P13,2) -> 0 | AB13: =IFERROR(SUMIFS('BM MORRO DA CRUZ - VERTICAL'!AF$6:AF$546,'BM MORRO DA CRUZ - VERTICAL'!$O$6:$O$546,'BM MORRO DA CRUZ'!$K13),0) -> 0 | AC13: =ROUND(AB13*$P13,2) -> 0 | AD13: =IFERROR(SUMIFS('BM MORRO DA CRUZ - VERTICAL'!AH$6:AH$546,'BM MORRO DA CRUZ - VERTICAL'!$O$6:$O$546,'BM MORRO DA CRUZ'!$K13),0) -> 0 | AE13: =ROUND(AD13*$P13,2) -> 0 | AF13: =IFERROR(SUMIFS('BM MORRO DA CRUZ - VERTICAL'!AJ$6:AJ$546,'BM MORRO DA CRUZ - VERTICAL'!$O$6:$O$546,'BM MORRO DA CRUZ'!$K13),0) -> 0 | AG13: =ROUND(AF13*$P13,2) -> 0 | AH13: =IFERROR(SUMIFS('BM MORRO DA CRUZ - VERTICAL'!AL$6:AL$546,'BM MORRO DA CRUZ - VERTICAL'!$O$6:$O$546,'BM MORRO DA CRUZ'!$K13),0) -> 0 | AI13: =ROUND(AH13*$P13,2) -> 0 | AJ13: =IFERROR(SUMIFS('BM MORRO DA CRUZ - VERTICAL'!AN$6:AN$546,'BM MORRO DA CRUZ - VERTICAL'!$O$6:$O$546,'BM MORRO DA CRUZ'!$K13),0) -> 0 | AK13: =ROUND(AJ13*$P13,2) -> 0 | AL13: =IFERROR(SUMIFS('BM MORRO DA CRUZ - VERTICAL'!AP$6:AP$546,'BM MORRO DA CRUZ - VERTICAL'!$O$6:$O$546,'BM MORRO DA CRUZ'!$K13),0) -> 0 | AM13: =ROUND(AL13*$P13,2) -> 0 | AN13: =IFERROR(SUMIFS('BM MORRO DA CRUZ - VERTICAL'!AR$6:AR$546,'BM MORRO DA CRUZ - VERTICAL'!$O$6:$O$546,'BM MORRO DA CRUZ'!$K13),0) -> 0 | AO13: =ROUND(AN13*$P13,2) -> 0 | AP13: =IFERROR(SUMIFS('BM MORRO DA CRUZ - VERTICAL'!AT$6:AT$546,'BM MORRO DA CRUZ - VERTICAL'!$O$6:$O$546,'BM MORRO DA CRUZ'!$K13),0) -> 0 | AQ13: =ROUND(AP13*$P13,2) -> 0 | AR13: =IFERROR(SUMIFS('BM MORRO DA CRUZ - VERTICAL'!AV$6:AV$546,'BM MORRO DA CRUZ - VERTICAL'!$O$6:$O$546,'BM MORRO DA CRUZ'!$K13),0) -> 0 | AS13: =ROUND(AR13*$P13,2) -> 0 | AT13: =IFERROR(SUMIFS('BM MORRO DA CRUZ - VERTICAL'!AX$6:AX$546,'BM MORRO DA CRUZ - VERTICAL'!$O$6:$O$546,'BM MORRO DA CRUZ'!$K13),0) -> 0 | AU13: =ROUND(AT13*$P13,2) -> 0 | AV13: =IFERROR(SUMIFS('BM MORRO DA CRUZ - VERTICAL'!AZ$6:AZ$546,'BM MORRO DA CRUZ - VERTICAL'!$O$6:$O$546,'BM MORRO DA CRUZ'!$K13),0) -> 0 | AW13: =ROUND(AV13*$P13,2) -> 0 | AX13: =IFERROR(SUMIFS('BM MORRO DA CRUZ - VERTICAL'!BB$6:BB$546,'BM MORRO DA CRUZ - VERTICAL'!$O$6:$O$546,'BM MORRO DA CRUZ'!$K13),0) -> 0 | AY13: =ROUND(AX13*$P13,2) -> 0 | AZ13: =IFERROR(SUMIFS('BM MORRO DA CRUZ - VERTICAL'!BD$6:BD$546,'BM MORRO DA CRUZ - VERTICAL'!$O$6:$O$546,'BM MORRO DA CRUZ'!$K13),0) -> 0 | BA13: =ROUND(AZ13*$P13,2) -> 0 | BB13: =IFERROR(SUMIFS($R13:$BA13,$R$5:$BA$5,$BB$5),0) -> 0 | BC13: =SUMIFS($R13:$BA13,$R$5:$BA$5,$S$5) -> 0 | BD13: =IFERROR(BB13/O13,0) -> 0 | BE13: =IFERROR((O13-BB13)/O13,0) -> 1
A14: 1.4 | K14: 02630 | M14: DRENAGEM DE ÁGUAS PLUVIAIS | Q14: =SUM(Q15:Q15) -> 18953.72 | S14: =SUM(S15:S15) -> 0 | U14: =SUM(U15:U15) -> 0 | W14: =SUM(W15:W15) -> 0 | Y14: =SUM(Y15:Y15) -> 0 | AA14: =SUM(AA15:AA15) -> 0 | AC14: =SUM(AC15:AC15) -> 0 | AE14: =SUM(AE15:AE15) -> 0 | AG14: =SUM(AG15:AG15) -> 0 | AI14: =SUM(AI15:AI15) -> 0 | AK14: =SUM(AK15:AK15) -> 0 | AM14: =SUM(AM15:AM15) -> 0 | AO14: =SUM(AO15:AO15) -> 0 | AQ14: =SUM(AQ15:AQ15) -> 0 | AS14: =SUM(AS15:AS15) -> 0 | AU14: =SUM(AU15:AU15) -> 0 | AW14: =SUM(AW15:AW15) -> 0 | AY14: =SUM(AY15:AY15) -> 0 | BA14: =SUM(BA15:BA15) -> 0 | BC14: =SUM(BC15:BC15) -> 0
A15: 1.4.1 | B15: TAMPA DE CONCRETO ARMADO PARA CAIXA DE INSPEÇÃO | C15: N/A | D15: N/A | E15: TAMPA | F15: N/A | G15: 600 | H15: CONCRETO | I15: CAIXAS | J15: CONCRETO | K15: 0263003006007 | L15: MATERIAL | M15: TAMPA DE CONCRETO ARMADO PARA CAIXA DE INSPEÇÃO (DIÂMETRO NOMINAL: 600 MM / ESPESSURA: 60 MM) | N15: UN | O15: 146 | P15: 129.82 | Q15: =ROUND(P15*$O15,2) -> 18953.72 | R15: =IFERROR(SUMIFS('BM MORRO DA CRUZ - VERTICAL'!V$6:V$546,'BM MORRO DA CRUZ - VERTICAL'!$O$6:$O$546,'BM MORRO DA CRUZ'!$K15),0) -> 0 | S15: =ROUND(R15*$P15,2) -> 0 | T15: =IFERROR(SUMIFS('BM MORRO DA CRUZ - VERTICAL'!X$6:X$546,'BM MORRO DA CRUZ - VERTICAL'!$O$6:$O$546,'BM MORRO DA CRUZ'!$K15),0) -> 0 | U15: =ROUND(T15*$P15,2) -> 0 | V15: =IFERROR(SUMIFS('BM MORRO DA CRUZ - VERTICAL'!Z$6:Z$546,'BM MORRO DA CRUZ - VERTICAL'!$O$6:$O$546,'BM MORRO DA CRUZ'!$K15),0) -> 0 | W15: =ROUND(V15*$P15,2) -> 0 | X15: =IFERROR(SUMIFS('BM MORRO DA CRUZ - VERTICAL'!AB$6:AB$546,'BM MORRO DA CRUZ - VERTICAL'!$O$6:$O$546,'BM MORRO DA CRUZ'!$K15),0) -> 0 | Y15: =ROUND(X15*$P15,2) -> 0 | Z15: =IFERROR(SUMIFS('BM MORRO DA CRUZ - VERTICAL'!AD$6:AD$546,'BM MORRO DA CRUZ - VERTICAL'!$O$6:$O$546,'BM MORRO DA CRUZ'!$K15),0) -> 0 | AA15: =ROUND(Z15*$P15,2) -> 0 | AB15: =IFERROR(SUMIFS('BM MORRO DA CRUZ - VERTICAL'!AF$6:AF$546,'BM MORRO DA CRUZ - VERTICAL'!$O$6:$O$546,'BM MORRO DA CRUZ'!$K15),0) -> 0 | AC15: =ROUND(AB15*$P15,2) -> 0 | AD15: =IFERROR(SUMIFS('BM MORRO DA CRUZ - VERTICAL'!AH$6:AH$546,'BM MORRO DA CRUZ - VERTICAL'!$O$6:$O$546,'BM MORRO DA CRUZ'!$K15),0) -> 0 | AE15: =ROUND(AD15*$P15,2) -> 0 | AF15: =IFERROR(SUMIFS('BM MORRO DA CRUZ - VERTICAL'!AJ$6:AJ$546,'BM MORRO DA CRUZ - VERTICAL'!$O$6:$O$546,'BM MORRO DA CRUZ'!$K15),0) -> 0 | AG15: =ROUND(AF15*$P15,2) -> 0 | AH15: =IFERROR(SUMIFS('BM MORRO DA CRUZ - VERTICAL'!AL$6:AL$546,'BM MORRO DA CRUZ - VERTICAL'!$O$6:$O$546,'BM MORRO DA CRUZ'!$K15),0) -> 0 | AI15: =ROUND(AH15*$P15,2) -> 0 | AJ15: =IFERROR(SUMIFS('BM MORRO DA CRUZ - VERTICAL'!AN$6:AN$546,'BM MORRO DA CRUZ - VERTICAL'!$O$6:$O$546,'BM MORRO DA CRUZ'!$K15),0) -> 0 | AK15: =ROUND(AJ15*$P15,2) -> 0 | AL15: =IFERROR(SUMIFS('BM MORRO DA CRUZ - VERTICAL'!AP$6:AP$546,'BM MORRO DA CRUZ - VERTICAL'!$O$6:$O$546,'BM MORRO DA CRUZ'!$K15),0) -> 0 | AM15: =ROUND(AL15*$P15,2) -> 0 | AN15: =IFERROR(SUMIFS('BM MORRO DA CRUZ - VERTICAL'!AR$6:AR$546,'BM MORRO DA CRUZ - VERTICAL'!$O$6:$O$546,'BM MORRO DA CRUZ'!$K15),0) -> 0 | AO15: =ROUND(AN15*$P15,2) -> 0 | AP15: =IFERROR(SUMIFS('BM MORRO DA CRUZ - VERTICAL'!AT$6:AT$546,'BM MORRO DA CRUZ - VERTICAL'!$O$6:$O$546,'BM MORRO DA CRUZ'!$K15),0) -> 0 | AQ15: =ROUND(AP15*$P15,2) -> 0 | AR15: =IFERROR(SUMIFS('BM MORRO DA CRUZ - VERTICAL'!AV$6:AV$546,'BM MORRO DA CRUZ - VERTICAL'!$O$6:$O$546,'BM MORRO DA CRUZ'!$K15),0) -> 0 | AS15: =ROUND(AR15*$P15,2) -> 0 | AT15: =IFERROR(SUMIFS('BM MORRO DA CRUZ - VERTICAL'!AX$6:AX$546,'BM MORRO DA CRUZ - VERTICAL'!$O$6:$O$546,'BM MORRO DA CRUZ'!$K15),0) -> 0 | AU15: =ROUND(AT15*$P15,2) -> 0 | AV15: =IFERROR(SUMIFS('BM MORRO DA CRUZ - VERTICAL'!AZ$6:AZ$546,'BM MORRO DA CRUZ - VERTICAL'!$O$6:$O$546,'BM MORRO DA CRUZ'!$K15),0) -> 0 | AW15: =ROUND(AV15*$P15,2) -> 0 | AX15: =IFERROR(SUMIFS('BM MORRO DA CRUZ - VERTICAL'!BB$6:BB$546,'BM MORRO DA CRUZ - VERTICAL'!$O$6:$O$546,'BM MORRO DA CRUZ'!$K15),0) -> 0 | AY15: =ROUND(AX15*$P15,2) -> 0 | AZ15: =IFERROR(SUMIFS('BM MORRO DA CRUZ - VERTICAL'!BD$6:BD$546,'BM MORRO DA CRUZ - VERTICAL'!$O$6:$O$546,'BM MORRO DA CRUZ'!$K15),0) -> 0 | BA15: =ROUND(AZ15*$P15,2) -> 0 | BB15: =IFERROR(SUMIFS($R15:$BA15,$R$5:$BA$5,$BB$5),0) -> 0 | BC15: =SUMIFS($R15:$BA15,$R$5:$BA$5,$S$5) -> 0 | BD15: =IFERROR(BB15/O15,0) -> 0 | BE15: =IFERROR((O15-BB15)/O15,0) -> 1
A16: 1.5 | K16: 03480 | M16: CONCRETOS PRÉ-MOLDADOS | Q16: =SUM(Q17:Q17) -> 6211998.3 | S16: =SUM(S17:S17) -> 0 | U16: =SUM(U17:U17) -> 0 | W16: =SUM(W17:W17) -> 0 | Y16: =SUM(Y17:Y17) -> 0 | AA16: =SUM(AA17:AA17) -> 0 | AC16: =SUM(AC17:AC17) -> 0 | AE16: =SUM(AE17:AE17) -> 0 | AG16: =SUM(AG17:AG17) -> 0 | AI16: =SUM(AI17:AI17) -> 0 | AK16: =SUM(AK17:AK17) -> 0 | AM16: =SUM(AM17:AM17) -> 0 | AO16: =SUM(AO17:AO17) -> 0 | AQ16: =SUM(AQ17:AQ17) -> 0 | AS16: =SUM(AS17:AS17) -> 0 | AU16: =SUM(AU17:AU17) -> 0 | AW16: =SUM(AW17:AW17) -> 0 | AY16: =SUM(AY17:AY17) -> 0 | BA16: =SUM(BA17:BA17) -> 0 | BC16: =SUM(BC17:BC17) -> 0
A17: 1.5.1 | B17: ABRIGO/MURETA PRÉ-MOLDADA P/ 02 HIDRÔMETROS | C17: N/A | D17: N/A | E17: MURETA | F17: N/A | G17: 50 | H17: PVC | I17: LIGAÇÕES | J17: CONCRETO | K17: 0348003003016 | L17: MATERIAL | M17: ABRIGO/MURETA PRÉ-MOLDADA DE CONCRETO ARMADO FCK = 25 MPA PADRÃO CAESB COM CAIXA DE POLICARBONATO PARA DOIS HIDRÔMETROS INSTALADA. MEDIDAS DO REQUADRO: 0,70 X 0,60 X 0,15 M. MEDIDAS DOS PILARES: 0,16 X 0,64 X 0,15 M. MEDIDAS EXTERNAS: 0,70 X 1,24 X 0,15 M. PREVISÃO DE TUBOS DE PVC COM DIÂMETRO DE 50 MM: UM COM COMPRIMENTO DE 0,75 M PARA ENTRADA E DOIS COM COMPRIMENTO DE 0,11 M PARA SAÍDAS | N17: UN | O17: 11894 | P17: 522.28 | Q17: =ROUND(P17*$O17,2) -> 6211998.3 | R17: =IFERROR(SUMIFS('BM MORRO DA CRUZ - VERTICAL'!V$6:V$546,'BM MORRO DA CRUZ - VERTICAL'!$O$6:$O$546,'BM MORRO DA CRUZ'!$K17),0) -> 0 | S17: =ROUND(R17*$P17,2) -> 0 | T17: =IFERROR(SUMIFS('BM MORRO DA CRUZ - VERTICAL'!X$6:X$546,'BM MORRO DA CRUZ - VERTICAL'!$O$6:$O$546,'BM MORRO DA CRUZ'!$K17),0) -> 0 | U17: =ROUND(T17*$P17,2) -> 0 | V17: =IFERROR(SUMIFS('BM MORRO DA CRUZ - VERTICAL'!Z$6:Z$546,'BM MORRO DA CRUZ - VERTICAL'!$O$6:$O$546,'BM MORRO DA CRUZ'!$K17),0) -> 0 | W17: =ROUND(V17*$P17,2) -> 0 | X17: =IFERROR(SUMIFS('BM MORRO DA CRUZ - VERTICAL'!AB$6:AB$546,'BM MORRO DA CRUZ - VERTICAL'!$O$6:$O$546,'BM MORRO DA CRUZ'!$K17),0) -> 0 | Y17: =ROUND(X17*$P17,2) -> 0 | Z17: =IFERROR(SUMIFS('BM MORRO DA CRUZ - VERTICAL'!AD$6:AD$546,'BM MORRO DA CRUZ - VERTICAL'!$O$6:$O$546,'BM MORRO DA CRUZ'!$K17),0) -> 0 | AA17: =ROUND(Z17*$P17,2) -> 0 | AB17: =IFERROR(SUMIFS('BM MORRO DA CRUZ - VERTICAL'!AF$6:AF$546,'BM MORRO DA CRUZ - VERTICAL'!$O$6:$O$546,'BM MORRO DA CRUZ'!$K17),0) -> 0 | AC17: =ROUND(AB17*$P17,2) -> 0 | AD17: =IFERROR(SUMIFS('BM MORRO DA CRUZ - VERTICAL'!AH$6:AH$546,'BM MORRO DA CRUZ - VERTICAL'!$O$6:$O$546,'BM MORRO DA CRUZ'!$K17),0) -> 0 | AE17: =ROUND(AD17*$P17,2) -> 0 | AF17: =IFERROR(SUMIFS('BM MORRO DA CRUZ - VERTICAL'!AJ$6:AJ$546,'BM MORRO DA CRUZ - VERTICAL'!$O$6:$O$546,'BM MORRO DA CRUZ'!$K17),0) -> 0 | AG17: =ROUND(AF17*$P17,2) -> 0 | AH17: =IFERROR(SUMIFS('BM MORRO DA CRUZ - VERTICAL'!AL$6:AL$546,'BM MORRO DA CRUZ - VERTICAL'!$O$6:$O$546,'BM MORRO DA CRUZ'!$K17),0) -> 0 | AI17: =ROUND(AH17*$P17,2) -> 0 | AJ17: =IFERROR(SUMIFS('BM MORRO DA CRUZ - VERTICAL'!AN$6:AN$546,'BM MORRO DA CRUZ - VERTICAL'!$O$6:$O$546,'BM MORRO DA CRUZ'!$K17),0) -> 0 | AK17: =ROUND(AJ17*$P17,2) -> 0 | AL17: =IFERROR(SUMIFS('BM MORRO DA CRUZ - VERTICAL'!AP$6:AP$546,'BM MORRO DA CRUZ - VERTICAL'!$O$6:$O$546,'BM MORRO DA CRUZ'!$K17),0) -> 0 | AM17: =ROUND(AL17*$P17,2) -> 0 | AN17: =IFERROR(SUMIFS('BM MORRO DA CRUZ - VERTICAL'!AR$6:AR$546,'BM MORRO DA CRUZ - VERTICAL'!$O$6:$O$546,'BM MORRO DA CRUZ'!$K17),0) -> 0 | AO17: =ROUND(AN17*$P17,2) -> 0 | AP17: =IFERROR(SUMIFS('BM MORRO DA CRUZ - VERTICAL'!AT$6:AT$546,'BM MORRO DA CRUZ - VERTICAL'!$O$6:$O$546,'BM MORRO DA CRUZ'!$K17),0) -> 0 | AQ17: =ROUND(AP17*$P17,2) -> 0 | AR17: =IFERROR(SUMIFS('BM MORRO DA CRUZ - VERTICAL'!AV$6:AV$546,'BM MORRO DA CRUZ - VERTICAL'!$O$6:$O$546,'BM MORRO DA CRUZ'!$K17),0) -> 0 | AS17: =ROUND(AR17*$P17,2) -> 0 | AT17: =IFERROR(SUMIFS('BM MORRO DA CRUZ - VERTICAL'!AX$6:AX$546,'BM MORRO DA CRUZ - VERTICAL'!$O$6:$O$546,'BM MORRO DA CRUZ'!$K17),0) -> 0 | AU17: =ROUND(AT17*$P17,2) -> 0 | AV17: =IFERROR(SUMIFS('BM MORRO DA CRUZ - VERTICAL'!AZ$6:AZ$546,'BM MORRO DA CRUZ - VERTICAL'!$O$6:$O$546,'BM MORRO DA CRUZ'!$K17),0) -> 0 | AW17: =ROUND(AV17*$P17,2) -> 0 | AX17: =IFERROR(SUMIFS('BM MORRO DA CRUZ - VERTICAL'!BB$6:BB$546,'BM MORRO DA CRUZ - VERTICAL'!$O$6:$O$546,'BM MORRO DA CRUZ'!$K17),0) -> 0 | AY17: =ROUND(AX17*$P17,2) -> 0 | AZ17: =IFERROR(SUMIFS('BM MORRO DA CRUZ - VERTICAL'!BD$6:BD$546,'BM MORRO DA CRUZ - VERTICAL'!$O$6:$O$546,'BM MORRO DA CRUZ'!$K17),0) -> 0 | BA17: =ROUND(AZ17*$P17,2) -> 0 | BB17: =IFERROR(SUMIFS($R17:$BA17,$R$5:$BA$5,$BB$5),0) -> 0 | BC17: =SUMIFS($R17:$BA17,$R$5:$BA$5,$S$5) -> 0 | BD17: =IFERROR(BB17/O17,0) -> 0 | BE17: =IFERROR((O17-BB17)/O17,0) -> 1
A18: 1.6 | K18: 10180 | M18: COBERTURAS | Q18: =SUM(Q19:Q19) -> 5200 | S18: =SUM(S19:S19) -> 0 | U18: =SUM(U19:U19) -> 0 | W18: =SUM(W19:W19) -> 0 | Y18: =SUM(Y19:Y19) -> 0 | AA18: =SUM(AA19:AA19) -> 0 | AC18: =SUM(AC19:AC19) -> 0 | AE18: =SUM(AE19:AE19) -> 0 | AG18: =SUM(AG19:AG19) -> 0 | AI18: =SUM(AI19:AI19) -> 0 | AK18: =SUM(AK19:AK19) -> 0 | AM18: =SUM(AM19:AM19) -> 0 | AO18: =SUM(AO19:AO19) -> 0 | AQ18: =SUM(AQ19:AQ19) -> 0 | AS18: =SUM(AS19:AS19) -> 0 | AU18: =SUM(AU19:AU19) -> 0 | AW18: =SUM(AW19:AW19) -> 0 | AY18: =SUM(AY19:AY19) -> 0 | BA18: =SUM(BA19:BA19) -> 0 | BC18: =SUM(BC19:BC19) -> 0
A19: 1.6.1 | B19: TENDA PIRAMIDAL 3,00 X 3,00 M COM FECHAMENTOS LATERAIS | C19: N/A | D19: N/A | E19: TENDA | F19: N/A | G19: 3,00X3,00 | H19: LONA PVC | I19: CANTEIRO | J19: CANTEIRO | K19: 1018003001001 | L19: MATERIAL | M19: TENDA PIRAMIDAL 3,00 X 3,00 M COM FECHAMENTOS LATERAIS | N19: UN | O19: 2 | P19: 2600 | Q19: =ROUND(P19*$O19,2) -> 5200 | R19: =IFERROR(SUMIFS('BM MORRO DA CRUZ - VERTICAL'!V$6:V$546,'BM MORRO DA CRUZ - VERTICAL'!$O$6:$O$546,'BM MORRO DA CRUZ'!$K19),0) -> 0 | S19: =ROUND(R19*$P19,2) -> 0 | T19: =IFERROR(SUMIFS('BM MORRO DA CRUZ - VERTICAL'!X$6:X$546,'BM MORRO DA CRUZ - VERTICAL'!$O$6:$O$546,'BM MORRO DA CRUZ'!$K19),0) -> 0 | U19: =ROUND(T19*$P19,2) -> 0 | V19: =IFERROR(SUMIFS('BM MORRO DA CRUZ - VERTICAL'!Z$6:Z$546,'BM MORRO DA CRUZ - VERTICAL'!$O$6:$O$546,'BM MORRO DA CRUZ'!$K19),0) -> 0 | W19: =ROUND(V19*$P19,2) -> 0 | X19: =IFERROR(SUMIFS('BM MORRO DA CRUZ - VERTICAL'!AB$6:AB$546,'BM MORRO DA CRUZ - VERTICAL'!$O$6:$O$546,'BM MORRO DA CRUZ'!$K19),0) -> 0 | Y19: =ROUND(X19*$P19,2) -> 0 | Z19: =IFERROR(SUMIFS('BM MORRO DA CRUZ - VERTICAL'!AD$6:AD$546,'BM MORRO DA CRUZ - VERTICAL'!$O$6:$O$546,'BM MORRO DA CRUZ'!$K19),0) -> 0 | AA19: =ROUND(Z19*$P19,2) -> 0 | AB19: =IFERROR(SUMIFS('BM MORRO DA CRUZ - VERTICAL'!AF$6:AF$546,'BM MORRO DA CRUZ - VERTICAL'!$O$6:$O$546,'BM MORRO DA CRUZ'!$K19),0) -> 0 | AC19: =ROUND(AB19*$P19,2) -> 0 | AD19: =IFERROR(SUMIFS('BM MORRO DA CRUZ - VERTICAL'!AH$6:AH$546,'BM MORRO DA CRUZ - VERTICAL'!$O$6:$O$546,'BM MORRO DA CRUZ'!$K19),0) -> 0 | AE19: =ROUND(AD19*$P19,2) -> 0 | AF19: =IFERROR(SUMIFS('BM MORRO DA CRUZ - VERTICAL'!AJ$6:AJ$546,'BM MORRO DA CRUZ - VERTICAL'!$O$6:$O$546,'BM MORRO DA CRUZ'!$K19),0) -> 0 | AG19: =ROUND(AF19*$P19,2) -> 0 | AH19: =IFERROR(SUMIFS('BM MORRO DA CRUZ - VERTICAL'!AL$6:AL$546,'BM MORRO DA CRUZ - VERTICAL'!$O$6:$O$546,'BM MORRO DA CRUZ'!$K19),0) -> 0 | AI19: =ROUND(AH19*$P19,2) -> 0 | AJ19: =IFERROR(SUMIFS('BM MORRO DA CRUZ - VERTICAL'!AN$6:AN$546,'BM MORRO DA CRUZ - VERTICAL'!$O$6:$O$546,'BM MORRO DA CRUZ'!$K19),0) -> 0 | AK19: =ROUND(AJ19*$P19,2) -> 0 | AL19: =IFERROR(SUMIFS('BM MORRO DA CRUZ - VERTICAL'!AP$6:AP$546,'BM MORRO DA CRUZ - VERTICAL'!$O$6:$O$546,'BM MORRO DA CRUZ'!$K19),0) -> 0 | AM19: =ROUND(AL19*$P19,2) -> 0 | AN19: =IFERROR(SUMIFS('BM MORRO DA CRUZ - VERTICAL'!AR$6:AR$546,'BM MORRO DA CRUZ - VERTICAL'!$O$6:$O$546,'BM MORRO DA CRUZ'!$K19),0) -> 0 | AO19: =ROUND(AN19*$P19,2) -> 0 | AP19: =IFERROR(SUMIFS('BM MORRO DA CRUZ - VERTICAL'!AT$6:AT$546,'BM MORRO DA CRUZ - VERTICAL'!$O$6:$O$546,'BM MORRO DA CRUZ'!$K19),0) -> 0 | AQ19: =ROUND(AP19*$P19,2) -> 0 | AR19: =IFERROR(SUMIFS('BM MORRO DA CRUZ - VERTICAL'!AV$6:AV$546,'BM MORRO DA CRUZ - VERTICAL'!$O$6:$O$546,'BM MORRO DA CRUZ'!$K19),0) -> 0 | AS19: =ROUND(AR19*$P19,2) -> 0 | AT19: =IFERROR(SUMIFS('BM MORRO DA CRUZ - VERTICAL'!AX$6:AX$546,'BM MORRO DA CRUZ - VERTICAL'!$O$6:$O$546,'BM MORRO DA CRUZ'!$K19),0) -> 0 | AU19: =ROUND(AT19*$P19,2) -> 0 | AV19: =IFERROR(SUMIFS('BM MORRO DA CRUZ - VERTICAL'!AZ$6:AZ$546,'BM MORRO DA CRUZ - VERTICAL'!$O$6:$O$546,'BM MORRO DA CRUZ'!$K19),0) -> 0 | AW19: =ROUND(AV19*$P19,2) -> 0 | AX19: =IFERROR(SUMIFS('BM MORRO DA CRUZ - VERTICAL'!BB$6:BB$546,'BM MORRO DA CRUZ - VERTICAL'!$O$6:$O$546,'BM MORRO DA CRUZ'!$K19),0) -> 0 | AY19: =ROUND(AX19*$P19,2) -> 0 | AZ19: =IFERROR(SUMIFS('BM MORRO DA CRUZ - VERTICAL'!BD$6:BD$546,'BM MORRO DA CRUZ - VERTICAL'!$O$6:$O$546,'BM MORRO DA CRUZ'!$K19),0) -> 0 | BA19: =ROUND(AZ19*$P19,2) -> 0 | BB19: =IFERROR(SUMIFS($R19:$BA19,$R$5:$BA$5,$BB$5),0) -> 0 | BC19: =SUMIFS($R19:$BA19,$R$5:$BA$5,$S$5) -> 0 | BD19: =IFERROR(BB19/O19,0) -> 0 | BE19: =IFERROR((O19-BB19)/O19,0) -> 1
A20: 1.7 | K20: 12510 | M20: MÓVEIS PARA ESCRITÓRIO | Q20: =SUM(Q21:Q21) -> 8892.18 | S20: =SUM(S21:S21) -> 0 | U20: =SUM(U21:U21) -> 0 | W20: =SUM(W21:W21) -> 0 | Y20: =SUM(Y21:Y21) -> 0 | AA20: =SUM(AA21:AA21) -> 0 | AC20: =SUM(AC21:AC21) -> 0 | AE20: =SUM(AE21:AE21) -> 0 | AG20: =SUM(AG21:AG21) -> 0 | AI20: =SUM(AI21:AI21) -> 0 | AK20: =SUM(AK21:AK21) -> 0 | AM20: =SUM(AM21:AM21) -> 0 | AO20: =SUM(AO21:AO21) -> 0 | AQ20: =SUM(AQ21:AQ21) -> 0 | AS20: =SUM(AS21:AS21) -> 0 | AU20: =SUM(AU21:AU21) -> 0 | AW20: =SUM(AW21:AW21) -> 0 | AY20: =SUM(AY21:AY21) -> 0 | BA20: =SUM(BA21:BA21) -> 0 | BC20: =SUM(BC21:BC21) -> 0
A21: 1.7.1 | B21: INFRAESTRUTURA BÁSICA PARA FISCALIZAÇÃO | C21: N/A | D21: N/A | E21: N/A | F21: N/A | G21: N/A | H21: N/A | I21: CANTEIRO | J21: CANTEIRO | K21: 1251003008004 | L21: MATERIAL | M21: INFRAESTRUTURA BÁSICA PARA FISCALIZAÇÃO INCLUINDO NO MÍNIMO OS ITENS A SEGUIR: MÓVEIS E EQUIPAMENTOS (DUAS MESAS, QUATRO CADEIRAS, UM PURIFICADOR DE ÁGUA, UM APARELHO DE AR CONDICIONADO 7500 BTUS, UM NOTEBOOK INTEL CORE I7, 12GB, SSD 256GB, TELA COM RESOLUÇÃO MÍNIMA 1920X1080P, WINDOWS 10 OU VERSÕES SUPERIORES, COM PACOTE MICROSOFT OFFICE 360 E ACESSO À INTERNET). | N21: MES | O21: 18 | P21: 494.01 | Q21: =ROUND(P21*$O21,2) -> 8892.18 | R21: =IFERROR(SUMIFS('BM MORRO DA CRUZ - VERTICAL'!V$6:V$546,'BM MORRO DA CRUZ - VERTICAL'!$O$6:$O$546,'BM MORRO DA CRUZ'!$K21),0) -> 0 | S21: =ROUND(R21*$P21,2) -> 0 | T21: =IFERROR(SUMIFS('BM MORRO DA CRUZ - VERTICAL'!X$6:X$546,'BM MORRO DA CRUZ - VERTICAL'!$O$6:$O$546,'BM MORRO DA CRUZ'!$K21),0) -> 0 | U21: =ROUND(T21*$P21,2) -> 0 | V21: =IFERROR(SUMIFS('BM MORRO DA CRUZ - VERTICAL'!Z$6:Z$546,'BM MORRO DA CRUZ - VERTICAL'!$O$6:$O$546,'BM MORRO DA CRUZ'!$K21),0) -> 0 | W21: =ROUND(V21*$P21,2) -> 0 | X21: =IFERROR(SUMIFS('BM MORRO DA CRUZ - VERTICAL'!AB$6:AB$546,'BM MORRO DA CRUZ - VERTICAL'!$O$6:$O$546,'BM MORRO DA CRUZ'!$K21),0) -> 0 | Y21: =ROUND(X21*$P21,2) -> 0 | Z21: =IFERROR(SUMIFS('BM MORRO DA CRUZ - VERTICAL'!AD$6:AD$546,'BM MORRO DA CRUZ - VERTICAL'!$O$6:$O$546,'BM MORRO DA CRUZ'!$K21),0) -> 0 | AA21: =ROUND(Z21*$P21,2) -> 0 | AB21: =IFERROR(SUMIFS('BM MORRO DA CRUZ - VERTICAL'!AF$6:AF$546,'BM MORRO DA CRUZ - VERTICAL'!$O$6:$O$546,'BM MORRO DA CRUZ'!$K21),0) -> 0 | AC21: =ROUND(AB21*$P21,2) -> 0 | AD21: =IFERROR(SUMIFS('BM MORRO DA CRUZ - VERTICAL'!AH$6:AH$546,'BM MORRO DA CRUZ - VERTICAL'!$O$6:$O$546,'BM MORRO DA CRUZ'!$K21),0) -> 0 | AE21: =ROUND(AD21*$P21,2) -> 0 | AF21: =IFERROR(SUMIFS('BM MORRO DA CRUZ - VERTICAL'!AJ$6:AJ$546,'BM MORRO DA CRUZ - VERTICAL'!$O$6:$O$546,'BM MORRO DA CRUZ'!$K21),0) -> 0 | AG21: =ROUND(AF21*$P21,2) -> 0 | AH21: =IFERROR(SUMIFS('BM MORRO DA CRUZ - VERTICAL'!AL$6:AL$546,'BM MORRO DA CRUZ - VERTICAL'!$O$6:$O$546,'BM MORRO DA CRUZ'!$K21),0) -> 0 | AI21: =ROUND(AH21*$P21,2) -> 0 | AJ21: =IFERROR(SUMIFS('BM MORRO DA CRUZ - VERTICAL'!AN$6:AN$546,'BM MORRO DA CRUZ - VERTICAL'!$O$6:$O$546,'BM MORRO DA CRUZ'!$K21),0) -> 0 | AK21: =ROUND(AJ21*$P21,2) -> 0 | AL21: =IFERROR(SUMIFS('BM MORRO DA CRUZ - VERTICAL'!AP$6:AP$546,'BM MORRO DA CRUZ - VERTICAL'!$O$6:$O$546,'BM MORRO DA CRUZ'!$K21),0) -> 0 | AM21: =ROUND(AL21*$P21,2) -> 0 | AN21: =IFERROR(SUMIFS('BM MORRO DA CRUZ - VERTICAL'!AR$6:AR$546,'BM MORRO DA CRUZ - VERTICAL'!$O$6:$O$546,'BM MORRO DA CRUZ'!$K21),0) -> 0 | AO21: =ROUND(AN21*$P21,2) -> 0 | AP21: =IFERROR(SUMIFS('BM MORRO DA CRUZ - VERTICAL'!AT$6:AT$546,'BM MORRO DA CRUZ - VERTICAL'!$O$6:$O$546,'BM MORRO DA CRUZ'!$K21),0) -> 0 | AQ21: =ROUND(AP21*$P21,2) -> 0 | AR21: =IFERROR(SUMIFS('BM MORRO DA CRUZ - VERTICAL'!AV$6:AV$546,'BM MORRO DA CRUZ - VERTICAL'!$O$6:$O$546,'BM MORRO DA CRUZ'!$K21),0) -> 0 | AS21: =ROUND(AR21*$P21,2) -> 0 | AT21: =IFERROR(SUMIFS('BM MORRO DA CRUZ - VERTICAL'!AX$6:AX$546,'BM MORRO DA CRUZ - VERTICAL'!$O$6:$O$546,'BM MORRO DA CRUZ'!$K21),0) -> 0 | AU21: =ROUND(AT21*$P21,2) -> 0 | AV21: =IFERROR(SUMIFS('BM MORRO DA CRUZ - VERTICAL'!AZ$6:AZ$546,'BM MORRO DA CRUZ - VERTICAL'!$O$6:$O$546,'BM MORRO DA CRUZ'!$K21),0) -> 0 | AW21: =ROUND(AV21*$P21,2) -> 0 | AX21: =IFERROR(SUMIFS('BM MORRO DA CRUZ - VERTICAL'!BB$6:BB$546,'BM MORRO DA CRUZ - VERTICAL'!$O$6:$O$546,'BM MORRO DA CRUZ'!$K21),0) -> 0 | AY21: =ROUND(AX21*$P21,2) -> 0 | AZ21: =IFERROR(SUMIFS('BM MORRO DA CRUZ - VERTICAL'!BD$6:BD$546,'BM MORRO DA CRUZ - VERTICAL'!$O$6:$O$546,'BM MORRO DA CRUZ'!$K21),0) -> 0 | BA21: =ROUND(AZ21*$P21,2) -> 0 | BB21: =IFERROR(SUMIFS($R21:$BA21,$R$5:$BA$5,$BB$5),0) -> 0 | BC21: =SUMIFS($R21:$BA21,$R$5:$BA$5,$S$5) -> 0 | BD21: =IFERROR(BB21/O21,0) -> 0 | BE21: =IFERROR((O21-BB21)/O21,0) -> 1
A22: 1.8 | K22: 15002 | M22: ACESSÓRIOS PARA TRATAMENTO DE ÁGUA | Q22: =SUM(Q23:Q23) -> 147.3 | S22: =SUM(S23:S23) -> 0 | U22: =SUM(U23:U23) -> 0 | W22: =SUM(W23:W23) -> 0 | Y22: =SUM(Y23:Y23) -> 0 | AA22: =SUM(AA23:AA23) -> 0 | AC22: =SUM(AC23:AC23) -> 0 | AE22: =SUM(AE23:AE23) -> 0 | AG22: =SUM(AG23:AG23) -> 0 | AI22: =SUM(AI23:AI23) -> 0 | AK22: =SUM(AK23:AK23) -> 0 | AM22: =SUM(AM23:AM23) -> 0 | AO22: =SUM(AO23:AO23) -> 0 | AQ22: =SUM(AQ23:AQ23) -> 0 | AS22: =SUM(AS23:AS23) -> 0 | AU22: =SUM(AU23:AU23) -> 0 | AW22: =SUM(AW23:AW23) -> 0 | AY22: =SUM(AY23:AY23) -> 0 | BA22: =SUM(BA23:BA23) -> 0 | BC22: =SUM(BC23:BC23) -> 0
A23: 1.8.1 | B23: ARRUELA BORRACHA S/ ALMA METÁLICA (ABF) | C23: PN10 | D23: N/A | E23: ARRUELA | F23: N/A | G23: 200 | H23: BORRACHA | I23: HIDROMECÂNICO | J23: FOFO | K23: 1500203055014 | L23: MATERIAL | M23: ACESSÓRIO PARA FLANGE: ARRUELA DE BORRACHA SEM ALMA METÁLICA (ABF), COM ELASTÔMERO SBR, EXCLUSIVO PARA ÁGUA (CLASSE DE PRESSÃO: 10 KGF/CM² / DIÂMETRO DA SEÇÃO: 200 MM) | N23: UN | O23: 15 | P23: 9.82 | Q23: =ROUND(P23*$O23,2) -> 147.3 | R23: =IFERROR(SUMIFS('BM MORRO DA CRUZ - VERTICAL'!V$6:V$546,'BM MORRO DA CRUZ - VERTICAL'!$O$6:$O$546,'BM MORRO DA CRUZ'!$K23),0) -> 0 | S23: =ROUND(R23*$P23,2) -> 0 | T23: =IFERROR(SUMIFS('BM MORRO DA CRUZ - VERTICAL'!X$6:X$546,'BM MORRO DA CRUZ - VERTICAL'!$O$6:$O$546,'BM MORRO DA CRUZ'!$K23),0) -> 0 | U23: =ROUND(T23*$P23,2) -> 0 | V23: =IFERROR(SUMIFS('BM MORRO DA CRUZ - VERTICAL'!Z$6:Z$546,'BM MORRO DA CRUZ - VERTICAL'!$O$6:$O$546,'BM MORRO DA CRUZ'!$K23),0) -> 0 | W23: =ROUND(V23*$P23,2) -> 0 | X23: =IFERROR(SUMIFS('BM MORRO DA CRUZ - VERTICAL'!AB$6:AB$546,'BM MORRO DA CRUZ - VERTICAL'!$O$6:$O$546,'BM MORRO DA CRUZ'!$K23),0) -> 0 | Y23: =ROUND(X23*$P23,2) -> 0 | Z23: =IFERROR(SUMIFS('BM MORRO DA CRUZ - VERTICAL'!AD$6:AD$546,'BM MORRO DA CRUZ - VERTICAL'!$O$6:$O$546,'BM MORRO DA CRUZ'!$K23),0) -> 0 | AA23: =ROUND(Z23*$P23,2) -> 0 | AB23: =IFERROR(SUMIFS('BM MORRO DA CRUZ - VERTICAL'!AF$6:AF$546,'BM MORRO DA CRUZ - VERTICAL'!$O$6:$O$546,'BM MORRO DA CRUZ'!$K23),0) -> 0 | AC23: =ROUND(AB23*$P23,2) -> 0 | AD23: =IFERROR(SUMIFS('BM MORRO DA CRUZ - VERTICAL'!AH$6:AH$546,'BM MORRO DA CRUZ - VERTICAL'!$O$6:$O$546,'BM MORRO DA CRUZ'!$K23),0) -> 0 | AE23: =ROUND(AD23*$P23,2) -> 0 | AF23: =IFERROR(SUMIFS('BM MORRO DA CRUZ - VERTICAL'!AJ$6:AJ$546,'BM MORRO DA CRUZ - VERTICAL'!$O$6:$O$546,'BM MORRO DA CRUZ'!$K23),0) -> 0 | AG23: =ROUND(AF23*$P23,2) -> 0 | AH23: =IFERROR(SUMIFS('BM MORRO DA CRUZ - VERTICAL'!AL$6:AL$546,'BM MORRO DA CRUZ - VERTICAL'!$O$6:$O$546,'BM MORRO DA CRUZ'!$K23),0) -> 0 | AI23: =ROUND(AH23*$P23,2) -> 0 | AJ23: =IFERROR(SUMIFS('BM MORRO DA CRUZ - VERTICAL'!AN$6:AN$546,'BM MORRO DA CRUZ - VERTICAL'!$O$6:$O$546,'BM MORRO DA CRUZ'!$K23),0) -> 0 | AK23: =ROUND(AJ23*$P23,2) -> 0 | AL23: =IFERROR(SUMIFS('BM MORRO DA CRUZ - VERTICAL'!AP$6:AP$546,'BM MORRO DA CRUZ - VERTICAL'!$O$6:$O$546,'BM MORRO DA CRUZ'!$K23),0) -> 0 | AM23: =ROUND(AL23*$P23,2) -> 0 | AN23: =IFERROR(SUMIFS('BM MORRO DA CRUZ - VERTICAL'!AR$6:AR$546,'BM MORRO DA CRUZ - VERTICAL'!$O$6:$O$546,'BM MORRO DA CRUZ'!$K23),0) -> 0 | AO23: =ROUND(AN23*$P23,2) -> 0 | AP23: =IFERROR(SUMIFS('BM MORRO DA CRUZ - VERTICAL'!AT$6:AT$546,'BM MORRO DA CRUZ - VERTICAL'!$O$6:$O$546,'BM MORRO DA CRUZ'!$K23),0) -> 0 | AQ23: =ROUND(AP23*$P23,2) -> 0 | AR23: =IFERROR(SUMIFS('BM MORRO DA CRUZ - VERTICAL'!AV$6:AV$546,'BM MORRO DA CRUZ - VERTICAL'!$O$6:$O$546,'BM MORRO DA CRUZ'!$K23),0) -> 0 | AS23: =ROUND(AR23*$P23,2) -> 0 | AT23: =IFERROR(SUMIFS('BM MORRO DA CRUZ - VERTICAL'!AX$6:AX$546,'BM MORRO DA CRUZ - VERTICAL'!$O$6:$O$546,'BM MORRO DA CRUZ'!$K23),0) -> 0 | AU23: =ROUND(AT23*$P23,2) -> 0 | AV23: =IFERROR(SUMIFS('BM MORRO DA CRUZ - VERTICAL'!AZ$6:AZ$546,'BM MORRO DA CRUZ - VERTICAL'!$O$6:$O$546,'BM MORRO DA CRUZ'!$K23),0) -> 0 | AW23: =ROUND(AV23*$P23,2) -> 0 | AX23: =IFERROR(SUMIFS('BM MORRO DA CRUZ - VERTICAL'!BB$6:BB$546,'BM MORRO DA CRUZ - VERTICAL'!$O$6:$O$546,'BM MORRO DA CRUZ'!$K23),0) -> 0 | AY23: =ROUND(AX23*$P23,2) -> 0 | AZ23: =IFERROR(SUMIFS('BM MORRO DA CRUZ - VERTICAL'!BD$6:BD$546,'BM MORRO DA CRUZ - VERTICAL'!$O$6:$O$546,'BM MORRO DA CRUZ'!$K23),0) -> 0 | BA23: =ROUND(AZ23*$P23,2) -> 0 | BB23: =IFERROR(SUMIFS($R23:$BA23,$R$5:$BA$5,$BB$5),0) -> 0 | BC23: =SUMIFS($R23:$BA23,$R$5:$BA$5,$S$5) -> 0 | BD23: =IFERROR(BB23/O23,0) -> 0 | BE23: =IFERROR((O23-BB23)/O23,0) -> 1
A24: 1.9 | K24: 15055 | M24: TAMPÕES E CAIXAS PARA MANUTENÇÃO DE REDES | Q24: =SUM(Q25:Q25) -> 53243.68 | S24: =SUM(S25:S25) -> 0 | U24: =SUM(U25:U25) -> 0 | W24: =SUM(W25:W25) -> 0 | Y24: =SUM(Y25:Y25) -> 0 | AA24: =SUM(AA25:AA25) -> 0 | AC24: =SUM(AC25:AC25) -> 0 | AE24: =SUM(AE25:AE25) -> 0 | AG24: =SUM(AG25:AG25) -> 0 | AI24: =SUM(AI25:AI25) -> 0 | AK24: =SUM(AK25:AK25) -> 0 | AM24: =SUM(AM25:AM25) -> 0 | AO24: =SUM(AO25:AO25) -> 0 | AQ24: =SUM(AQ25:AQ25) -> 0 | AS24: =SUM(AS25:AS25) -> 0 | AU24: =SUM(AU25:AU25) -> 0 | AW24: =SUM(AW25:AW25) -> 0 | AY24: =SUM(AY25:AY25) -> 0 | BA24: =SUM(BA25:BA25) -> 0 | BC24: =SUM(BC25:BC25) -> 0
A25: 1.9.1 | B25: TAMPA FºFº BIARTICULADA - T2RBI | C25: N/A | D25: N/A | E25: TAMPA BIARTICULADA | F25: N/A | G25: 1285X980 | H25: FºFº | I25: HIDROMECÂNICO | J25: TAMPÃO | K25: 1505503002016 | L25: MATERIAL | M25: TAMPA METÁLICA BIARTICULADA, FERRO FUNDIDO, MODELO T2RBI | N25: UN | O25: 28 | P25: 1901.56 | Q25: =ROUND(P25*$O25,2) -> 53243.68 | R25: =IFERROR(SUMIFS('BM MORRO DA CRUZ - VERTICAL'!V$6:V$546,'BM MORRO DA CRUZ - VERTICAL'!$O$6:$O$546,'BM MORRO DA CRUZ'!$K25),0) -> 0 | S25: =ROUND(R25*$P25,2) -> 0 | T25: =IFERROR(SUMIFS('BM MORRO DA CRUZ - VERTICAL'!X$6:X$546,'BM MORRO DA CRUZ - VERTICAL'!$O$6:$O$546,'BM MORRO DA CRUZ'!$K25),0) -> 0 | U25: =ROUND(T25*$P25,2) -> 0 | V25: =IFERROR(SUMIFS('BM MORRO DA CRUZ - VERTICAL'!Z$6:Z$546,'BM MORRO DA CRUZ - VERTICAL'!$O$6:$O$546,'BM MORRO DA CRUZ'!$K25),0) -> 0 | W25: =ROUND(V25*$P25,2) -> 0 | X25: =IFERROR(SUMIFS('BM MORRO DA CRUZ - VERTICAL'!AB$6:AB$546,'BM MORRO DA CRUZ - VERTICAL'!$O$6:$O$546,'BM MORRO DA CRUZ'!$K25),0) -> 0 | Y25: =ROUND(X25*$P25,2) -> 0 | Z25: =IFERROR(SUMIFS('BM MORRO DA CRUZ - VERTICAL'!AD$6:AD$546,'BM MORRO DA CRUZ - VERTICAL'!$O$6:$O$546,'BM MORRO DA CRUZ'!$K25),0) -> 0 | AA25: =ROUND(Z25*$P25,2) -> 0 | AB25: =IFERROR(SUMIFS('BM MORRO DA CRUZ - VERTICAL'!AF$6:AF$546,'BM MORRO DA CRUZ - VERTICAL'!$O$6:$O$546,'BM MORRO DA CRUZ'!$K25),0) -> 0 | AC25: =ROUND(AB25*$P25,2) -> 0 | AD25: =IFERROR(SUMIFS('BM MORRO DA CRUZ - VERTICAL'!AH$6:AH$546,'BM MORRO DA CRUZ - VERTICAL'!$O$6:$O$546,'BM MORRO DA CRUZ'!$K25),0) -> 0 | AE25: =ROUND(AD25*$P25,2) -> 0 | AF25: =IFERROR(SUMIFS('BM MORRO DA CRUZ - VERTICAL'!AJ$6:AJ$546,'BM MORRO DA CRUZ - VERTICAL'!$O$6:$O$546,'BM MORRO DA CRUZ'!$K25),0) -> 0 | AG25: =ROUND(AF25*$P25,2) -> 0 | AH25: =IFERROR(SUMIFS('BM MORRO DA CRUZ - VERTICAL'!AL$6:AL$546,'BM MORRO DA CRUZ - VERTICAL'!$O$6:$O$546,'BM MORRO DA CRUZ'!$K25),0) -> 0 | AI25: =ROUND(AH25*$P25,2) -> 0 | AJ25: =IFERROR(SUMIFS('BM MORRO DA CRUZ - VERTICAL'!AN$6:AN$546,'BM MORRO DA CRUZ - VERTICAL'!$O$6:$O$546,'BM MORRO DA CRUZ'!$K25),0) -> 0 | AK25: =ROUND(AJ25*$P25,2) -> 0 | AL25: =IFERROR(SUMIFS('BM MORRO DA CRUZ - VERTICAL'!AP$6:AP$546,'BM MORRO DA CRUZ - VERTICAL'!$O$6:$O$546,'BM MORRO DA CRUZ'!$K25),0) -> 0 | AM25: =ROUND(AL25*$P25,2) -> 0 | AN25: =IFERROR(SUMIFS('BM MORRO DA CRUZ - VERTICAL'!AR$6:AR$546,'BM MORRO DA CRUZ - VERTICAL'!$O$6:$O$546,'BM MORRO DA CRUZ'!$K25),0) -> 0 | AO25: =ROUND(AN25*$P25,2) -> 0 | AP25: =IFERROR(SUMIFS('BM MORRO DA CRUZ - VERTICAL'!AT$6:AT$546,'BM MORRO DA CRUZ - VERTICAL'!$O$6:$O$546,'BM MORRO DA CRUZ'!$K25),0) -> 0 | AQ25: =ROUND(AP25*$P25,2) -> 0 | AR25: =IFERROR(SUMIFS('BM MORRO DA CRUZ - VERTICAL'!AV$6:AV$546,'BM MORRO DA CRUZ - VERTICAL'!$O$6:$O$546,'BM MORRO DA CRUZ'!$K25),0) -> 0 | AS25: =ROUND(AR25*$P25,2) -> 0 | AT25: =IFERROR(SUMIFS('BM MORRO DA CRUZ - VERTICAL'!AX$6:AX$546,'BM MORRO DA CRUZ - VERTICAL'!$O$6:$O$546,'BM MORRO DA CRUZ'!$K25),0) -> 0 | AU25: =ROUND(AT25*$P25,2) -> 0 | AV25: =IFERROR(SUMIFS('BM MORRO DA CRUZ - VERTICAL'!AZ$6:AZ$546,'BM MORRO DA CRUZ - VERTICAL'!$O$6:$O$546,'BM MORRO DA CRUZ'!$K25),0) -> 0 | AW25: =ROUND(AV25*$P25,2) -> 0 | AX25: =IFERROR(SUMIFS('BM MORRO DA CRUZ - VERTICAL'!BB$6:BB$546,'BM MORRO DA CRUZ - VERTICAL'!$O$6:$O$546,'BM MORRO DA CRUZ'!$K25),0) -> 0 | AY25: =ROUND(AX25*$P25,2) -> 0 | AZ25: =IFERROR(SUMIFS('BM MORRO DA CRUZ - VERTICAL'!BD$6:BD$546,'BM MORRO DA CRUZ - VERTICAL'!$O$6:$O$546,'BM MORRO DA CRUZ'!$K25),0) -> 0 | BA25: =ROUND(AZ25*$P25,2) -> 0 | BB25: =IFERROR(SUMIFS($R25:$BA25,$R$5:$BA$5,$BB$5),0) -> 0 | BC25: =SUMIFS($R25:$BA25,$R$5:$BA$5,$S$5) -> 0 | BD25: =IFERROR(BB25/O25,0) -> 0 | BE25: =IFERROR((O25-BB25)/O25,0) -> 1
A26: 1.10 | K26: 15110 | M26: REGISTROS, VÁLVULAS E ACESSÓRIOS | Q26: =SUM(Q27:Q44) -> 446602.52 | S26: =SUM(S27:S44) -> 0 | U26: =SUM(U27:U44) -> 0 | W26: =SUM(W27:W44) -> 0 | Y26: =SUM(Y27:Y44) -> 0 | AA26: =SUM(AA27:AA44) -> 0 | AC26: =SUM(AC27:AC44) -> 0 | AE26: =SUM(AE27:AE44) -> 0 | AG26: =SUM(AG27:AG44) -> 0 | AI26: =SUM(AI27:AI44) -> 0 | AK26: =SUM(AK27:AK44) -> 0 | AM26: =SUM(AM27:AM44) -> 0 | AO26: =SUM(AO27:AO44) -> 0 | AQ26: =SUM(AQ27:AQ44) -> 0 | AS26: =SUM(AS27:AS44) -> 0 | AU26: =SUM(AU27:AU44) -> 0 | AW26: =SUM(AW27:AW44) -> 0 | AY26: =SUM(AY27:AY44) -> 0 | BA26: =SUM(BA27:BA44) -> 0 | BC26: =SUM(BC27:BC44) -> 0
A27: 1.10.1 | B27: TAMPA P/ ACIONAMENTO DE REGISTRO | C27: N/A | D27: N/A | E27: TAMPA ACIONAMENTO | F27: N/A | G27: 100 | H27: FºFº | I27: HIDROMECÂNICO | J27: TAMPÃO | K27: 1511003106005 | L27: MATERIAL | M27: TAMPA PARA ACIONAMENTO DE REGISTRO DE FERRO FUNDIDO (DIÂMETRO: 100 MM) | N27: UN | O27: 6 | P27: 189.06 | Q27: =ROUND(P27*$O27,2) -> 1134.36 | R27: =IFERROR(SUMIFS('BM MORRO DA CRUZ - VERTICAL'!V$6:V$546,'BM MORRO DA CRUZ - VERTICAL'!$O$6:$O$546,'BM MORRO DA CRUZ'!$K27),0) -> 0 | S27: =ROUND(R27*$P27,2) -> 0 | T27: =IFERROR(SUMIFS('BM MORRO DA CRUZ - VERTICAL'!X$6:X$546,'BM MORRO DA CRUZ - VERTICAL'!$O$6:$O$546,'BM MORRO DA CRUZ'!$K27),0) -> 0 | U27: =ROUND(T27*$P27,2) -> 0 | V27: =IFERROR(SUMIFS('BM MORRO DA CRUZ - VERTICAL'!Z$6:Z$546,'BM MORRO DA CRUZ - VERTICAL'!$O$6:$O$546,'BM MORRO DA CRUZ'!$K27),0) -> 0 | W27: =ROUND(V27*$P27,2) -> 0 | X27: =IFERROR(SUMIFS('BM MORRO DA CRUZ - VERTICAL'!AB$6:AB$546,'BM MORRO DA CRUZ - VERTICAL'!$O$6:$O$546,'BM MORRO DA CRUZ'!$K27),0) -> 0 | Y27: =ROUND(X27*$P27,2) -> 0 | Z27: =IFERROR(SUMIFS('BM MORRO DA CRUZ - VERTICAL'!AD$6:AD$546,'BM MORRO DA CRUZ - VERTICAL'!$O$6:$O$546,'BM MORRO DA CRUZ'!$K27),0) -> 0 | AA27: =ROUND(Z27*$P27,2) -> 0 | AB27: =IFERROR(SUMIFS('BM MORRO DA CRUZ - VERTICAL'!AF$6:AF$546,'BM MORRO DA CRUZ - VERTICAL'!$O$6:$O$546,'BM MORRO DA CRUZ'!$K27),0) -> 0 | AC27: =ROUND(AB27*$P27,2) -> 0 | AD27: =IFERROR(SUMIFS('BM MORRO DA CRUZ - VERTICAL'!AH$6:AH$546,'BM MORRO DA CRUZ - VERTICAL'!$O$6:$O$546,'BM MORRO DA CRUZ'!$K27),0) -> 0 | AE27: =ROUND(AD27*$P27,2) -> 0 | AF27: =IFERROR(SUMIFS('BM MORRO DA CRUZ - VERTICAL'!AJ$6:AJ$546,'BM MORRO DA CRUZ - VERTICAL'!$O$6:$O$546,'BM MORRO DA CRUZ'!$K27),0) -> 0 | AG27: =ROUND(AF27*$P27,2) -> 0 | AH27: =IFERROR(SUMIFS('BM MORRO DA CRUZ - VERTICAL'!AL$6:AL$546,'BM MORRO DA CRUZ - VERTICAL'!$O$6:$O$546,'BM MORRO DA CRUZ'!$K27),0) -> 0 | AI27: =ROUND(AH27*$P27,2) -> 0 | AJ27: =IFERROR(SUMIFS('BM MORRO DA CRUZ - VERTICAL'!AN$6:AN$546,'BM MORRO DA CRUZ - VERTICAL'!$O$6:$O$546,'BM MORRO DA CRUZ'!$K27),0) -> 0 | AK27: =ROUND(AJ27*$P27,2) -> 0 | AL27: =IFERROR(SUMIFS('BM MORRO DA CRUZ - VERTICAL'!AP$6:AP$546,'BM MORRO DA CRUZ - VERTICAL'!$O$6:$O$546,'BM MORRO DA CRUZ'!$K27),0) -> 0 | AM27: =ROUND(AL27*$P27,2) -> 0 | AN27: =IFERROR(SUMIFS('BM MORRO DA CRUZ - VERTICAL'!AR$6:AR$546,'BM MORRO DA CRUZ - VERTICAL'!$O$6:$O$546,'BM MORRO DA CRUZ'!$K27),0) -> 0 | AO27: =ROUND(AN27*$P27,2) -> 0 | AP27: =IFERROR(SUMIFS('BM MORRO DA CRUZ - VERTICAL'!AT$6:AT$546,'BM MORRO DA CRUZ - VERTICAL'!$O$6:$O$546,'BM MORRO DA CRUZ'!$K27),0) -> 0 | AQ27: =ROUND(AP27*$P27,2) -> 0 | AR27: =IFERROR(SUMIFS('BM MORRO DA CRUZ - VERTICAL'!AV$6:AV$546,'BM MORRO DA CRUZ - VERTICAL'!$O$6:$O$546,'BM MORRO DA CRUZ'!$K27),0) -> 0 | AS27: =ROUND(AR27*$P27,2) -> 0 | AT27: =IFERROR(SUMIFS('BM MORRO DA CRUZ - VERTICAL'!AX$6:AX$546,'BM MORRO DA CRUZ - VERTICAL'!$O$6:$O$546,'BM MORRO DA CRUZ'!$K27),0) -> 0 | AU27: =ROUND(AT27*$P27,2) -> 0 | AV27: =IFERROR(SUMIFS('BM MORRO DA CRUZ - VERTICAL'!AZ$6:AZ$546,'BM MORRO DA CRUZ - VERTICAL'!$O$6:$O$546,'BM MORRO DA CRUZ'!$K27),0) -> 0 | AW27: =ROUND(AV27*$P27,2) -> 0 | AX27: =IFERROR(SUMIFS('BM MORRO DA CRUZ - VERTICAL'!BB$6:BB$546,'BM MORRO DA CRUZ - VERTICAL'!$O$6:$O$546,'BM MORRO DA CRUZ'!$K27),0) -> 0 | AY27: =ROUND(AX27*$P27,2) -> 0 | AZ27: =IFERROR(SUMIFS('BM MORRO DA CRUZ - VERTICAL'!BD$6:BD$546,'BM MORRO DA CRUZ - VERTICAL'!$O$6:$O$546,'BM MORRO DA CRUZ'!$K27),0) -> 0 | BA27: =ROUND(AZ27*$P27,2) -> 0 | BB27: =IFERROR(SUMIFS($R27:$BA27,$R$5:$BA$5,$BB$5),0) -> 0 | BC27: =SUMIFS($R27:$BA27,$R$5:$BA$5,$S$5) -> 0 | BD27: =IFERROR(BB27/O27,0) -> 0 | BE27: =IFERROR((O27-BB27)/O27,0) -> 1
A28: 1.10.2 | B28: VÁLVULA BORBOLETA FF CC - ACIONAMENTO CABEÇOTE | C28: PN10 | D28: N/A | E28: VÁLVULA BORBOLETA | F28: N/A | G28: 200 | H28: FºFº | I28: HIDROMECÂNICO | J28: VÁLVULA | K28: 1511003139041 | L28: MATERIAL | M28: VÁLVULA BORBOLETA FLANGEADA DE FERRO FUNDIDO DÚCTIL COM CORPO CURTO, MECANISMO DE REDUÇÃO TIPO C E ACIONAMENTO COM CABEÇOTE (CLASSE DE PRESSÃO: 10 KGF/CM² / DIÂMETRO DA SEÇÃO: 200 MM) | N28: UN | O28: 4 | P28: 17589.88 | Q28: =ROUND(P28*$O28,2) -> 70359.52 | R28: =IFERROR(SUMIFS('BM MORRO DA CRUZ - VERTICAL'!V$6:V$546,'BM MORRO DA CRUZ - VERTICAL'!$O$6:$O$546,'BM MORRO DA CRUZ'!$K28),0) -> 0 | S28: =ROUND(R28*$P28,2) -> 0 | T28: =IFERROR(SUMIFS('BM MORRO DA CRUZ - VERTICAL'!X$6:X$546,'BM MORRO DA CRUZ - VERTICAL'!$O$6:$O$546,'BM MORRO DA CRUZ'!$K28),0) -> 0 | U28: =ROUND(T28*$P28,2) -> 0 | V28: =IFERROR(SUMIFS('BM MORRO DA CRUZ - VERTICAL'!Z$6:Z$546,'BM MORRO DA CRUZ - VERTICAL'!$O$6:$O$546,'BM MORRO DA CRUZ'!$K28),0) -> 0 | W28: =ROUND(V28*$P28,2) -> 0 | X28: =IFERROR(SUMIFS('BM MORRO DA CRUZ - VERTICAL'!AB$6:AB$546,'BM MORRO DA CRUZ - VERTICAL'!$O$6:$O$546,'BM MORRO DA CRUZ'!$K28),0) -> 0 | Y28: =ROUND(X28*$P28,2) -> 0 | Z28: =IFERROR(SUMIFS('BM MORRO DA CRUZ - VERTICAL'!AD$6:AD$546,'BM MORRO DA CRUZ - VERTICAL'!$O$6:$O$546,'BM MORRO DA CRUZ'!$K28),0) -> 0 | AA28: =ROUND(Z28*$P28,2) -> 0 | AB28: =IFERROR(SUMIFS('BM MORRO DA CRUZ - VERTICAL'!AF$6:AF$546,'BM MORRO DA CRUZ - VERTICAL'!$O$6:$O$546,'BM MORRO DA CRUZ'!$K28),0) -> 0 | AC28: =ROUND(AB28*$P28,2) -> 0 | AD28: =IFERROR(SUMIFS('BM MORRO DA CRUZ - VERTICAL'!AH$6:AH$546,'BM MORRO DA CRUZ - VERTICAL'!$O$6:$O$546,'BM MORRO DA CRUZ'!$K28),0) -> 0 | AE28: =ROUND(AD28*$P28,2) -> 0 | AF28: =IFERROR(SUMIFS('BM MORRO DA CRUZ - VERTICAL'!AJ$6:AJ$546,'BM MORRO DA CRUZ - VERTICAL'!$O$6:$O$546,'BM MORRO DA CRUZ'!$K28),0) -> 0 | AG28: =ROUND(AF28*$P28,2) -> 0 | AH28: =IFERROR(SUMIFS('BM MORRO DA CRUZ - VERTICAL'!AL$6:AL$546,'BM MORRO DA CRUZ - VERTICAL'!$O$6:$O$546,'BM MORRO DA CRUZ'!$K28),0) -> 0 | AI28: =ROUND(AH28*$P28,2) -> 0 | AJ28: =IFERROR(SUMIFS('BM MORRO DA CRUZ - VERTICAL'!AN$6:AN$546,'BM MORRO DA CRUZ - VERTICAL'!$O$6:$O$546,'BM MORRO DA CRUZ'!$K28),0) -> 0 | AK28: =ROUND(AJ28*$P28,2) -> 0 | AL28: =IFERROR(SUMIFS('BM MORRO DA CRUZ - VERTICAL'!AP$6:AP$546,'BM MORRO DA CRUZ - VERTICAL'!$O$6:$O$546,'BM MORRO DA CRUZ'!$K28),0) -> 0 | AM28: =ROUND(AL28*$P28,2) -> 0 | AN28: =IFERROR(SUMIFS('BM MORRO DA CRUZ - VERTICAL'!AR$6:AR$546,'BM MORRO DA CRUZ - VERTICAL'!$O$6:$O$546,'BM MORRO DA CRUZ'!$K28),0) -> 0 | AO28: =ROUND(AN28*$P28,2) -> 0 | AP28: =IFERROR(SUMIFS('BM MORRO DA CRUZ - VERTICAL'!AT$6:AT$546,'BM MORRO DA CRUZ - VERTICAL'!$O$6:$O$546,'BM MORRO DA CRUZ'!$K28),0) -> 0 | AQ28: =ROUND(AP28*$P28,2) -> 0 | AR28: =IFERROR(SUMIFS('BM MORRO DA CRUZ - VERTICAL'!AV$6:AV$546,'BM MORRO DA CRUZ - VERTICAL'!$O$6:$O$546,'BM MORRO DA CRUZ'!$K28),0) -> 0 | AS28: =ROUND(AR28*$P28,2) -> 0 | AT28: =IFERROR(SUMIFS('BM MORRO DA CRUZ - VERTICAL'!AX$6:AX$546,'BM MORRO DA CRUZ - VERTICAL'!$O$6:$O$546,'BM MORRO DA CRUZ'!$K28),0) -> 0 | AU28: =ROUND(AT28*$P28,2) -> 0 | AV28: =IFERROR(SUMIFS('BM MORRO DA CRUZ - VERTICAL'!AZ$6:AZ$546,'BM MORRO DA CRUZ - VERTICAL'!$O$6:$O$546,'BM MORRO DA CRUZ'!$K28),0) -> 0 | AW28: =ROUND(AV28*$P28,2) -> 0 | AX28: =IFERROR(SUMIFS('BM MORRO DA CRUZ - VERTICAL'!BB$6:BB$546,'BM MORRO DA CRUZ - VERTICAL'!$O$6:$O$546,'BM MORRO DA CRUZ'!$K28),0) -> 0 | AY28: =ROUND(AX28*$P28,2) -> 0 | AZ28: =IFERROR(SUMIFS('BM MORRO DA CRUZ - VERTICAL'!BD$6:BD$546,'BM MORRO DA CRUZ - VERTICAL'!$O$6:$O$546,'BM MORRO DA CRUZ'!$K28),0) -> 0 | BA28: =ROUND(AZ28*$P28,2) -> 0 | BB28: =IFERROR(SUMIFS($R28:$BA28,$R$5:$BA$5,$BB$5),0) -> 0 | BC28: =SUMIFS($R28:$BA28,$R$5:$BA$5,$S$5) -> 0 | BD28: =IFERROR(BB28/O28,0) -> 0 | BE28: =IFERROR((O28-BB28)/O28,0) -> 1
A29: 1.10.3 | B29: VÁLVULA BORBOLETA FF CC - ACIONAMENTO CABEÇOTE | C29: PN10 | D29: N/A | E29: VÁLVULA BORBOLETA | F29: N/A | G29: 350 | H29: FºFº | I29: HIDROMECÂNICO | J29: VÁLVULA | K29: 1511003139044 | L29: MATERIAL | M29: VÁLVULA BORBOLETA FLANGEADA DE FERRO FUNDIDO DÚCTIL COM CORPO CURTO, MECANISMO DE REDUÇÃO TIPO C E ACIONAMENTO COM CABEÇOTE (CLASSE DE PRESSÃO: 10 KGF/CM² / DIÂMETRO DA SEÇÃO: 350 MM) | N29: UN | O29: 2 | P29: 23595.41 | Q29: =ROUND(P29*$O29,2) -> 47190.82 | R29: =IFERROR(SUMIFS('BM MORRO DA CRUZ - VERTICAL'!V$6:V$546,'BM MORRO DA CRUZ - VERTICAL'!$O$6:$O$546,'BM MORRO DA CRUZ'!$K29),0) -> 0 | S29: =ROUND(R29*$P29,2) -> 0 | T29: =IFERROR(SUMIFS('BM MORRO DA CRUZ - VERTICAL'!X$6:X$546,'BM MORRO DA CRUZ - VERTICAL'!$O$6:$O$546,'BM MORRO DA CRUZ'!$K29),0) -> 0 | U29: =ROUND(T29*$P29,2) -> 0 | V29: =IFERROR(SUMIFS('BM MORRO DA CRUZ - VERTICAL'!Z$6:Z$546,'BM MORRO DA CRUZ - VERTICAL'!$O$6:$O$546,'BM MORRO DA CRUZ'!$K29),0) -> 0 | W29: =ROUND(V29*$P29,2) -> 0 | X29: =IFERROR(SUMIFS('BM MORRO DA CRUZ - VERTICAL'!AB$6:AB$546,'BM MORRO DA CRUZ - VERTICAL'!$O$6:$O$546,'BM MORRO DA CRUZ'!$K29),0) -> 0 | Y29: =ROUND(X29*$P29,2) -> 0 | Z29: =IFERROR(SUMIFS('BM MORRO DA CRUZ - VERTICAL'!AD$6:AD$546,'BM MORRO DA CRUZ - VERTICAL'!$O$6:$O$546,'BM MORRO DA CRUZ'!$K29),0) -> 0 | AA29: =ROUND(Z29*$P29,2) -> 0 | AB29: =IFERROR(SUMIFS('BM MORRO DA CRUZ - VERTICAL'!AF$6:AF$546,'BM MORRO DA CRUZ - VERTICAL'!$O$6:$O$546,'BM MORRO DA CRUZ'!$K29),0) -> 0 | AC29: =ROUND(AB29*$P29,2) -> 0 | AD29: =IFERROR(SUMIFS('BM MORRO DA CRUZ - VERTICAL'!AH$6:AH$546,'BM MORRO DA CRUZ - VERTICAL'!$O$6:$O$546,'BM MORRO DA CRUZ'!$K29),0) -> 0 | AE29: =ROUND(AD29*$P29,2) -> 0 | AF29: =IFERROR(SUMIFS('BM MORRO DA CRUZ - VERTICAL'!AJ$6:AJ$546,'BM MORRO DA CRUZ - VERTICAL'!$O$6:$O$546,'BM MORRO DA CRUZ'!$K29),0) -> 0 | AG29: =ROUND(AF29*$P29,2) -> 0 | AH29: =IFERROR(SUMIFS('BM MORRO DA CRUZ - VERTICAL'!AL$6:AL$546,'BM MORRO DA CRUZ - VERTICAL'!$O$6:$O$546,'BM MORRO DA CRUZ'!$K29),0) -> 0 | AI29: =ROUND(AH29*$P29,2) -> 0 | AJ29: =IFERROR(SUMIFS('BM MORRO DA CRUZ - VERTICAL'!AN$6:AN$546,'BM MORRO DA CRUZ - VERTICAL'!$O$6:$O$546,'BM MORRO DA CRUZ'!$K29),0) -> 0 | AK29: =ROUND(AJ29*$P29,2) -> 0 | AL29: =IFERROR(SUMIFS('BM MORRO DA CRUZ - VERTICAL'!AP$6:AP$546,'BM MORRO DA CRUZ - VERTICAL'!$O$6:$O$546,'BM MORRO DA CRUZ'!$K29),0) -> 0 | AM29: =ROUND(AL29*$P29,2) -> 0 | AN29: =IFERROR(SUMIFS('BM MORRO DA CRUZ - VERTICAL'!AR$6:AR$546,'BM MORRO DA CRUZ - VERTICAL'!$O$6:$O$546,'BM MORRO DA CRUZ'!$K29),0) -> 0 | AO29: =ROUND(AN29*$P29,2) -> 0 | AP29: =IFERROR(SUMIFS('BM MORRO DA CRUZ - VERTICAL'!AT$6:AT$546,'BM MORRO DA CRUZ - VERTICAL'!$O$6:$O$546,'BM MORRO DA CRUZ'!$K29),0) -> 0 | AQ29: =ROUND(AP29*$P29,2) -> 0 | AR29: =IFERROR(SUMIFS('BM MORRO DA CRUZ - VERTICAL'!AV$6:AV$546,'BM MORRO DA CRUZ - VERTICAL'!$O$6:$O$546,'BM MORRO DA CRUZ'!$K29),0) -> 0 | AS29: =ROUND(AR29*$P29,2) -> 0 | AT29: =IFERROR(SUMIFS('BM MORRO DA CRUZ - VERTICAL'!AX$6:AX$546,'BM MORRO DA CRUZ - VERTICAL'!$O$6:$O$546,'BM MORRO DA CRUZ'!$K29),0) -> 0 | AU29: =ROUND(AT29*$P29,2) -> 0 | AV29: =IFERROR(SUMIFS('BM MORRO DA CRUZ - VERTICAL'!AZ$6:AZ$546,'BM MORRO DA CRUZ - VERTICAL'!$O$6:$O$546,'BM MORRO DA CRUZ'!$K29),0) -> 0 | AW29: =ROUND(AV29*$P29,2) -> 0 | AX29: =IFERROR(SUMIFS('BM MORRO DA CRUZ - VERTICAL'!BB$6:BB$546,'BM MORRO DA CRUZ - VERTICAL'!$O$6:$O$546,'BM MORRO DA CRUZ'!$K29),0) -> 0 | AY29: =ROUND(AX29*$P29,2) -> 0 | AZ29: =IFERROR(SUMIFS('BM MORRO DA CRUZ - VERTICAL'!BD$6:BD$546,'BM MORRO DA CRUZ - VERTICAL'!$O$6:$O$546,'BM MORRO DA CRUZ'!$K29),0) -> 0 | BA29: =ROUND(AZ29*$P29,2) -> 0 | BB29: =IFERROR(SUMIFS($R29:$BA29,$R$5:$BA$5,$BB$5),0) -> 0 | BC29: =SUMIFS($R29:$BA29,$R$5:$BA$5,$S$5) -> 0 | BD29: =IFERROR(BB29/O29,0) -> 0 | BE29: =IFERROR((O29-BB29)/O29,0) -> 1
A30: 1.10.4 | B30: VÁLVULA BORBOLETA FF CC - ACIONAMENTO CABEÇOTE | C30: PN10/16 | D30: N/A | E30: VÁLVULA BORBOLETA | F30: N/A | G30: 100 | H30: FºFº | I30: HIDROMECÂNICO | J30: VÁLVULA | K30: 1511003139037 | L30: MATERIAL | M30: VÁLVULA BORBOLETA FLANGEADA DE FERRO FUNDIDO DÚCTIL COM CORPO CURTO, MECANISMO DE REDUÇÃO TIPO C E ACIONAMENTO COM CABEÇOTE (CLASSE DE PRESSÃO: 10/16 KGF/CM² / DIÂMETRO DA SEÇÃO: 100 MM) | N30: UN | O30: 2 | P30: 15871.73 | Q30: =ROUND(P30*$O30,2) -> 31743.46 | R30: =IFERROR(SUMIFS('BM MORRO DA CRUZ - VERTICAL'!V$6:V$546,'BM MORRO DA CRUZ - VERTICAL'!$O$6:$O$546,'BM MORRO DA CRUZ'!$K30),0) -> 0 | S30: =ROUND(R30*$P30,2) -> 0 | T30: =IFERROR(SUMIFS('BM MORRO DA CRUZ - VERTICAL'!X$6:X$546,'BM MORRO DA CRUZ - VERTICAL'!$O$6:$O$546,'BM MORRO DA CRUZ'!$K30),0) -> 0 | U30: =ROUND(T30*$P30,2) -> 0 | V30: =IFERROR(SUMIFS('BM MORRO DA CRUZ - VERTICAL'!Z$6:Z$546,'BM MORRO DA CRUZ - VERTICAL'!$O$6:$O$546,'BM MORRO DA CRUZ'!$K30),0) -> 0 | W30: =ROUND(V30*$P30,2) -> 0 | X30: =IFERROR(SUMIFS('BM MORRO DA CRUZ - VERTICAL'!AB$6:AB$546,'BM MORRO DA CRUZ - VERTICAL'!$O$6:$O$546,'BM MORRO DA CRUZ'!$K30),0) -> 0 | Y30: =ROUND(X30*$P30,2) -> 0 | Z30: =IFERROR(SUMIFS('BM MORRO DA CRUZ - VERTICAL'!AD$6:AD$546,'BM MORRO DA CRUZ - VERTICAL'!$O$6:$O$546,'BM MORRO DA CRUZ'!$K30),0) -> 0 | AA30: =ROUND(Z30*$P30,2) -> 0 | AB30: =IFERROR(SUMIFS('BM MORRO DA CRUZ - VERTICAL'!AF$6:AF$546,'BM MORRO DA CRUZ - VERTICAL'!$O$6:$O$546,'BM MORRO DA CRUZ'!$K30),0) -> 0 | AC30: =ROUND(AB30*$P30,2) -> 0 | AD30: =IFERROR(SUMIFS('BM MORRO DA CRUZ - VERTICAL'!AH$6:AH$546,'BM MORRO DA CRUZ - VERTICAL'!$O$6:$O$546,'BM MORRO DA CRUZ'!$K30),0) -> 0 | AE30: =ROUND(AD30*$P30,2) -> 0 | AF30: =IFERROR(SUMIFS('BM MORRO DA CRUZ - VERTICAL'!AJ$6:AJ$546,'BM MORRO DA CRUZ - VERTICAL'!$O$6:$O$546,'BM MORRO DA CRUZ'!$K30),0) -> 0 | AG30: =ROUND(AF30*$P30,2) -> 0 | AH30: =IFERROR(SUMIFS('BM MORRO DA CRUZ - VERTICAL'!AL$6:AL$546,'BM MORRO DA CRUZ - VERTICAL'!$O$6:$O$546,'BM MORRO DA CRUZ'!$K30),0) -> 0 | AI30: =ROUND(AH30*$P30,2) -> 0 | AJ30: =IFERROR(SUMIFS('BM MORRO DA CRUZ - VERTICAL'!AN$6:AN$546,'BM MORRO DA CRUZ - VERTICAL'!$O$6:$O$546,'BM MORRO DA CRUZ'!$K30),0) -> 0 | AK30: =ROUND(AJ30*$P30,2) -> 0 | AL30: =IFERROR(SUMIFS('BM MORRO DA CRUZ - VERTICAL'!AP$6:AP$546,'BM MORRO DA CRUZ - VERTICAL'!$O$6:$O$546,'BM MORRO DA CRUZ'!$K30),0) -> 0 | AM30: =ROUND(AL30*$P30,2) -> 0 | AN30: =IFERROR(SUMIFS('BM MORRO DA CRUZ - VERTICAL'!AR$6:AR$546,'BM MORRO DA CRUZ - VERTICAL'!$O$6:$O$546,'BM MORRO DA CRUZ'!$K30),0) -> 0 | AO30: =ROUND(AN30*$P30,2) -> 0 | AP30: =IFERROR(SUMIFS('BM MORRO DA CRUZ - VERTICAL'!AT$6:AT$546,'BM MORRO DA CRUZ - VERTICAL'!$O$6:$O$546,'BM MORRO DA CRUZ'!$K30),0) -> 0 | AQ30: =ROUND(AP30*$P30,2) -> 0 | AR30: =IFERROR(SUMIFS('BM MORRO DA CRUZ - VERTICAL'!AV$6:AV$546,'BM MORRO DA CRUZ - VERTICAL'!$O$6:$O$546,'BM MORRO DA CRUZ'!$K30),0) -> 0 | AS30: =ROUND(AR30*$P30,2) -> 0 | AT30: =IFERROR(SUMIFS('BM MORRO DA CRUZ - VERTICAL'!AX$6:AX$546,'BM MORRO DA CRUZ - VERTICAL'!$O$6:$O$546,'BM MORRO DA CRUZ'!$K30),0) -> 0 | AU30: =ROUND(AT30*$P30,2) -> 0 | AV30: =IFERROR(SUMIFS('BM MORRO DA CRUZ - VERTICAL'!AZ$6:AZ$546,'BM MORRO DA CRUZ - VERTICAL'!$O$6:$O$546,'BM MORRO DA CRUZ'!$K30),0) -> 0 | AW30: =ROUND(AV30*$P30,2) -> 0 | AX30: =IFERROR(SUMIFS('BM MORRO DA CRUZ - VERTICAL'!BB$6:BB$546,'BM MORRO DA CRUZ - VERTICAL'!$O$6:$O$546,'BM MORRO DA CRUZ'!$K30),0) -> 0 | AY30: =ROUND(AX30*$P30,2) -> 0 | AZ30: =IFERROR(SUMIFS('BM MORRO DA CRUZ - VERTICAL'!BD$6:BD$546,'BM MORRO DA CRUZ - VERTICAL'!$O$6:$O$546,'BM MORRO DA CRUZ'!$K30),0) -> 0 | BA30: =ROUND(AZ30*$P30,2) -> 0 | BB30: =IFERROR(SUMIFS($R30:$BA30,$R$5:$BA$5,$BB$5),0) -> 0 | BC30: =SUMIFS($R30:$BA30,$R$5:$BA$5,$S$5) -> 0 | BD30: =IFERROR(BB30/O30,0) -> 0 | BE30: =IFERROR((O30-BB30)/O30,0) -> 1
A31: 1.10.5 | B31: VÁLVULA BORBOLETA FF CC - ACIONAMENTO CABEÇOTE | C31: PN10/16 | D31: N/A | E31: VÁLVULA BORBOLETA | F31: N/A | G31: 150 | H31: FºFº | I31: HIDROMECÂNICO | J31: VÁLVULA | K31: 1511003139038 | L31: MATERIAL | M31: VÁLVULA BORBOLETA FLANGEADA DE FERRO FUNDIDO DÚCTIL COM CORPO CURTO, MECANISMO DE REDUÇÃO TIPO C E ACIONAMENTO COM CABEÇOTE (CLASSE DE PRESSÃO: 10/16 KGF/CM² / DIÂMETRO DA SEÇÃO: 150 MM) | N31: UN | O31: 4 | P31: 16664.81 | Q31: =ROUND(P31*$O31,2) -> 66659.24 | R31: =IFERROR(SUMIFS('BM MORRO DA CRUZ - VERTICAL'!V$6:V$546,'BM MORRO DA CRUZ - VERTICAL'!$O$6:$O$546,'BM MORRO DA CRUZ'!$K31),0) -> 0 | S31: =ROUND(R31*$P31,2) -> 0 | T31: =IFERROR(SUMIFS('BM MORRO DA CRUZ - VERTICAL'!X$6:X$546,'BM MORRO DA CRUZ - VERTICAL'!$O$6:$O$546,'BM MORRO DA CRUZ'!$K31),0) -> 0 | U31: =ROUND(T31*$P31,2) -> 0 | V31: =IFERROR(SUMIFS('BM MORRO DA CRUZ - VERTICAL'!Z$6:Z$546,'BM MORRO DA CRUZ - VERTICAL'!$O$6:$O$546,'BM MORRO DA CRUZ'!$K31),0) -> 0 | W31: =ROUND(V31*$P31,2) -> 0 | X31: =IFERROR(SUMIFS('BM MORRO DA CRUZ - VERTICAL'!AB$6:AB$546,'BM MORRO DA CRUZ - VERTICAL'!$O$6:$O$546,'BM MORRO DA CRUZ'!$K31),0) -> 0 | Y31: =ROUND(X31*$P31,2) -> 0 | Z31: =IFERROR(SUMIFS('BM MORRO DA CRUZ - VERTICAL'!AD$6:AD$546,'BM MORRO DA CRUZ - VERTICAL'!$O$6:$O$546,'BM MORRO DA CRUZ'!$K31),0) -> 0 | AA31: =ROUND(Z31*$P31,2) -> 0 | AB31: =IFERROR(SUMIFS('BM MORRO DA CRUZ - VERTICAL'!AF$6:AF$546,'BM MORRO DA CRUZ - VERTICAL'!$O$6:$O$546,'BM MORRO DA CRUZ'!$K31),0) -> 0 | AC31: =ROUND(AB31*$P31,2) -> 0 | AD31: =IFERROR(SUMIFS('BM MORRO DA CRUZ - VERTICAL'!AH$6:AH$546,'BM MORRO DA CRUZ - VERTICAL'!$O$6:$O$546,'BM MORRO DA CRUZ'!$K31),0) -> 0 | AE31: =ROUND(AD31*$P31,2) -> 0 | AF31: =IFERROR(SUMIFS('BM MORRO DA CRUZ - VERTICAL'!AJ$6:AJ$546,'BM MORRO DA CRUZ - VERTICAL'!$O$6:$O$546,'BM MORRO DA CRUZ'!$K31),0) -> 0 | AG31: =ROUND(AF31*$P31,2) -> 0 | AH31: =IFERROR(SUMIFS('BM MORRO DA CRUZ - VERTICAL'!AL$6:AL$546,'BM MORRO DA CRUZ - VERTICAL'!$O$6:$O$546,'BM MORRO DA CRUZ'!$K31),0) -> 0 | AI31: =ROUND(AH31*$P31,2) -> 0 | AJ31: =IFERROR(SUMIFS('BM MORRO DA CRUZ - VERTICAL'!AN$6:AN$546,'BM MORRO DA CRUZ - VERTICAL'!$O$6:$O$546,'BM MORRO DA CRUZ'!$K31),0) -> 0 | AK31: =ROUND(AJ31*$P31,2) -> 0 | AL31: =IFERROR(SUMIFS('BM MORRO DA CRUZ - VERTICAL'!AP$6:AP$546,'BM MORRO DA CRUZ - VERTICAL'!$O$6:$O$546,'BM MORRO DA CRUZ'!$K31),0) -> 0 | AM31: =ROUND(AL31*$P31,2) -> 0 | AN31: =IFERROR(SUMIFS('BM MORRO DA CRUZ - VERTICAL'!AR$6:AR$546,'BM MORRO DA CRUZ - VERTICAL'!$O$6:$O$546,'BM MORRO DA CRUZ'!$K31),0) -> 0 | AO31: =ROUND(AN31*$P31,2) -> 0 | AP31: =IFERROR(SUMIFS('BM MORRO DA CRUZ - VERTICAL'!AT$6:AT$546,'BM MORRO DA CRUZ - VERTICAL'!$O$6:$O$546,'BM MORRO DA CRUZ'!$K31),0) -> 0 | AQ31: =ROUND(AP31*$P31,2) -> 0 | AR31: =IFERROR(SUMIFS('BM MORRO DA CRUZ - VERTICAL'!AV$6:AV$546,'BM MORRO DA CRUZ - VERTICAL'!$O$6:$O$546,'BM MORRO DA CRUZ'!$K31),0) -> 0 | AS31: =ROUND(AR31*$P31,2) -> 0 | AT31: =IFERROR(SUMIFS('BM MORRO DA CRUZ - VERTICAL'!AX$6:AX$546,'BM MORRO DA CRUZ - VERTICAL'!$O$6:$O$546,'BM MORRO DA CRUZ'!$K31),0) -> 0 | AU31: =ROUND(AT31*$P31,2) -> 0 | AV31: =IFERROR(SUMIFS('BM MORRO DA CRUZ - VERTICAL'!AZ$6:AZ$546,'BM MORRO DA CRUZ - VERTICAL'!$O$6:$O$546,'BM MORRO DA CRUZ'!$K31),0) -> 0 | AW31: =ROUND(AV31*$P31,2) -> 0 | AX31: =IFERROR(SUMIFS('BM MORRO DA CRUZ - VERTICAL'!BB$6:BB$546,'BM MORRO DA CRUZ - VERTICAL'!$O$6:$O$546,'BM MORRO DA CRUZ'!$K31),0) -> 0 | AY31: =ROUND(AX31*$P31,2) -> 0 | AZ31: =IFERROR(SUMIFS('BM MORRO DA CRUZ - VERTICAL'!BD$6:BD$546,'BM MORRO DA CRUZ - VERTICAL'!$O$6:$O$546,'BM MORRO DA CRUZ'!$K31),0) -> 0 | BA31: =ROUND(AZ31*$P31,2) -> 0 | BB31: =IFERROR(SUMIFS($R31:$BA31,$R$5:$BA$5,$BB$5),0) -> 0 | BC31: =SUMIFS($R31:$BA31,$R$5:$BA$5,$S$5) -> 0 | BD31: =IFERROR(BB31/O31,0) -> 0 | BE31: =IFERROR((O31-BB31)/O31,0) -> 1
A32: 1.10.6 | B32: VÁLVULA CONTROLE REDUTORA DE PRESSÃO EM Y - PROPORCIONAL | C32: PN10 | D32: N/A | E32: VRP | F32: N/A | G32: 2.1/2" | H32: FºFº | I32: HIDROMECÂNICO | J32: VÁLVULA | K32: 1511003043036 | L32: MATERIAL | M32: VÁLVULA DE CONTROLE EM Y REDUTORA DE PRESSÃO DE FERRO FUNDIDO FLANGEADA PD - PROPORCIONAL (CLASSE DE PRESSÃO: 10 KGF/CM² / DIÂMETRO DA SEÇÃO: 2 1/2 ") | N32: UN | O32: 8 | P32: 3351.67 | Q32: =ROUND(P32*$O32,2) -> 26813.36 | R32: =IFERROR(SUMIFS('BM MORRO DA CRUZ - VERTICAL'!V$6:V$546,'BM MORRO DA CRUZ - VERTICAL'!$O$6:$O$546,'BM MORRO DA CRUZ'!$K32),0) -> 0 | S32: =ROUND(R32*$P32,2) -> 0 | T32: =IFERROR(SUMIFS('BM MORRO DA CRUZ - VERTICAL'!X$6:X$546,'BM MORRO DA CRUZ - VERTICAL'!$O$6:$O$546,'BM MORRO DA CRUZ'!$K32),0) -> 0 | U32: =ROUND(T32*$P32,2) -> 0 | V32: =IFERROR(SUMIFS('BM MORRO DA CRUZ - VERTICAL'!Z$6:Z$546,'BM MORRO DA CRUZ - VERTICAL'!$O$6:$O$546,'BM MORRO DA CRUZ'!$K32),0) -> 0 | W32: =ROUND(V32*$P32,2) -> 0 | X32: =IFERROR(SUMIFS('BM MORRO DA CRUZ - VERTICAL'!AB$6:AB$546,'BM MORRO DA CRUZ - VERTICAL'!$O$6:$O$546,'BM MORRO DA CRUZ'!$K32),0) -> 0 | Y32: =ROUND(X32*$P32,2) -> 0 | Z32: =IFERROR(SUMIFS('BM MORRO DA CRUZ - VERTICAL'!AD$6:AD$546,'BM MORRO DA CRUZ - VERTICAL'!$O$6:$O$546,'BM MORRO DA CRUZ'!$K32),0) -> 0 | AA32: =ROUND(Z32*$P32,2) -> 0 | AB32: =IFERROR(SUMIFS('BM MORRO DA CRUZ - VERTICAL'!AF$6:AF$546,'BM MORRO DA CRUZ - VERTICAL'!$O$6:$O$546,'BM MORRO DA CRUZ'!$K32),0) -> 0 | AC32: =ROUND(AB32*$P32,2) -> 0 | AD32: =IFERROR(SUMIFS('BM MORRO DA CRUZ - VERTICAL'!AH$6:AH$546,'BM MORRO DA CRUZ - VERTICAL'!$O$6:$O$546,'BM MORRO DA CRUZ'!$K32),0) -> 0 | AE32: =ROUND(AD32*$P32,2) -> 0 | AF32: =IFERROR(SUMIFS('BM MORRO DA CRUZ - VERTICAL'!AJ$6:AJ$546,'BM MORRO DA CRUZ - VERTICAL'!$O$6:$O$546,'BM MORRO DA CRUZ'!$K32),0) -> 0 | AG32: =ROUND(AF32*$P32,2) -> 0 | AH32: =IFERROR(SUMIFS('BM MORRO DA CRUZ - VERTICAL'!AL$6:AL$546,'BM MORRO DA CRUZ - VERTICAL'!$O$6:$O$546,'BM MORRO DA CRUZ'!$K32),0) -> 0 | AI32: =ROUND(AH32*$P32,2) -> 0 | AJ32: =IFERROR(SUMIFS('BM MORRO DA CRUZ - VERTICAL'!AN$6:AN$546,'BM MORRO DA CRUZ - VERTICAL'!$O$6:$O$546,'BM MORRO DA CRUZ'!$K32),0) -> 0 | AK32: =ROUND(AJ32*$P32,2) -> 0 | AL32: =IFERROR(SUMIFS('BM MORRO DA CRUZ - VERTICAL'!AP$6:AP$546,'BM MORRO DA CRUZ - VERTICAL'!$O$6:$O$546,'BM MORRO DA CRUZ'!$K32),0) -> 0 | AM32: =ROUND(AL32*$P32,2) -> 0 | AN32: =IFERROR(SUMIFS('BM MORRO DA CRUZ - VERTICAL'!AR$6:AR$546,'BM MORRO DA CRUZ - VERTICAL'!$O$6:$O$546,'BM MORRO DA CRUZ'!$K32),0) -> 0 | AO32: =ROUND(AN32*$P32,2) -> 0 | AP32: =IFERROR(SUMIFS('BM MORRO DA CRUZ - VERTICAL'!AT$6:AT$546,'BM MORRO DA CRUZ - VERTICAL'!$O$6:$O$546,'BM MORRO DA CRUZ'!$K32),0) -> 0 | AQ32: =ROUND(AP32*$P32,2) -> 0 | AR32: =IFERROR(SUMIFS('BM MORRO DA CRUZ - VERTICAL'!AV$6:AV$546,'BM MORRO DA CRUZ - VERTICAL'!$O$6:$O$546,'BM MORRO DA CRUZ'!$K32),0) -> 0 | AS32: =ROUND(AR32*$P32,2) -> 0 | AT32: =IFERROR(SUMIFS('BM MORRO DA CRUZ - VERTICAL'!AX$6:AX$546,'BM MORRO DA CRUZ - VERTICAL'!$O$6:$O$546,'BM MORRO DA CRUZ'!$K32),0) -> 0 | AU32: =ROUND(AT32*$P32,2) -> 0 | AV32: =IFERROR(SUMIFS('BM MORRO DA CRUZ - VERTICAL'!AZ$6:AZ$546,'BM MORRO DA CRUZ - VERTICAL'!$O$6:$O$546,'BM MORRO DA CRUZ'!$K32),0) -> 0 | AW32: =ROUND(AV32*$P32,2) -> 0 | AX32: =IFERROR(SUMIFS('BM MORRO DA CRUZ - VERTICAL'!BB$6:BB$546,'BM MORRO DA CRUZ - VERTICAL'!$O$6:$O$546,'BM MORRO DA CRUZ'!$K32),0) -> 0 | AY32: =ROUND(AX32*$P32,2) -> 0 | AZ32: =IFERROR(SUMIFS('BM MORRO DA CRUZ - VERTICAL'!BD$6:BD$546,'BM MORRO DA CRUZ - VERTICAL'!$O$6:$O$546,'BM MORRO DA CRUZ'!$K32),0) -> 0 | BA32: =ROUND(AZ32*$P32,2) -> 0 | BB32: =IFERROR(SUMIFS($R32:$BA32,$R$5:$BA$5,$BB$5),0) -> 0 | BC32: =SUMIFS($R32:$BA32,$R$5:$BA$5,$S$5) -> 0 | BD32: =IFERROR(BB32/O32,0) -> 0 | BE32: =IFERROR((O32-BB32)/O32,0) -> 1
A33: 1.10.7 | B33: VÁLVULA CONTROLE REDUTORA DE PRESSÃO FLANGE X FLANGE | C33: PN10 | D33: N/A | E33: VRP | F33: N/A | G33: 80 | H33: FºFº | I33: HIDROMECÂNICO | J33: VÁLVULA | K33: 1511003043030 | L33: MATERIAL | M33: VÁLVULA DE CONTROLE REDUTORA DE PRESSÃO DE FERRO FUNDIDO FLANGEADA (CLASSE DE PRESSÃO: 10 KGF/CM² / DIÂMETRO DA SEÇÃO: 80 MM) | N33: UN | O33: 3 | P33: 1568.14 | Q33: =ROUND(P33*$O33,2) -> 4704.42 | R33: =IFERROR(SUMIFS('BM MORRO DA CRUZ - VERTICAL'!V$6:V$546,'BM MORRO DA CRUZ - VERTICAL'!$O$6:$O$546,'BM MORRO DA CRUZ'!$K33),0) -> 0 | S33: =ROUND(R33*$P33,2) -> 0 | T33: =IFERROR(SUMIFS('BM MORRO DA CRUZ - VERTICAL'!X$6:X$546,'BM MORRO DA CRUZ - VERTICAL'!$O$6:$O$546,'BM MORRO DA CRUZ'!$K33),0) -> 0 | U33: =ROUND(T33*$P33,2) -> 0 | V33: =IFERROR(SUMIFS('BM MORRO DA CRUZ - VERTICAL'!Z$6:Z$546,'BM MORRO DA CRUZ - VERTICAL'!$O$6:$O$546,'BM MORRO DA CRUZ'!$K33),0) -> 0 | W33: =ROUND(V33*$P33,2) -> 0 | X33: =IFERROR(SUMIFS('BM MORRO DA CRUZ - VERTICAL'!AB$6:AB$546,'BM MORRO DA CRUZ - VERTICAL'!$O$6:$O$546,'BM MORRO DA CRUZ'!$K33),0) -> 0 | Y33: =ROUND(X33*$P33,2) -> 0 | Z33: =IFERROR(SUMIFS('BM MORRO DA CRUZ - VERTICAL'!AD$6:AD$546,'BM MORRO DA CRUZ - VERTICAL'!$O$6:$O$546,'BM MORRO DA CRUZ'!$K33),0) -> 0 | AA33: =ROUND(Z33*$P33,2) -> 0 | AB33: =IFERROR(SUMIFS('BM MORRO DA CRUZ - VERTICAL'!AF$6:AF$546,'BM MORRO DA CRUZ - VERTICAL'!$O$6:$O$546,'BM MORRO DA CRUZ'!$K33),0) -> 0 | AC33: =ROUND(AB33*$P33,2) -> 0 | AD33: =IFERROR(SUMIFS('BM MORRO DA CRUZ - VERTICAL'!AH$6:AH$546,'BM MORRO DA CRUZ - VERTICAL'!$O$6:$O$546,'BM MORRO DA CRUZ'!$K33),0) -> 0 | AE33: =ROUND(AD33*$P33,2) -> 0 | AF33: =IFERROR(SUMIFS('BM MORRO DA CRUZ - VERTICAL'!AJ$6:AJ$546,'BM MORRO DA CRUZ - VERTICAL'!$O$6:$O$546,'BM MORRO DA CRUZ'!$K33),0) -> 0 | AG33: =ROUND(AF33*$P33,2) -> 0 | AH33: =IFERROR(SUMIFS('BM MORRO DA CRUZ - VERTICAL'!AL$6:AL$546,'BM MORRO DA CRUZ - VERTICAL'!$O$6:$O$546,'BM MORRO DA CRUZ'!$K33),0) -> 0 | AI33: =ROUND(AH33*$P33,2) -> 0 | AJ33: =IFERROR(SUMIFS('BM MORRO DA CRUZ - VERTICAL'!AN$6:AN$546,'BM MORRO DA CRUZ - VERTICAL'!$O$6:$O$546,'BM MORRO DA CRUZ'!$K33),0) -> 0 | AK33: =ROUND(AJ33*$P33,2) -> 0 | AL33: =IFERROR(SUMIFS('BM MORRO DA CRUZ - VERTICAL'!AP$6:AP$546,'BM MORRO DA CRUZ - VERTICAL'!$O$6:$O$546,'BM MORRO DA CRUZ'!$K33),0) -> 0 | AM33: =ROUND(AL33*$P33,2) -> 0 | AN33: =IFERROR(SUMIFS('BM MORRO DA CRUZ - VERTICAL'!AR$6:AR$546,'BM MORRO DA CRUZ - VERTICAL'!$O$6:$O$546,'BM MORRO DA CRUZ'!$K33),0) -> 0 | AO33: =ROUND(AN33*$P33,2) -> 0 | AP33: =IFERROR(SUMIFS('BM MORRO DA CRUZ - VERTICAL'!AT$6:AT$546,'BM MORRO DA CRUZ - VERTICAL'!$O$6:$O$546,'BM MORRO DA CRUZ'!$K33),0) -> 0 | AQ33: =ROUND(AP33*$P33,2) -> 0 | AR33: =IFERROR(SUMIFS('BM MORRO DA CRUZ - VERTICAL'!AV$6:AV$546,'BM MORRO DA CRUZ - VERTICAL'!$O$6:$O$546,'BM MORRO DA CRUZ'!$K33),0) -> 0 | AS33: =ROUND(AR33*$P33,2) -> 0 | AT33: =IFERROR(SUMIFS('BM MORRO DA CRUZ - VERTICAL'!AX$6:AX$546,'BM MORRO DA CRUZ - VERTICAL'!$O$6:$O$546,'BM MORRO DA CRUZ'!$K33),0) -> 0 | AU33: =ROUND(AT33*$P33,2) -> 0 | AV33: =IFERROR(SUMIFS('BM MORRO DA CRUZ - VERTICAL'!AZ$6:AZ$546,'BM MORRO DA CRUZ - VERTICAL'!$O$6:$O$546,'BM MORRO DA CRUZ'!$K33),0) -> 0 | AW33: =ROUND(AV33*$P33,2) -> 0 | AX33: =IFERROR(SUMIFS('BM MORRO DA CRUZ - VERTICAL'!BB$6:BB$546,'BM MORRO DA CRUZ - VERTICAL'!$O$6:$O$546,'BM MORRO DA CRUZ'!$K33),0) -> 0 | AY33: =ROUND(AX33*$P33,2) -> 0 | AZ33: =IFERROR(SUMIFS('BM MORRO DA CRUZ - VERTICAL'!BD$6:BD$546,'BM MORRO DA CRUZ - VERTICAL'!$O$6:$O$546,'BM MORRO DA CRUZ'!$K33),0) -> 0 | BA33: =ROUND(AZ33*$P33,2) -> 0 | BB33: =IFERROR(SUMIFS($R33:$BA33,$R$5:$BA$5,$BB$5),0) -> 0 | BC33: =SUMIFS($R33:$BA33,$R$5:$BA$5,$S$5) -> 0 | BD33: =IFERROR(BB33/O33,0) -> 0 | BE33: =IFERROR((O33-BB33)/O33,0) -> 1
A34: 1.10.8 | B34: VÁLVULA CONTROLE REDUTORA DE PRESSÃO FLANGE X FLANGE - AUTO OPERADA TIPO GLOBO | C34: PN10 | D34: N/A | E34: VRP | F34: N/A | G34: 100 | H34: FºFº | I34: HIDROMECÂNICO | J34: VÁLVULA | K34: 1511003043042 | L34: MATERIAL | M34: VÁLVULA DE CONTROLE REDUTORA DE PRESSÃO DE FERRO FUNDIDO FLANGEADA, AUTO OPERADA COM CORPO TIPO GLOBO (CLASSE DE PRESSÃO: 10 KGF/CM² / DIÂMETRO DA SEÇÃO: 100 MM) | N34: UN | O34: 1 | P34: 2010.82 | Q34: =ROUND(P34*$O34,2) -> 2010.82 | R34: =IFERROR(SUMIFS('BM MORRO DA CRUZ - VERTICAL'!V$6:V$546,'BM MORRO DA CRUZ - VERTICAL'!$O$6:$O$546,'BM MORRO DA CRUZ'!$K34),0) -> 0 | S34: =ROUND(R34*$P34,2) -> 0 | T34: =IFERROR(SUMIFS('BM MORRO DA CRUZ - VERTICAL'!X$6:X$546,'BM MORRO DA CRUZ - VERTICAL'!$O$6:$O$546,'BM MORRO DA CRUZ'!$K34),0) -> 0 | U34: =ROUND(T34*$P34,2) -> 0 | V34: =IFERROR(SUMIFS('BM MORRO DA CRUZ - VERTICAL'!Z$6:Z$546,'BM MORRO DA CRUZ - VERTICAL'!$O$6:$O$546,'BM MORRO DA CRUZ'!$K34),0) -> 0 | W34: =ROUND(V34*$P34,2) -> 0 | X34: =IFERROR(SUMIFS('BM MORRO DA CRUZ - VERTICAL'!AB$6:AB$546,'BM MORRO DA CRUZ - VERTICAL'!$O$6:$O$546,'BM MORRO DA CRUZ'!$K34),0) -> 0 | Y34: =ROUND(X34*$P34,2) -> 0 | Z34: =IFERROR(SUMIFS('BM MORRO DA CRUZ - VERTICAL'!AD$6:AD$546,'BM MORRO DA CRUZ - VERTICAL'!$O$6:$O$546,'BM MORRO DA CRUZ'!$K34),0) -> 0 | AA34: =ROUND(Z34*$P34,2) -> 0 | AB34: =IFERROR(SUMIFS('BM MORRO DA CRUZ - VERTICAL'!AF$6:AF$546,'BM MORRO DA CRUZ - VERTICAL'!$O$6:$O$546,'BM MORRO DA CRUZ'!$K34),0) -> 0 | AC34: =ROUND(AB34*$P34,2) -> 0 | AD34: =IFERROR(SUMIFS('BM MORRO DA CRUZ - VERTICAL'!AH$6:AH$546,'BM MORRO DA CRUZ - VERTICAL'!$O$6:$O$546,'BM MORRO DA CRUZ'!$K34),0) -> 0 | AE34: =ROUND(AD34*$P34,2) -> 0 | AF34: =IFERROR(SUMIFS('BM MORRO DA CRUZ - VERTICAL'!AJ$6:AJ$546,'BM MORRO DA CRUZ - VERTICAL'!$O$6:$O$546,'BM MORRO DA CRUZ'!$K34),0) -> 0 | AG34: =ROUND(AF34*$P34,2) -> 0 | AH34: =IFERROR(SUMIFS('BM MORRO DA CRUZ - VERTICAL'!AL$6:AL$546,'BM MORRO DA CRUZ - VERTICAL'!$O$6:$O$546,'BM MORRO DA CRUZ'!$K34),0) -> 0 | AI34: =ROUND(AH34*$P34,2) -> 0 | AJ34: =IFERROR(SUMIFS('BM MORRO DA CRUZ - VERTICAL'!AN$6:AN$546,'BM MORRO DA CRUZ - VERTICAL'!$O$6:$O$546,'BM MORRO DA CRUZ'!$K34),0) -> 0 | AK34: =ROUND(AJ34*$P34,2) -> 0 | AL34: =IFERROR(SUMIFS('BM MORRO DA CRUZ - VERTICAL'!AP$6:AP$546,'BM MORRO DA CRUZ - VERTICAL'!$O$6:$O$546,'BM MORRO DA CRUZ'!$K34),0) -> 0 | AM34: =ROUND(AL34*$P34,2) -> 0 | AN34: =IFERROR(SUMIFS('BM MORRO DA CRUZ - VERTICAL'!AR$6:AR$546,'BM MORRO DA CRUZ - VERTICAL'!$O$6:$O$546,'BM MORRO DA CRUZ'!$K34),0) -> 0 | AO34: =ROUND(AN34*$P34,2) -> 0 | AP34: =IFERROR(SUMIFS('BM MORRO DA CRUZ - VERTICAL'!AT$6:AT$546,'BM MORRO DA CRUZ - VERTICAL'!$O$6:$O$546,'BM MORRO DA CRUZ'!$K34),0) -> 0 | AQ34: =ROUND(AP34*$P34,2) -> 0 | AR34: =IFERROR(SUMIFS('BM MORRO DA CRUZ - VERTICAL'!AV$6:AV$546,'BM MORRO DA CRUZ - VERTICAL'!$O$6:$O$546,'BM MORRO DA CRUZ'!$K34),0) -> 0 | AS34: =ROUND(AR34*$P34,2) -> 0 | AT34: =IFERROR(SUMIFS('BM MORRO DA CRUZ - VERTICAL'!AX$6:AX$546,'BM MORRO DA CRUZ - VERTICAL'!$O$6:$O$546,'BM MORRO DA CRUZ'!$K34),0) -> 0 | AU34: =ROUND(AT34*$P34,2) -> 0 | AV34: =IFERROR(SUMIFS('BM MORRO DA CRUZ - VERTICAL'!AZ$6:AZ$546,'BM MORRO DA CRUZ - VERTICAL'!$O$6:$O$546,'BM MORRO DA CRUZ'!$K34),0) -> 0 | AW34: =ROUND(AV34*$P34,2) -> 0 | AX34: =IFERROR(SUMIFS('BM MORRO DA CRUZ - VERTICAL'!BB$6:BB$546,'BM MORRO DA CRUZ - VERTICAL'!$O$6:$O$546,'BM MORRO DA CRUZ'!$K34),0) -> 0 | AY34: =ROUND(AX34*$P34,2) -> 0 | AZ34: =IFERROR(SUMIFS('BM MORRO DA CRUZ - VERTICAL'!BD$6:BD$546,'BM MORRO DA CRUZ - VERTICAL'!$O$6:$O$546,'BM MORRO DA CRUZ'!$K34),0) -> 0 | BA34: =ROUND(AZ34*$P34,2) -> 0 | BB34: =IFERROR(SUMIFS($R34:$BA34,$R$5:$BA$5,$BB$5),0) -> 0 | BC34: =SUMIFS($R34:$BA34,$R$5:$BA$5,$S$5) -> 0 | BD34: =IFERROR(BB34/O34,0) -> 0 | BE34: =IFERROR((O34-BB34)/O34,0) -> 1
A35: 1.10.9 | B35: VÁLVULA CONTROLE REDUTORA DE PRESSÃO FLANGE X FLANGE - AUTO OPERADA TIPO GLOBO | C35: PN10 | D35: N/A | E35: VRP | F35: N/A | G35: 150 | H35: FºFº | I35: HIDROMECÂNICO | J35: VÁLVULA | K35: 1511003043040 | L35: MATERIAL | M35: VÁLVULA DE CONTROLE REDUTORA DE PRESSÃO DE FERRO FUNDIDO FLANGEADA, AUTO OPERADA COM CORPO TIPO GLOBO (CLASSE DE PRESSÃO: 10 KGF/CM² / DIÂMETRO DA SEÇÃO: 150 MM) | N35: UN | O35: 2 | P35: 2343.08 | Q35: =ROUND(P35*$O35,2) -> 4686.16 | R35: =IFERROR(SUMIFS('BM MORRO DA CRUZ - VERTICAL'!V$6:V$546,'BM MORRO DA CRUZ - VERTICAL'!$O$6:$O$546,'BM MORRO DA CRUZ'!$K35),0) -> 0 | S35: =ROUND(R35*$P35,2) -> 0 | T35: =IFERROR(SUMIFS('BM MORRO DA CRUZ - VERTICAL'!X$6:X$546,'BM MORRO DA CRUZ - VERTICAL'!$O$6:$O$546,'BM MORRO DA CRUZ'!$K35),0) -> 0 | U35: =ROUND(T35*$P35,2) -> 0 | V35: =IFERROR(SUMIFS('BM MORRO DA CRUZ - VERTICAL'!Z$6:Z$546,'BM MORRO DA CRUZ - VERTICAL'!$O$6:$O$546,'BM MORRO DA CRUZ'!$K35),0) -> 0 | W35: =ROUND(V35*$P35,2) -> 0 | X35: =IFERROR(SUMIFS('BM MORRO DA CRUZ - VERTICAL'!AB$6:AB$546,'BM MORRO DA CRUZ - VERTICAL'!$O$6:$O$546,'BM MORRO DA CRUZ'!$K35),0) -> 0 | Y35: =ROUND(X35*$P35,2) -> 0 | Z35: =IFERROR(SUMIFS('BM MORRO DA CRUZ - VERTICAL'!AD$6:AD$546,'BM MORRO DA CRUZ - VERTICAL'!$O$6:$O$546,'BM MORRO DA CRUZ'!$K35),0) -> 0 | AA35: =ROUND(Z35*$P35,2) -> 0 | AB35: =IFERROR(SUMIFS('BM MORRO DA CRUZ - VERTICAL'!AF$6:AF$546,'BM MORRO DA CRUZ - VERTICAL'!$O$6:$O$546,'BM MORRO DA CRUZ'!$K35),0) -> 0 | AC35: =ROUND(AB35*$P35,2) -> 0 | AD35: =IFERROR(SUMIFS('BM MORRO DA CRUZ - VERTICAL'!AH$6:AH$546,'BM MORRO DA CRUZ - VERTICAL'!$O$6:$O$546,'BM MORRO DA CRUZ'!$K35),0) -> 0 | AE35: =ROUND(AD35*$P35,2) -> 0 | AF35: =IFERROR(SUMIFS('BM MORRO DA CRUZ - VERTICAL'!AJ$6:AJ$546,'BM MORRO DA CRUZ - VERTICAL'!$O$6:$O$546,'BM MORRO DA CRUZ'!$K35),0) -> 0 | AG35: =ROUND(AF35*$P35,2) -> 0 | AH35: =IFERROR(SUMIFS('BM MORRO DA CRUZ - VERTICAL'!AL$6:AL$546,'BM MORRO DA CRUZ - VERTICAL'!$O$6:$O$546,'BM MORRO DA CRUZ'!$K35),0) -> 0 | AI35: =ROUND(AH35*$P35,2) -> 0 | AJ35: =IFERROR(SUMIFS('BM MORRO DA CRUZ - VERTICAL'!AN$6:AN$546,'BM MORRO DA CRUZ - VERTICAL'!$O$6:$O$546,'BM MORRO DA CRUZ'!$K35),0) -> 0 | AK35: =ROUND(AJ35*$P35,2) -> 0 | AL35: =IFERROR(SUMIFS('BM MORRO DA CRUZ - VERTICAL'!AP$6:AP$546,'BM MORRO DA CRUZ - VERTICAL'!$O$6:$O$546,'BM MORRO DA CRUZ'!$K35),0) -> 0 | AM35: =ROUND(AL35*$P35,2) -> 0 | AN35: =IFERROR(SUMIFS('BM MORRO DA CRUZ - VERTICAL'!AR$6:AR$546,'BM MORRO DA CRUZ - VERTICAL'!$O$6:$O$546,'BM MORRO DA CRUZ'!$K35),0) -> 0 | AO35: =ROUND(AN35*$P35,2) -> 0 | AP35: =IFERROR(SUMIFS('BM MORRO DA CRUZ - VERTICAL'!AT$6:AT$546,'BM MORRO DA CRUZ - VERTICAL'!$O$6:$O$546,'BM MORRO DA CRUZ'!$K35),0) -> 0 | AQ35: =ROUND(AP35*$P35,2) -> 0 | AR35: =IFERROR(SUMIFS('BM MORRO DA CRUZ - VERTICAL'!AV$6:AV$546,'BM MORRO DA CRUZ - VERTICAL'!$O$6:$O$546,'BM MORRO DA CRUZ'!$K35),0) -> 0 | AS35: =ROUND(AR35*$P35,2) -> 0 | AT35: =IFERROR(SUMIFS('BM MORRO DA CRUZ - VERTICAL'!AX$6:AX$546,'BM MORRO DA CRUZ - VERTICAL'!$O$6:$O$546,'BM MORRO DA CRUZ'!$K35),0) -> 0 | AU35: =ROUND(AT35*$P35,2) -> 0 | AV35: =IFERROR(SUMIFS('BM MORRO DA CRUZ - VERTICAL'!AZ$6:AZ$546,'BM MORRO DA CRUZ - VERTICAL'!$O$6:$O$546,'BM MORRO DA CRUZ'!$K35),0) -> 0 | AW35: =ROUND(AV35*$P35,2) -> 0 | AX35: =IFERROR(SUMIFS('BM MORRO DA CRUZ - VERTICAL'!BB$6:BB$546,'BM MORRO DA CRUZ - VERTICAL'!$O$6:$O$546,'BM MORRO DA CRUZ'!$K35),0) -> 0 | AY35: =ROUND(AX35*$P35,2) -> 0 | AZ35: =IFERROR(SUMIFS('BM MORRO DA CRUZ - VERTICAL'!BD$6:BD$546,'BM MORRO DA CRUZ - VERTICAL'!$O$6:$O$546,'BM MORRO DA CRUZ'!$K35),0) -> 0 | BA35: =ROUND(AZ35*$P35,2) -> 0 | BB35: =IFERROR(SUMIFS($R35:$BA35,$R$5:$BA$5,$BB$5),0) -> 0 | BC35: =SUMIFS($R35:$BA35,$R$5:$BA$5,$S$5) -> 0 | BD35: =IFERROR(BB35/O35,0) -> 0 | BE35: =IFERROR((O35-BB35)/O35,0) -> 1
A36: 1.10.10 | B36: VÁLVULA CONTROLE REDUTORA DE PRESSÃO FLANGE X FLANGE - AUTO OPERADA TIPO GLOBO | C36: PN10 | D36: N/A | E36: VRP | F36: N/A | G36: 200 | H36: FºFº | I36: HIDROMECÂNICO | J36: VÁLVULA | K36: 1511003043041 | L36: MATERIAL | M36: VÁLVULA DE CONTROLE REDUTORA DE PRESSÃO DE FERRO FUNDIDO FLANGEADA, AUTO OPERADA COM CORPO TIPO GLOBO (CLASSE DE PRESSÃO: 10 KGF/CM² / DIÂMETRO DA SEÇÃO: 200 MM) | N36: UN | O36: 2 | P36: 5060.67 | Q36: =ROUND(P36*$O36,2) -> 10121.34 | R36: =IFERROR(SUMIFS('BM MORRO DA CRUZ - VERTICAL'!V$6:V$546,'BM MORRO DA CRUZ - VERTICAL'!$O$6:$O$546,'BM MORRO DA CRUZ'!$K36),0) -> 0 | S36: =ROUND(R36*$P36,2) -> 0 | T36: =IFERROR(SUMIFS('BM MORRO DA CRUZ - VERTICAL'!X$6:X$546,'BM MORRO DA CRUZ - VERTICAL'!$O$6:$O$546,'BM MORRO DA CRUZ'!$K36),0) -> 0 | U36: =ROUND(T36*$P36,2) -> 0 | V36: =IFERROR(SUMIFS('BM MORRO DA CRUZ - VERTICAL'!Z$6:Z$546,'BM MORRO DA CRUZ - VERTICAL'!$O$6:$O$546,'BM MORRO DA CRUZ'!$K36),0) -> 0 | W36: =ROUND(V36*$P36,2) -> 0 | X36: =IFERROR(SUMIFS('BM MORRO DA CRUZ - VERTICAL'!AB$6:AB$546,'BM MORRO DA CRUZ - VERTICAL'!$O$6:$O$546,'BM MORRO DA CRUZ'!$K36),0) -> 0 | Y36: =ROUND(X36*$P36,2) -> 0 | Z36: =IFERROR(SUMIFS('BM MORRO DA CRUZ - VERTICAL'!AD$6:AD$546,'BM MORRO DA CRUZ - VERTICAL'!$O$6:$O$546,'BM MORRO DA CRUZ'!$K36),0) -> 0 | AA36: =ROUND(Z36*$P36,2) -> 0 | AB36: =IFERROR(SUMIFS('BM MORRO DA CRUZ - VERTICAL'!AF$6:AF$546,'BM MORRO DA CRUZ - VERTICAL'!$O$6:$O$546,'BM MORRO DA CRUZ'!$K36),0) -> 0 | AC36: =ROUND(AB36*$P36,2) -> 0 | AD36: =IFERROR(SUMIFS('BM MORRO DA CRUZ - VERTICAL'!AH$6:AH$546,'BM MORRO DA CRUZ - VERTICAL'!$O$6:$O$546,'BM MORRO DA CRUZ'!$K36),0) -> 0 | AE36: =ROUND(AD36*$P36,2) -> 0 | AF36: =IFERROR(SUMIFS('BM MORRO DA CRUZ - VERTICAL'!AJ$6:AJ$546,'BM MORRO DA CRUZ - VERTICAL'!$O$6:$O$546,'BM MORRO DA CRUZ'!$K36),0) -> 0 | AG36: =ROUND(AF36*$P36,2) -> 0 | AH36: =IFERROR(SUMIFS('BM MORRO DA CRUZ - VERTICAL'!AL$6:AL$546,'BM MORRO DA CRUZ - VERTICAL'!$O$6:$O$546,'BM MORRO DA CRUZ'!$K36),0) -> 0 | AI36: =ROUND(AH36*$P36,2) -> 0 | AJ36: =IFERROR(SUMIFS('BM MORRO DA CRUZ - VERTICAL'!AN$6:AN$546,'BM MORRO DA CRUZ - VERTICAL'!$O$6:$O$546,'BM MORRO DA CRUZ'!$K36),0) -> 0 | AK36: =ROUND(AJ36*$P36,2) -> 0 | AL36: =IFERROR(SUMIFS('BM MORRO DA CRUZ - VERTICAL'!AP$6:AP$546,'BM MORRO DA CRUZ - VERTICAL'!$O$6:$O$546,'BM MORRO DA CRUZ'!$K36),0) -> 0 | AM36: =ROUND(AL36*$P36,2) -> 0 | AN36: =IFERROR(SUMIFS('BM MORRO DA CRUZ - VERTICAL'!AR$6:AR$546,'BM MORRO DA CRUZ - VERTICAL'!$O$6:$O$546,'BM MORRO DA CRUZ'!$K36),0) -> 0 | AO36: =ROUND(AN36*$P36,2) -> 0 | AP36: =IFERROR(SUMIFS('BM MORRO DA CRUZ - VERTICAL'!AT$6:AT$546,'BM MORRO DA CRUZ - VERTICAL'!$O$6:$O$546,'BM MORRO DA CRUZ'!$K36),0) -> 0 | AQ36: =ROUND(AP36*$P36,2) -> 0 | AR36: =IFERROR(SUMIFS('BM MORRO DA CRUZ - VERTICAL'!AV$6:AV$546,'BM MORRO DA CRUZ - VERTICAL'!$O$6:$O$546,'BM MORRO DA CRUZ'!$K36),0) -> 0 | AS36: =ROUND(AR36*$P36,2) -> 0 | AT36: =IFERROR(SUMIFS('BM MORRO DA CRUZ - VERTICAL'!AX$6:AX$546,'BM MORRO DA CRUZ - VERTICAL'!$O$6:$O$546,'BM MORRO DA CRUZ'!$K36),0) -> 0 | AU36: =ROUND(AT36*$P36,2) -> 0 | AV36: =IFERROR(SUMIFS('BM MORRO DA CRUZ - VERTICAL'!AZ$6:AZ$546,'BM MORRO DA CRUZ - VERTICAL'!$O$6:$O$546,'BM MORRO DA CRUZ'!$K36),0) -> 0 | AW36: =ROUND(AV36*$P36,2) -> 0 | AX36: =IFERROR(SUMIFS('BM MORRO DA CRUZ - VERTICAL'!BB$6:BB$546,'BM MORRO DA CRUZ - VERTICAL'!$O$6:$O$546,'BM MORRO DA CRUZ'!$K36),0) -> 0 | AY36: =ROUND(AX36*$P36,2) -> 0 | AZ36: =IFERROR(SUMIFS('BM MORRO DA CRUZ - VERTICAL'!BD$6:BD$546,'BM MORRO DA CRUZ - VERTICAL'!$O$6:$O$546,'BM MORRO DA CRUZ'!$K36),0) -> 0 | BA36: =ROUND(AZ36*$P36,2) -> 0 | BB36: =IFERROR(SUMIFS($R36:$BA36,$R$5:$BA$5,$BB$5),0) -> 0 | BC36: =SUMIFS($R36:$BA36,$R$5:$BA$5,$S$5) -> 0 | BD36: =IFERROR(BB36/O36,0) -> 0 | BE36: =IFERROR((O36-BB36)/O36,0) -> 1
A37: 1.10.11 | B37: VÁLVULA GAVETA FF CUNHA BORRACHA CC - ACIONAMENTO CABEÇOTE | C37: PN10/16 | D37: N/A | E37: VÁLVULA GAVETA | F37: N/A | G37: 100 | H37: FºFº | I37: HIDROMECÂNICO | J37: VÁLVULA | K37: 1511003138007 | L37: MATERIAL | M37: VÁLVULA DE GAVETA FLANGEADA DE FERRO FUNDIDO DÚCTIL COM CUNHA DE BORRACHA, CORPO CURTO E ACIONAMENTO COM CABEÇOTE (CLASSE DE PRESSÃO: 10/16 KGF/CM² / DIÂMETRO DA SEÇÃO: 100 MM) | N37: UN | O37: 2 | P37: 893.5 | Q37: =ROUND(P37*$O37,2) -> 1787 | R37: =IFERROR(SUMIFS('BM MORRO DA CRUZ - VERTICAL'!V$6:V$546,'BM MORRO DA CRUZ - VERTICAL'!$O$6:$O$546,'BM MORRO DA CRUZ'!$K37),0) -> 0 | S37: =ROUND(R37*$P37,2) -> 0 | T37: =IFERROR(SUMIFS('BM MORRO DA CRUZ - VERTICAL'!X$6:X$546,'BM MORRO DA CRUZ - VERTICAL'!$O$6:$O$546,'BM MORRO DA CRUZ'!$K37),0) -> 0 | U37: =ROUND(T37*$P37,2) -> 0 | V37: =IFERROR(SUMIFS('BM MORRO DA CRUZ - VERTICAL'!Z$6:Z$546,'BM MORRO DA CRUZ - VERTICAL'!$O$6:$O$546,'BM MORRO DA CRUZ'!$K37),0) -> 0 | W37: =ROUND(V37*$P37,2) -> 0 | X37: =IFERROR(SUMIFS('BM MORRO DA CRUZ - VERTICAL'!AB$6:AB$546,'BM MORRO DA CRUZ - VERTICAL'!$O$6:$O$546,'BM MORRO DA CRUZ'!$K37),0) -> 0 | Y37: =ROUND(X37*$P37,2) -> 0 | Z37: =IFERROR(SUMIFS('BM MORRO DA CRUZ - VERTICAL'!AD$6:AD$546,'BM MORRO DA CRUZ - VERTICAL'!$O$6:$O$546,'BM MORRO DA CRUZ'!$K37),0) -> 0 | AA37: =ROUND(Z37*$P37,2) -> 0 | AB37: =IFERROR(SUMIFS('BM MORRO DA CRUZ - VERTICAL'!AF$6:AF$546,'BM MORRO DA CRUZ - VERTICAL'!$O$6:$O$546,'BM MORRO DA CRUZ'!$K37),0) -> 0 | AC37: =ROUND(AB37*$P37,2) -> 0 | AD37: =IFERROR(SUMIFS('BM MORRO DA CRUZ - VERTICAL'!AH$6:AH$546,'BM MORRO DA CRUZ - VERTICAL'!$O$6:$O$546,'BM MORRO DA CRUZ'!$K37),0) -> 0 | AE37: =ROUND(AD37*$P37,2) -> 0 | AF37: =IFERROR(SUMIFS('BM MORRO DA CRUZ - VERTICAL'!AJ$6:AJ$546,'BM MORRO DA CRUZ - VERTICAL'!$O$6:$O$546,'BM MORRO DA CRUZ'!$K37),0) -> 0 | AG37: =ROUND(AF37*$P37,2) -> 0 | AH37: =IFERROR(SUMIFS('BM MORRO DA CRUZ - VERTICAL'!AL$6:AL$546,'BM MORRO DA CRUZ - VERTICAL'!$O$6:$O$546,'BM MORRO DA CRUZ'!$K37),0) -> 0 | AI37: =ROUND(AH37*$P37,2) -> 0 | AJ37: =IFERROR(SUMIFS('BM MORRO DA CRUZ - VERTICAL'!AN$6:AN$546,'BM MORRO DA CRUZ - VERTICAL'!$O$6:$O$546,'BM MORRO DA CRUZ'!$K37),0) -> 0 | AK37: =ROUND(AJ37*$P37,2) -> 0 | AL37: =IFERROR(SUMIFS('BM MORRO DA CRUZ - VERTICAL'!AP$6:AP$546,'BM MORRO DA CRUZ - VERTICAL'!$O$6:$O$546,'BM MORRO DA CRUZ'!$K37),0) -> 0 | AM37: =ROUND(AL37*$P37,2) -> 0 | AN37: =IFERROR(SUMIFS('BM MORRO DA CRUZ - VERTICAL'!AR$6:AR$546,'BM MORRO DA CRUZ - VERTICAL'!$O$6:$O$546,'BM MORRO DA CRUZ'!$K37),0) -> 0 | AO37: =ROUND(AN37*$P37,2) -> 0 | AP37: =IFERROR(SUMIFS('BM MORRO DA CRUZ - VERTICAL'!AT$6:AT$546,'BM MORRO DA CRUZ - VERTICAL'!$O$6:$O$546,'BM MORRO DA CRUZ'!$K37),0) -> 0 | AQ37: =ROUND(AP37*$P37,2) -> 0 | AR37: =IFERROR(SUMIFS('BM MORRO DA CRUZ - VERTICAL'!AV$6:AV$546,'BM MORRO DA CRUZ - VERTICAL'!$O$6:$O$546,'BM MORRO DA CRUZ'!$K37),0) -> 0 | AS37: =ROUND(AR37*$P37,2) -> 0 | AT37: =IFERROR(SUMIFS('BM MORRO DA CRUZ - VERTICAL'!AX$6:AX$546,'BM MORRO DA CRUZ - VERTICAL'!$O$6:$O$546,'BM MORRO DA CRUZ'!$K37),0) -> 0 | AU37: =ROUND(AT37*$P37,2) -> 0 | AV37: =IFERROR(SUMIFS('BM MORRO DA CRUZ - VERTICAL'!AZ$6:AZ$546,'BM MORRO DA CRUZ - VERTICAL'!$O$6:$O$546,'BM MORRO DA CRUZ'!$K37),0) -> 0 | AW37: =ROUND(AV37*$P37,2) -> 0 | AX37: =IFERROR(SUMIFS('BM MORRO DA CRUZ - VERTICAL'!BB$6:BB$546,'BM MORRO DA CRUZ - VERTICAL'!$O$6:$O$546,'BM MORRO DA CRUZ'!$K37),0) -> 0 | AY37: =ROUND(AX37*$P37,2) -> 0 | AZ37: =IFERROR(SUMIFS('BM MORRO DA CRUZ - VERTICAL'!BD$6:BD$546,'BM MORRO DA CRUZ - VERTICAL'!$O$6:$O$546,'BM MORRO DA CRUZ'!$K37),0) -> 0 | BA37: =ROUND(AZ37*$P37,2) -> 0 | BB37: =IFERROR(SUMIFS($R37:$BA37,$R$5:$BA$5,$BB$5),0) -> 0 | BC37: =SUMIFS($R37:$BA37,$R$5:$BA$5,$S$5) -> 0 | BD37: =IFERROR(BB37/O37,0) -> 0 | BE37: =IFERROR((O37-BB37)/O37,0) -> 1
A38: 1.10.12 | B38: VÁLVULA GAVETA FF CUNHA BORRACHA CC - ACIONAMENTO CABEÇOTE | C38: PN10/16 | D38: N/A | E38: VÁLVULA GAVETA | F38: N/A | G38: 150 | H38: FºFº | I38: HIDROMECÂNICO | J38: VÁLVULA | K38: 1511003138034 | L38: MATERIAL | M38: VÁLVULA DE GAVETA FLANGEADA DE FERRO FUNDIDO DÚCTIL COM CUNHA DE BORRACHA, CORPO CURTO E ACIONAMENTO COM CABEÇOTE (CLASSE DE PRESSÃO: 10/16 KGF/CM² / DIÂMETRO DA SEÇÃO: 150 MM) | N38: UN | O38: 20 | P38: 1436.8 | Q38: =ROUND(P38*$O38,2) -> 28736 | R38: =IFERROR(SUMIFS('BM MORRO DA CRUZ - VERTICAL'!V$6:V$546,'BM MORRO DA CRUZ - VERTICAL'!$O$6:$O$546,'BM MORRO DA CRUZ'!$K38),0) -> 0 | S38: =ROUND(R38*$P38,2) -> 0 | T38: =IFERROR(SUMIFS('BM MORRO DA CRUZ - VERTICAL'!X$6:X$546,'BM MORRO DA CRUZ - VERTICAL'!$O$6:$O$546,'BM MORRO DA CRUZ'!$K38),0) -> 0 | U38: =ROUND(T38*$P38,2) -> 0 | V38: =IFERROR(SUMIFS('BM MORRO DA CRUZ - VERTICAL'!Z$6:Z$546,'BM MORRO DA CRUZ - VERTICAL'!$O$6:$O$546,'BM MORRO DA CRUZ'!$K38),0) -> 0 | W38: =ROUND(V38*$P38,2) -> 0 | X38: =IFERROR(SUMIFS('BM MORRO DA CRUZ - VERTICAL'!AB$6:AB$546,'BM MORRO DA CRUZ - VERTICAL'!$O$6:$O$546,'BM MORRO DA CRUZ'!$K38),0) -> 0 | Y38: =ROUND(X38*$P38,2) -> 0 | Z38: =IFERROR(SUMIFS('BM MORRO DA CRUZ - VERTICAL'!AD$6:AD$546,'BM MORRO DA CRUZ - VERTICAL'!$O$6:$O$546,'BM MORRO DA CRUZ'!$K38),0) -> 0 | AA38: =ROUND(Z38*$P38,2) -> 0 | AB38: =IFERROR(SUMIFS('BM MORRO DA CRUZ - VERTICAL'!AF$6:AF$546,'BM MORRO DA CRUZ - VERTICAL'!$O$6:$O$546,'BM MORRO DA CRUZ'!$K38),0) -> 0 | AC38: =ROUND(AB38*$P38,2) -> 0 | AD38: =IFERROR(SUMIFS('BM MORRO DA CRUZ - VERTICAL'!AH$6:AH$546,'BM MORRO DA CRUZ - VERTICAL'!$O$6:$O$546,'BM MORRO DA CRUZ'!$K38),0) -> 0 | AE38: =ROUND(AD38*$P38,2) -> 0 | AF38: =IFERROR(SUMIFS('BM MORRO DA CRUZ - VERTICAL'!AJ$6:AJ$546,'BM MORRO DA CRUZ - VERTICAL'!$O$6:$O$546,'BM MORRO DA CRUZ'!$K38),0) -> 0 | AG38: =ROUND(AF38*$P38,2) -> 0 | AH38: =IFERROR(SUMIFS('BM MORRO DA CRUZ - VERTICAL'!AL$6:AL$546,'BM MORRO DA CRUZ - VERTICAL'!$O$6:$O$546,'BM MORRO DA CRUZ'!$K38),0) -> 0 | AI38: =ROUND(AH38*$P38,2) -> 0 | AJ38: =IFERROR(SUMIFS('BM MORRO DA CRUZ - VERTICAL'!AN$6:AN$546,'BM MORRO DA CRUZ - VERTICAL'!$O$6:$O$546,'BM MORRO DA CRUZ'!$K38),0) -> 0 | AK38: =ROUND(AJ38*$P38,2) -> 0 | AL38: =IFERROR(SUMIFS('BM MORRO DA CRUZ - VERTICAL'!AP$6:AP$546,'BM MORRO DA CRUZ - VERTICAL'!$O$6:$O$546,'BM MORRO DA CRUZ'!$K38),0) -> 0 | AM38: =ROUND(AL38*$P38,2) -> 0 | AN38: =IFERROR(SUMIFS('BM MORRO DA CRUZ - VERTICAL'!AR$6:AR$546,'BM MORRO DA CRUZ - VERTICAL'!$O$6:$O$546,'BM MORRO DA CRUZ'!$K38),0) -> 0 | AO38: =ROUND(AN38*$P38,2) -> 0 | AP38: =IFERROR(SUMIFS('BM MORRO DA CRUZ - VERTICAL'!AT$6:AT$546,'BM MORRO DA CRUZ - VERTICAL'!$O$6:$O$546,'BM MORRO DA CRUZ'!$K38),0) -> 0 | AQ38: =ROUND(AP38*$P38,2) -> 0 | AR38: =IFERROR(SUMIFS('BM MORRO DA CRUZ - VERTICAL'!AV$6:AV$546,'BM MORRO DA CRUZ - VERTICAL'!$O$6:$O$546,'BM MORRO DA CRUZ'!$K38),0) -> 0 | AS38: =ROUND(AR38*$P38,2) -> 0 | AT38: =IFERROR(SUMIFS('BM MORRO DA CRUZ - VERTICAL'!AX$6:AX$546,'BM MORRO DA CRUZ - VERTICAL'!$O$6:$O$546,'BM MORRO DA CRUZ'!$K38),0) -> 0 | AU38: =ROUND(AT38*$P38,2) -> 0 | AV38: =IFERROR(SUMIFS('BM MORRO DA CRUZ - VERTICAL'!AZ$6:AZ$546,'BM MORRO DA CRUZ - VERTICAL'!$O$6:$O$546,'BM MORRO DA CRUZ'!$K38),0) -> 0 | AW38: =ROUND(AV38*$P38,2) -> 0 | AX38: =IFERROR(SUMIFS('BM MORRO DA CRUZ - VERTICAL'!BB$6:BB$546,'BM MORRO DA CRUZ - VERTICAL'!$O$6:$O$546,'BM MORRO DA CRUZ'!$K38),0) -> 0 | AY38: =ROUND(AX38*$P38,2) -> 0 | AZ38: =IFERROR(SUMIFS('BM MORRO DA CRUZ - VERTICAL'!BD$6:BD$546,'BM MORRO DA CRUZ - VERTICAL'!$O$6:$O$546,'BM MORRO DA CRUZ'!$K38),0) -> 0 | BA38: =ROUND(AZ38*$P38,2) -> 0 | BB38: =IFERROR(SUMIFS($R38:$BA38,$R$5:$BA$5,$BB$5),0) -> 0 | BC38: =SUMIFS($R38:$BA38,$R$5:$BA$5,$S$5) -> 0 | BD38: =IFERROR(BB38/O38,0) -> 0 | BE38: =IFERROR((O38-BB38)/O38,0) -> 1
A39: 1.10.13 | B39: VÁLVULA GAVETA FF CUNHA BORRACHA CC - ACIONAMENTO CABEÇOTE | C39: PN10/16 | D39: N/A | E39: VÁLVULA GAVETA | F39: N/A | G39: 200 | H39: FºFº | I39: HIDROMECÂNICO | J39: VÁLVULA | K39: 1511003138001 | L39: MATERIAL | M39: VÁLVULA DE GAVETA FLANGEADA DE FERRO FUNDIDO DÚCTIL COM CUNHA DE BORRACHA, CORPO CURTO E ACIONAMENTO COM CABEÇOTE (CLASSE DE PRESSÃO: 10/16 KGF/CM² / DIÂMETRO DA SEÇÃO: 200 MM) | N39: UN | O39: 9 | P39: 2692.06 | Q39: =ROUND(P39*$O39,2) -> 24228.54 | R39: =IFERROR(SUMIFS('BM MORRO DA CRUZ - VERTICAL'!V$6:V$546,'BM MORRO DA CRUZ - VERTICAL'!$O$6:$O$546,'BM MORRO DA CRUZ'!$K39),0) -> 0 | S39: =ROUND(R39*$P39,2) -> 0 | T39: =IFERROR(SUMIFS('BM MORRO DA CRUZ - VERTICAL'!X$6:X$546,'BM MORRO DA CRUZ - VERTICAL'!$O$6:$O$546,'BM MORRO DA CRUZ'!$K39),0) -> 0 | U39: =ROUND(T39*$P39,2) -> 0 | V39: =IFERROR(SUMIFS('BM MORRO DA CRUZ - VERTICAL'!Z$6:Z$546,'BM MORRO DA CRUZ - VERTICAL'!$O$6:$O$546,'BM MORRO DA CRUZ'!$K39),0) -> 0 | W39: =ROUND(V39*$P39,2) -> 0 | X39: =IFERROR(SUMIFS('BM MORRO DA CRUZ - VERTICAL'!AB$6:AB$546,'BM MORRO DA CRUZ - VERTICAL'!$O$6:$O$546,'BM MORRO DA CRUZ'!$K39),0) -> 0 | Y39: =ROUND(X39*$P39,2) -> 0 | Z39: =IFERROR(SUMIFS('BM MORRO DA CRUZ - VERTICAL'!AD$6:AD$546,'BM MORRO DA CRUZ - VERTICAL'!$O$6:$O$546,'BM MORRO DA CRUZ'!$K39),0) -> 0 | AA39: =ROUND(Z39*$P39,2) -> 0 | AB39: =IFERROR(SUMIFS('BM MORRO DA CRUZ - VERTICAL'!AF$6:AF$546,'BM MORRO DA CRUZ - VERTICAL'!$O$6:$O$546,'BM MORRO DA CRUZ'!$K39),0) -> 0 | AC39: =ROUND(AB39*$P39,2) -> 0 | AD39: =IFERROR(SUMIFS('BM MORRO DA CRUZ - VERTICAL'!AH$6:AH$546,'BM MORRO DA CRUZ - VERTICAL'!$O$6:$O$546,'BM MORRO DA CRUZ'!$K39),0) -> 0 | AE39: =ROUND(AD39*$P39,2) -> 0 | AF39: =IFERROR(SUMIFS('BM MORRO DA CRUZ - VERTICAL'!AJ$6:AJ$546,'BM MORRO DA CRUZ - VERTICAL'!$O$6:$O$546,'BM MORRO DA CRUZ'!$K39),0) -> 0 | AG39: =ROUND(AF39*$P39,2) -> 0 | AH39: =IFERROR(SUMIFS('BM MORRO DA CRUZ - VERTICAL'!AL$6:AL$546,'BM MORRO DA CRUZ - VERTICAL'!$O$6:$O$546,'BM MORRO DA CRUZ'!$K39),0) -> 0 | AI39: =ROUND(AH39*$P39,2) -> 0 | AJ39: =IFERROR(SUMIFS('BM MORRO DA CRUZ - VERTICAL'!AN$6:AN$546,'BM MORRO DA CRUZ - VERTICAL'!$O$6:$O$546,'BM MORRO DA CRUZ'!$K39),0) -> 0 | AK39: =ROUND(AJ39*$P39,2) -> 0 | AL39: =IFERROR(SUMIFS('BM MORRO DA CRUZ - VERTICAL'!AP$6:AP$546,'BM MORRO DA CRUZ - VERTICAL'!$O$6:$O$546,'BM MORRO DA CRUZ'!$K39),0) -> 0 | AM39: =ROUND(AL39*$P39,2) -> 0 | AN39: =IFERROR(SUMIFS('BM MORRO DA CRUZ - VERTICAL'!AR$6:AR$546,'BM MORRO DA CRUZ - VERTICAL'!$O$6:$O$546,'BM MORRO DA CRUZ'!$K39),0) -> 0 | AO39: =ROUND(AN39*$P39,2) -> 0 | AP39: =IFERROR(SUMIFS('BM MORRO DA CRUZ - VERTICAL'!AT$6:AT$546,'BM MORRO DA CRUZ - VERTICAL'!$O$6:$O$546,'BM MORRO DA CRUZ'!$K39),0) -> 0 | AQ39: =ROUND(AP39*$P39,2) -> 0 | AR39: =IFERROR(SUMIFS('BM MORRO DA CRUZ - VERTICAL'!AV$6:AV$546,'BM MORRO DA CRUZ - VERTICAL'!$O$6:$O$546,'BM MORRO DA CRUZ'!$K39),0) -> 0 | AS39: =ROUND(AR39*$P39,2) -> 0 | AT39: =IFERROR(SUMIFS('BM MORRO DA CRUZ - VERTICAL'!AX$6:AX$546,'BM MORRO DA CRUZ - VERTICAL'!$O$6:$O$546,'BM MORRO DA CRUZ'!$K39),0) -> 0 | AU39: =ROUND(AT39*$P39,2) -> 0 | AV39: =IFERROR(SUMIFS('BM MORRO DA CRUZ - VERTICAL'!AZ$6:AZ$546,'BM MORRO DA CRUZ - VERTICAL'!$O$6:$O$546,'BM MORRO DA CRUZ'!$K39),0) -> 0 | AW39: =ROUND(AV39*$P39,2) -> 0 | AX39: =IFERROR(SUMIFS('BM MORRO DA CRUZ - VERTICAL'!BB$6:BB$546,'BM MORRO DA CRUZ - VERTICAL'!$O$6:$O$546,'BM MORRO DA CRUZ'!$K39),0) -> 0 | AY39: =ROUND(AX39*$P39,2) -> 0 | AZ39: =IFERROR(SUMIFS('BM MORRO DA CRUZ - VERTICAL'!BD$6:BD$546,'BM MORRO DA CRUZ - VERTICAL'!$O$6:$O$546,'BM MORRO DA CRUZ'!$K39),0) -> 0 | BA39: =ROUND(AZ39*$P39,2) -> 0 | BB39: =IFERROR(SUMIFS($R39:$BA39,$R$5:$BA$5,$BB$5),0) -> 0 | BC39: =SUMIFS($R39:$BA39,$R$5:$BA$5,$S$5) -> 0 | BD39: =IFERROR(BB39/O39,0) -> 0 | BE39: =IFERROR((O39-BB39)/O39,0) -> 1
A40: 1.10.14 | B40: VÁLVULA GAVETA FF CUNHA BORRACHA CC - ACIONAMENTO CABEÇOTE | C40: PN10/16 | D40: N/A | E40: VÁLVULA GAVETA | F40: N/A | G40: 250 | H40: FºFº | I40: HIDROMECÂNICO | J40: VÁLVULA | K40: 1511003138002 | L40: MATERIAL | M40: VÁLVULA DE GAVETA FLANGEADA DE FERRO FUNDIDO DÚCTIL COM CUNHA DE BORRACHA, CORPO CURTO E ACIONAMENTO COM CABEÇOTE (CLASSE DE PRESSÃO: 10/16 KGF/CM² / DIÂMETRO DA SEÇÃO: 250 MM) | N40: UN | O40: 3 | P40: 3538.73 | Q40: =ROUND(P40*$O40,2) -> 10616.19 | R40: =IFERROR(SUMIFS('BM MORRO DA CRUZ - VERTICAL'!V$6:V$546,'BM MORRO DA CRUZ - VERTICAL'!$O$6:$O$546,'BM MORRO DA CRUZ'!$K40),0) -> 0 | S40: =ROUND(R40*$P40,2) -> 0 | T40: =IFERROR(SUMIFS('BM MORRO DA CRUZ - VERTICAL'!X$6:X$546,'BM MORRO DA CRUZ - VERTICAL'!$O$6:$O$546,'BM MORRO DA CRUZ'!$K40),0) -> 0 | U40: =ROUND(T40*$P40,2) -> 0 | V40: =IFERROR(SUMIFS('BM MORRO DA CRUZ - VERTICAL'!Z$6:Z$546,'BM MORRO DA CRUZ - VERTICAL'!$O$6:$O$546,'BM MORRO DA CRUZ'!$K40),0) -> 0 | W40: =ROUND(V40*$P40,2) -> 0 | X40: =IFERROR(SUMIFS('BM MORRO DA CRUZ - VERTICAL'!AB$6:AB$546,'BM MORRO DA CRUZ - VERTICAL'!$O$6:$O$546,'BM MORRO DA CRUZ'!$K40),0) -> 0 | Y40: =ROUND(X40*$P40,2) -> 0 | Z40: =IFERROR(SUMIFS('BM MORRO DA CRUZ - VERTICAL'!AD$6:AD$546,'BM MORRO DA CRUZ - VERTICAL'!$O$6:$O$546,'BM MORRO DA CRUZ'!$K40),0) -> 0 | AA40: =ROUND(Z40*$P40,2) -> 0 | AB40: =IFERROR(SUMIFS('BM MORRO DA CRUZ - VERTICAL'!AF$6:AF$546,'BM MORRO DA CRUZ - VERTICAL'!$O$6:$O$546,'BM MORRO DA CRUZ'!$K40),0) -> 0 | AC40: =ROUND(AB40*$P40,2) -> 0 | AD40: =IFERROR(SUMIFS('BM MORRO DA CRUZ - VERTICAL'!AH$6:AH$546,'BM MORRO DA CRUZ - VERTICAL'!$O$6:$O$546,'BM MORRO DA CRUZ'!$K40),0) -> 0 | AE40: =ROUND(AD40*$P40,2) -> 0 | AF40: =IFERROR(SUMIFS('BM MORRO DA CRUZ - VERTICAL'!AJ$6:AJ$546,'BM MORRO DA CRUZ - VERTICAL'!$O$6:$O$546,'BM MORRO DA CRUZ'!$K40),0) -> 0 | AG40: =ROUND(AF40*$P40,2) -> 0 | AH40: =IFERROR(SUMIFS('BM MORRO DA CRUZ - VERTICAL'!AL$6:AL$546,'BM MORRO DA CRUZ - VERTICAL'!$O$6:$O$546,'BM MORRO DA CRUZ'!$K40),0) -> 0 | AI40: =ROUND(AH40*$P40,2) -> 0 | AJ40: =IFERROR(SUMIFS('BM MORRO DA CRUZ - VERTICAL'!AN$6:AN$546,'BM MORRO DA CRUZ - VERTICAL'!$O$6:$O$546,'BM MORRO DA CRUZ'!$K40),0) -> 0 | AK40: =ROUND(AJ40*$P40,2) -> 0 | AL40: =IFERROR(SUMIFS('BM MORRO DA CRUZ - VERTICAL'!AP$6:AP$546,'BM MORRO DA CRUZ - VERTICAL'!$O$6:$O$546,'BM MORRO DA CRUZ'!$K40),0) -> 0 | AM40: =ROUND(AL40*$P40,2) -> 0 | AN40: =IFERROR(SUMIFS('BM MORRO DA CRUZ - VERTICAL'!AR$6:AR$546,'BM MORRO DA CRUZ - VERTICAL'!$O$6:$O$546,'BM MORRO DA CRUZ'!$K40),0) -> 0 | AO40: =ROUND(AN40*$P40,2) -> 0 | AP40: =IFERROR(SUMIFS('BM MORRO DA CRUZ - VERTICAL'!AT$6:AT$546,'BM MORRO DA CRUZ - VERTICAL'!$O$6:$O$546,'BM MORRO DA CRUZ'!$K40),0) -> 0 | AQ40: =ROUND(AP40*$P40,2) -> 0 | AR40: =IFERROR(SUMIFS('BM MORRO DA CRUZ - VERTICAL'!AV$6:AV$546,'BM MORRO DA CRUZ - VERTICAL'!$O$6:$O$546,'BM MORRO DA CRUZ'!$K40),0) -> 0 | AS40: =ROUND(AR40*$P40,2) -> 0 | AT40: =IFERROR(SUMIFS('BM MORRO DA CRUZ - VERTICAL'!AX$6:AX$546,'BM MORRO DA CRUZ - VERTICAL'!$O$6:$O$546,'BM MORRO DA CRUZ'!$K40),0) -> 0 | AU40: =ROUND(AT40*$P40,2) -> 0 | AV40: =IFERROR(SUMIFS('BM MORRO DA CRUZ - VERTICAL'!AZ$6:AZ$546,'BM MORRO DA CRUZ - VERTICAL'!$O$6:$O$546,'BM MORRO DA CRUZ'!$K40),0) -> 0 | AW40: =ROUND(AV40*$P40,2) -> 0 | AX40: =IFERROR(SUMIFS('BM MORRO DA CRUZ - VERTICAL'!BB$6:BB$546,'BM MORRO DA CRUZ - VERTICAL'!$O$6:$O$546,'BM MORRO DA CRUZ'!$K40),0) -> 0 | AY40: =ROUND(AX40*$P40,2) -> 0 | AZ40: =IFERROR(SUMIFS('BM MORRO DA CRUZ - VERTICAL'!BD$6:BD$546,'BM MORRO DA CRUZ - VERTICAL'!$O$6:$O$546,'BM MORRO DA CRUZ'!$K40),0) -> 0 | BA40: =ROUND(AZ40*$P40,2) -> 0 | BB40: =IFERROR(SUMIFS($R40:$BA40,$R$5:$BA$5,$BB$5),0) -> 0 | BC40: =SUMIFS($R40:$BA40,$R$5:$BA$5,$S$5) -> 0 | BD40: =IFERROR(BB40/O40,0) -> 0 | BE40: =IFERROR((O40-BB40)/O40,0) -> 1
A41: 1.10.15 | B41: VÁLVULA GAVETA FF CUNHA BORRACHA CC - ACIONAMENTO CABEÇOTE | C41: PN10/16 | D41: N/A | E41: VÁLVULA GAVETA | F41: N/A | G41: 50 | H41: FºFº | I41: HIDROMECÂNICO | J41: VÁLVULA | K41: 1511003138014 | L41: MATERIAL | M41: VÁLVULA DE GAVETA FLANGEADA DE FERRO FUNDIDO DÚCTIL COM CUNHA DE BORRACHA, CORPO CURTO E ACIONAMENTO COM CABEÇOTE (CLASSE DE PRESSÃO: 10/16 KGF/CM² / DIÂMETRO DA SEÇÃO: 50 MM) | N41: UN | O41: 81 | P41: 551.46 | Q41: =ROUND(P41*$O41,2) -> 44668.26 | R41: =IFERROR(SUMIFS('BM MORRO DA CRUZ - VERTICAL'!V$6:V$546,'BM MORRO DA CRUZ - VERTICAL'!$O$6:$O$546,'BM MORRO DA CRUZ'!$K41),0) -> 0 | S41: =ROUND(R41*$P41,2) -> 0 | T41: =IFERROR(SUMIFS('BM MORRO DA CRUZ - VERTICAL'!X$6:X$546,'BM MORRO DA CRUZ - VERTICAL'!$O$6:$O$546,'BM MORRO DA CRUZ'!$K41),0) -> 0 | U41: =ROUND(T41*$P41,2) -> 0 | V41: =IFERROR(SUMIFS('BM MORRO DA CRUZ - VERTICAL'!Z$6:Z$546,'BM MORRO DA CRUZ - VERTICAL'!$O$6:$O$546,'BM MORRO DA CRUZ'!$K41),0) -> 0 | W41: =ROUND(V41*$P41,2) -> 0 | X41: =IFERROR(SUMIFS('BM MORRO DA CRUZ - VERTICAL'!AB$6:AB$546,'BM MORRO DA CRUZ - VERTICAL'!$O$6:$O$546,'BM MORRO DA CRUZ'!$K41),0) -> 0 | Y41: =ROUND(X41*$P41,2) -> 0 | Z41: =IFERROR(SUMIFS('BM MORRO DA CRUZ - VERTICAL'!AD$6:AD$546,'BM MORRO DA CRUZ - VERTICAL'!$O$6:$O$546,'BM MORRO DA CRUZ'!$K41),0) -> 0 | AA41: =ROUND(Z41*$P41,2) -> 0 | AB41: =IFERROR(SUMIFS('BM MORRO DA CRUZ - VERTICAL'!AF$6:AF$546,'BM MORRO DA CRUZ - VERTICAL'!$O$6:$O$546,'BM MORRO DA CRUZ'!$K41),0) -> 0 | AC41: =ROUND(AB41*$P41,2) -> 0 | AD41: =IFERROR(SUMIFS('BM MORRO DA CRUZ - VERTICAL'!AH$6:AH$546,'BM MORRO DA CRUZ - VERTICAL'!$O$6:$O$546,'BM MORRO DA CRUZ'!$K41),0) -> 0 | AE41: =ROUND(AD41*$P41,2) -> 0 | AF41: =IFERROR(SUMIFS('BM MORRO DA CRUZ - VERTICAL'!AJ$6:AJ$546,'BM MORRO DA CRUZ - VERTICAL'!$O$6:$O$546,'BM MORRO DA CRUZ'!$K41),0) -> 0 | AG41: =ROUND(AF41*$P41,2) -> 0 | AH41: =IFERROR(SUMIFS('BM MORRO DA CRUZ - VERTICAL'!AL$6:AL$546,'BM MORRO DA CRUZ - VERTICAL'!$O$6:$O$546,'BM MORRO DA CRUZ'!$K41),0) -> 0 | AI41: =ROUND(AH41*$P41,2) -> 0 | AJ41: =IFERROR(SUMIFS('BM MORRO DA CRUZ - VERTICAL'!AN$6:AN$546,'BM MORRO DA CRUZ - VERTICAL'!$O$6:$O$546,'BM MORRO DA CRUZ'!$K41),0) -> 0 | AK41: =ROUND(AJ41*$P41,2) -> 0 | AL41: =IFERROR(SUMIFS('BM MORRO DA CRUZ - VERTICAL'!AP$6:AP$546,'BM MORRO DA CRUZ - VERTICAL'!$O$6:$O$546,'BM MORRO DA CRUZ'!$K41),0) -> 0 | AM41: =ROUND(AL41*$P41,2) -> 0 | AN41: =IFERROR(SUMIFS('BM MORRO DA CRUZ - VERTICAL'!AR$6:AR$546,'BM MORRO DA CRUZ - VERTICAL'!$O$6:$O$546,'BM MORRO DA CRUZ'!$K41),0) -> 0 | AO41: =ROUND(AN41*$P41,2) -> 0 | AP41: =IFERROR(SUMIFS('BM MORRO DA CRUZ - VERTICAL'!AT$6:AT$546,'BM MORRO DA CRUZ - VERTICAL'!$O$6:$O$546,'BM MORRO DA CRUZ'!$K41),0) -> 0 | AQ41: =ROUND(AP41*$P41,2) -> 0 | AR41: =IFERROR(SUMIFS('BM MORRO DA CRUZ - VERTICAL'!AV$6:AV$546,'BM MORRO DA CRUZ - VERTICAL'!$O$6:$O$546,'BM MORRO DA CRUZ'!$K41),0) -> 0 | AS41: =ROUND(AR41*$P41,2) -> 0 | AT41: =IFERROR(SUMIFS('BM MORRO DA CRUZ - VERTICAL'!AX$6:AX$546,'BM MORRO DA CRUZ - VERTICAL'!$O$6:$O$546,'BM MORRO DA CRUZ'!$K41),0) -> 0 | AU41: =ROUND(AT41*$P41,2) -> 0 | AV41: =IFERROR(SUMIFS('BM MORRO DA CRUZ - VERTICAL'!AZ$6:AZ$546,'BM MORRO DA CRUZ - VERTICAL'!$O$6:$O$546,'BM MORRO DA CRUZ'!$K41),0) -> 0 | AW41: =ROUND(AV41*$P41,2) -> 0 | AX41: =IFERROR(SUMIFS('BM MORRO DA CRUZ - VERTICAL'!BB$6:BB$546,'BM MORRO DA CRUZ - VERTICAL'!$O$6:$O$546,'BM MORRO DA CRUZ'!$K41),0) -> 0 | AY41: =ROUND(AX41*$P41,2) -> 0 | AZ41: =IFERROR(SUMIFS('BM MORRO DA CRUZ - VERTICAL'!BD$6:BD$546,'BM MORRO DA CRUZ - VERTICAL'!$O$6:$O$546,'BM MORRO DA CRUZ'!$K41),0) -> 0 | BA41: =ROUND(AZ41*$P41,2) -> 0 | BB41: =IFERROR(SUMIFS($R41:$BA41,$R$5:$BA$5,$BB$5),0) -> 0 | BC41: =SUMIFS($R41:$BA41,$R$5:$BA$5,$S$5) -> 0 | BD41: =IFERROR(BB41/O41,0) -> 0 | BE41: =IFERROR((O41-BB41)/O41,0) -> 1
A42: 1.10.16 | B42: VÁLVULA GAVETA FF CUNHA BORRACHA CC - ACIONAMENTO CABEÇOTE | C42: PN10/16 | D42: N/A | E42: VÁLVULA GAVETA | F42: N/A | G42: 80 | H42: FºFº | I42: HIDROMECÂNICO | J42: VÁLVULA | K42: 1511003138042 | L42: MATERIAL | M42: VÁLVULA DE GAVETA FLANGEADA DE FERRO FUNDIDO DÚCTIL COM CUNHA DE BORRACHA, CORPO CURTO E ACIONAMENTO COM CABEÇOTE (CLASSE DE PRESSÃO: 10/16 KGF/CM² / DIÂMETRO DA SEÇÃO: 80 MM) | N42: UN | O42: 35 | P42: 745.07 | Q42: =ROUND(P42*$O42,2) -> 26077.45 | R42: =IFERROR(SUMIFS('BM MORRO DA CRUZ - VERTICAL'!V$6:V$546,'BM MORRO DA CRUZ - VERTICAL'!$O$6:$O$546,'BM MORRO DA CRUZ'!$K42),0) -> 0 | S42: =ROUND(R42*$P42,2) -> 0 | T42: =IFERROR(SUMIFS('BM MORRO DA CRUZ - VERTICAL'!X$6:X$546,'BM MORRO DA CRUZ - VERTICAL'!$O$6:$O$546,'BM MORRO DA CRUZ'!$K42),0) -> 0 | U42: =ROUND(T42*$P42,2) -> 0 | V42: =IFERROR(SUMIFS('BM MORRO DA CRUZ - VERTICAL'!Z$6:Z$546,'BM MORRO DA CRUZ - VERTICAL'!$O$6:$O$546,'BM MORRO DA CRUZ'!$K42),0) -> 0 | W42: =ROUND(V42*$P42,2) -> 0 | X42: =IFERROR(SUMIFS('BM MORRO DA CRUZ - VERTICAL'!AB$6:AB$546,'BM MORRO DA CRUZ - VERTICAL'!$O$6:$O$546,'BM MORRO DA CRUZ'!$K42),0) -> 0 | Y42: =ROUND(X42*$P42,2) -> 0 | Z42: =IFERROR(SUMIFS('BM MORRO DA CRUZ - VERTICAL'!AD$6:AD$546,'BM MORRO DA CRUZ - VERTICAL'!$O$6:$O$546,'BM MORRO DA CRUZ'!$K42),0) -> 0 | AA42: =ROUND(Z42*$P42,2) -> 0 | AB42: =IFERROR(SUMIFS('BM MORRO DA CRUZ - VERTICAL'!AF$6:AF$546,'BM MORRO DA CRUZ - VERTICAL'!$O$6:$O$546,'BM MORRO DA CRUZ'!$K42),0) -> 0 | AC42: =ROUND(AB42*$P42,2) -> 0 | AD42: =IFERROR(SUMIFS('BM MORRO DA CRUZ - VERTICAL'!AH$6:AH$546,'BM MORRO DA CRUZ - VERTICAL'!$O$6:$O$546,'BM MORRO DA CRUZ'!$K42),0) -> 0 | AE42: =ROUND(AD42*$P42,2) -> 0 | AF42: =IFERROR(SUMIFS('BM MORRO DA CRUZ - VERTICAL'!AJ$6:AJ$546,'BM MORRO DA CRUZ - VERTICAL'!$O$6:$O$546,'BM MORRO DA CRUZ'!$K42),0) -> 0 | AG42: =ROUND(AF42*$P42,2) -> 0 | AH42: =IFERROR(SUMIFS('BM MORRO DA CRUZ - VERTICAL'!AL$6:AL$546,'BM MORRO DA CRUZ - VERTICAL'!$O$6:$O$546,'BM MORRO DA CRUZ'!$K42),0) -> 0 | AI42: =ROUND(AH42*$P42,2) -> 0 | AJ42: =IFERROR(SUMIFS('BM MORRO DA CRUZ - VERTICAL'!AN$6:AN$546,'BM MORRO DA CRUZ - VERTICAL'!$O$6:$O$546,'BM MORRO DA CRUZ'!$K42),0) -> 0 | AK42: =ROUND(AJ42*$P42,2) -> 0 | AL42: =IFERROR(SUMIFS('BM MORRO DA CRUZ - VERTICAL'!AP$6:AP$546,'BM MORRO DA CRUZ - VERTICAL'!$O$6:$O$546,'BM MORRO DA CRUZ'!$K42),0) -> 0 | AM42: =ROUND(AL42*$P42,2) -> 0 | AN42: =IFERROR(SUMIFS('BM MORRO DA CRUZ - VERTICAL'!AR$6:AR$546,'BM MORRO DA CRUZ - VERTICAL'!$O$6:$O$546,'BM MORRO DA CRUZ'!$K42),0) -> 0 | AO42: =ROUND(AN42*$P42,2) -> 0 | AP42: =IFERROR(SUMIFS('BM MORRO DA CRUZ - VERTICAL'!AT$6:AT$546,'BM MORRO DA CRUZ - VERTICAL'!$O$6:$O$546,'BM MORRO DA CRUZ'!$K42),0) -> 0 | AQ42: =ROUND(AP42*$P42,2) -> 0 | AR42: =IFERROR(SUMIFS('BM MORRO DA CRUZ - VERTICAL'!AV$6:AV$546,'BM MORRO DA CRUZ - VERTICAL'!$O$6:$O$546,'BM MORRO DA CRUZ'!$K42),0) -> 0 | AS42: =ROUND(AR42*$P42,2) -> 0 | AT42: =IFERROR(SUMIFS('BM MORRO DA CRUZ - VERTICAL'!AX$6:AX$546,'BM MORRO DA CRUZ - VERTICAL'!$O$6:$O$546,'BM MORRO DA CRUZ'!$K42),0) -> 0 | AU42: =ROUND(AT42*$P42,2) -> 0 | AV42: =IFERROR(SUMIFS('BM MORRO DA CRUZ - VERTICAL'!AZ$6:AZ$546,'BM MORRO DA CRUZ - VERTICAL'!$O$6:$O$546,'BM MORRO DA CRUZ'!$K42),0) -> 0 | AW42: =ROUND(AV42*$P42,2) -> 0 | AX42: =IFERROR(SUMIFS('BM MORRO DA CRUZ - VERTICAL'!BB$6:BB$546,'BM MORRO DA CRUZ - VERTICAL'!$O$6:$O$546,'BM MORRO DA CRUZ'!$K42),0) -> 0 | AY42: =ROUND(AX42*$P42,2) -> 0 | AZ42: =IFERROR(SUMIFS('BM MORRO DA CRUZ - VERTICAL'!BD$6:BD$546,'BM MORRO DA CRUZ - VERTICAL'!$O$6:$O$546,'BM MORRO DA CRUZ'!$K42),0) -> 0 | BA42: =ROUND(AZ42*$P42,2) -> 0 | BB42: =IFERROR(SUMIFS($R42:$BA42,$R$5:$BA$5,$BB$5),0) -> 0 | BC42: =SUMIFS($R42:$BA42,$R$5:$BA$5,$S$5) -> 0 | BD42: =IFERROR(BB42/O42,0) -> 0 | BE42: =IFERROR((O42-BB42)/O42,0) -> 1
A43: 1.10.17 | B43: VÁLVULA SUSTENTADORA E REDUTORA DE PRESSÃO | C43: PN10 | D43: N/A | E43: VRP | F43: N/A | G43: 300 | H43: FºFº | I43: HIDROMECÂNICO | J43: VÁLVULA | K43: 1511003043XX19 | L43: MATERIAL | M43: VÁLVULA SUSTENTADORA E REDUTORA DE PRESSÃO, DN 300MM, PN 10, FLANGES NBR 7675. - VÁLVULA PRINCIPAL: CORPO EM F°F° DÚCTIL, REVESTIMENTO FBE, MOLA AÇO INOX, DIAFRAGMA DE BORRACHA NATURAL REFORÇADA C/ NYLON, MANGUEIRAS DO SISTEMA DE CONTROLE EM BORRACHA | N43: UN | O43: 1 | P43: 29340 | Q43: =ROUND(P43*$O43,2) -> 29340 | R43: =IFERROR(SUMIFS('BM MORRO DA CRUZ - VERTICAL'!V$6:V$546,'BM MORRO DA CRUZ - VERTICAL'!$O$6:$O$546,'BM MORRO DA CRUZ'!$K43),0) -> 0 | S43: =ROUND(R43*$P43,2) -> 0 | T43: =IFERROR(SUMIFS('BM MORRO DA CRUZ - VERTICAL'!X$6:X$546,'BM MORRO DA CRUZ - VERTICAL'!$O$6:$O$546,'BM MORRO DA CRUZ'!$K43),0) -> 0 | U43: =ROUND(T43*$P43,2) -> 0 | V43: =IFERROR(SUMIFS('BM MORRO DA CRUZ - VERTICAL'!Z$6:Z$546,'BM MORRO DA CRUZ - VERTICAL'!$O$6:$O$546,'BM MORRO DA CRUZ'!$K43),0) -> 0 | W43: =ROUND(V43*$P43,2) -> 0 | X43: =IFERROR(SUMIFS('BM MORRO DA CRUZ - VERTICAL'!AB$6:AB$546,'BM MORRO DA CRUZ - VERTICAL'!$O$6:$O$546,'BM MORRO DA CRUZ'!$K43),0) -> 0 | Y43: =ROUND(X43*$P43,2) -> 0 | Z43: =IFERROR(SUMIFS('BM MORRO DA CRUZ - VERTICAL'!AD$6:AD$546,'BM MORRO DA CRUZ - VERTICAL'!$O$6:$O$546,'BM MORRO DA CRUZ'!$K43),0) -> 0 | AA43: =ROUND(Z43*$P43,2) -> 0 | AB43: =IFERROR(SUMIFS('BM MORRO DA CRUZ - VERTICAL'!AF$6:AF$546,'BM MORRO DA CRUZ - VERTICAL'!$O$6:$O$546,'BM MORRO DA CRUZ'!$K43),0) -> 0 | AC43: =ROUND(AB43*$P43,2) -> 0 | AD43: =IFERROR(SUMIFS('BM MORRO DA CRUZ - VERTICAL'!AH$6:AH$546,'BM MORRO DA CRUZ - VERTICAL'!$O$6:$O$546,'BM MORRO DA CRUZ'!$K43),0) -> 0 | AE43: =ROUND(AD43*$P43,2) -> 0 | AF43: =IFERROR(SUMIFS('BM MORRO DA CRUZ - VERTICAL'!AJ$6:AJ$546,'BM MORRO DA CRUZ - VERTICAL'!$O$6:$O$546,'BM MORRO DA CRUZ'!$K43),0) -> 0 | AG43: =ROUND(AF43*$P43,2) -> 0 | AH43: =IFERROR(SUMIFS('BM MORRO DA CRUZ - VERTICAL'!AL$6:AL$546,'BM MORRO DA CRUZ - VERTICAL'!$O$6:$O$546,'BM MORRO DA CRUZ'!$K43),0) -> 0 | AI43: =ROUND(AH43*$P43,2) -> 0 | AJ43: =IFERROR(SUMIFS('BM MORRO DA CRUZ - VERTICAL'!AN$6:AN$546,'BM MORRO DA CRUZ - VERTICAL'!$O$6:$O$546,'BM MORRO DA CRUZ'!$K43),0) -> 0 | AK43: =ROUND(AJ43*$P43,2) -> 0 | AL43: =IFERROR(SUMIFS('BM MORRO DA CRUZ - VERTICAL'!AP$6:AP$546,'BM MORRO DA CRUZ - VERTICAL'!$O$6:$O$546,'BM MORRO DA CRUZ'!$K43),0) -> 0 | AM43: =ROUND(AL43*$P43,2) -> 0 | AN43: =IFERROR(SUMIFS('BM MORRO DA CRUZ - VERTICAL'!AR$6:AR$546,'BM MORRO DA CRUZ - VERTICAL'!$O$6:$O$546,'BM MORRO DA CRUZ'!$K43),0) -> 0 | AO43: =ROUND(AN43*$P43,2) -> 0 | AP43: =IFERROR(SUMIFS('BM MORRO DA CRUZ - VERTICAL'!AT$6:AT$546,'BM MORRO DA CRUZ - VERTICAL'!$O$6:$O$546,'BM MORRO DA CRUZ'!$K43),0) -> 0 | AQ43: =ROUND(AP43*$P43,2) -> 0 | AR43: =IFERROR(SUMIFS('BM MORRO DA CRUZ - VERTICAL'!AV$6:AV$546,'BM MORRO DA CRUZ - VERTICAL'!$O$6:$O$546,'BM MORRO DA CRUZ'!$K43),0) -> 0 | AS43: =ROUND(AR43*$P43,2) -> 0 | AT43: =IFERROR(SUMIFS('BM MORRO DA CRUZ - VERTICAL'!AX$6:AX$546,'BM MORRO DA CRUZ - VERTICAL'!$O$6:$O$546,'BM MORRO DA CRUZ'!$K43),0) -> 0 | AU43: =ROUND(AT43*$P43,2) -> 0 | AV43: =IFERROR(SUMIFS('BM MORRO DA CRUZ - VERTICAL'!AZ$6:AZ$546,'BM MORRO DA CRUZ - VERTICAL'!$O$6:$O$546,'BM MORRO DA CRUZ'!$K43),0) -> 0 | AW43: =ROUND(AV43*$P43,2) -> 0 | AX43: =IFERROR(SUMIFS('BM MORRO DA CRUZ - VERTICAL'!BB$6:BB$546,'BM MORRO DA CRUZ - VERTICAL'!$O$6:$O$546,'BM MORRO DA CRUZ'!$K43),0) -> 0 | AY43: =ROUND(AX43*$P43,2) -> 0 | AZ43: =IFERROR(SUMIFS('BM MORRO DA CRUZ - VERTICAL'!BD$6:BD$546,'BM MORRO DA CRUZ - VERTICAL'!$O$6:$O$546,'BM MORRO DA CRUZ'!$K43),0) -> 0 | BA43: =ROUND(AZ43*$P43,2) -> 0 | BB43: =IFERROR(SUMIFS($R43:$BA43,$R$5:$BA$5,$BB$5),0) -> 0 | BC43: =SUMIFS($R43:$BA43,$R$5:$BA$5,$S$5) -> 0 | BD43: =IFERROR(BB43/O43,0) -> 0 | BE43: =IFERROR((O43-BB43)/O43,0) -> 1
A44: 1.10.18 | B44: VENTOSA TRÍPLICE FUNÇÃO FLANGEADA | C44: PN10 | D44: N/A | E44: VENTOSA | F44: N/A | G44: 50 | H44: FºFº | I44: HIDROMECÂNICO | J44: VÁLVULA | K44: 1511003130004 | L44: MATERIAL | M44: VENTOSA TRÍPLICE FUNÇÃO DE FERRO FUNDIDO DÚCTIL COM FLANGE (CLASSE DE PRESSÃO: 10 KGF/CM² / DIÂMETRO NOMINAL: 50 MM) | N44: UN | O44: 26 | P44: 604.83 | Q44: =ROUND(P44*$O44,2) -> 15725.58 | R44: =IFERROR(SUMIFS('BM MORRO DA CRUZ - VERTICAL'!V$6:V$546,'BM MORRO DA CRUZ - VERTICAL'!$O$6:$O$546,'BM MORRO DA CRUZ'!$K44),0) -> 0 | S44: =ROUND(R44*$P44,2) -> 0 | T44: =IFERROR(SUMIFS('BM MORRO DA CRUZ - VERTICAL'!X$6:X$546,'BM MORRO DA CRUZ - VERTICAL'!$O$6:$O$546,'BM MORRO DA CRUZ'!$K44),0) -> 0 | U44: =ROUND(T44*$P44,2) -> 0 | V44: =IFERROR(SUMIFS('BM MORRO DA CRUZ - VERTICAL'!Z$6:Z$546,'BM MORRO DA CRUZ - VERTICAL'!$O$6:$O$546,'BM MORRO DA CRUZ'!$K44),0) -> 0 | W44: =ROUND(V44*$P44,2) -> 0 | X44: =IFERROR(SUMIFS('BM MORRO DA CRUZ - VERTICAL'!AB$6:AB$546,'BM MORRO DA CRUZ - VERTICAL'!$O$6:$O$546,'BM MORRO DA CRUZ'!$K44),0) -> 0 | Y44: =ROUND(X44*$P44,2) -> 0 | Z44: =IFERROR(SUMIFS('BM MORRO DA CRUZ - VERTICAL'!AD$6:AD$546,'BM MORRO DA CRUZ - VERTICAL'!$O$6:$O$546,'BM MORRO DA CRUZ'!$K44),0) -> 0 | AA44: =ROUND(Z44*$P44,2) -> 0 | AB44: =IFERROR(SUMIFS('BM MORRO DA CRUZ - VERTICAL'!AF$6:AF$546,'BM MORRO DA CRUZ - VERTICAL'!$O$6:$O$546,'BM MORRO DA CRUZ'!$K44),0) -> 0 | AC44: =ROUND(AB44*$P44,2) -> 0 | AD44: =IFERROR(SUMIFS('BM MORRO DA CRUZ - VERTICAL'!AH$6:AH$546,'BM MORRO DA CRUZ - VERTICAL'!$O$6:$O$546,'BM MORRO DA CRUZ'!$K44),0) -> 0 | AE44: =ROUND(AD44*$P44,2) -> 0 | AF44: =IFERROR(SUMIFS('BM MORRO DA CRUZ - VERTICAL'!AJ$6:AJ$546,'BM MORRO DA CRUZ - VERTICAL'!$O$6:$O$546,'BM MORRO DA CRUZ'!$K44),0) -> 0 | AG44: =ROUND(AF44*$P44,2) -> 0 | AH44: =IFERROR(SUMIFS('BM MORRO DA CRUZ - VERTICAL'!AL$6:AL$546,'BM MORRO DA CRUZ - VERTICAL'!$O$6:$O$546,'BM MORRO DA CRUZ'!$K44),0) -> 0 | AI44: =ROUND(AH44*$P44,2) -> 0 | AJ44: =IFERROR(SUMIFS('BM MORRO DA CRUZ - VERTICAL'!AN$6:AN$546,'BM MORRO DA CRUZ - VERTICAL'!$O$6:$O$546,'BM MORRO DA CRUZ'!$K44),0) -> 0 | AK44: =ROUND(AJ44*$P44,2) -> 0 | AL44: =IFERROR(SUMIFS('BM MORRO DA CRUZ - VERTICAL'!AP$6:AP$546,'BM MORRO DA CRUZ - VERTICAL'!$O$6:$O$546,'BM MORRO DA CRUZ'!$K44),0) -> 0 | AM44: =ROUND(AL44*$P44,2) -> 0 | AN44: =IFERROR(SUMIFS('BM MORRO DA CRUZ - VERTICAL'!AR$6:AR$546,'BM MORRO DA CRUZ - VERTICAL'!$O$6:$O$546,'BM MORRO DA CRUZ'!$K44),0) -> 0 | AO44: =ROUND(AN44*$P44,2) -> 0 | AP44: =IFERROR(SUMIFS('BM MORRO DA CRUZ - VERTICAL'!AT$6:AT$546,'BM MORRO DA CRUZ - VERTICAL'!$O$6:$O$546,'BM MORRO DA CRUZ'!$K44),0) -> 0 | AQ44: =ROUND(AP44*$P44,2) -> 0 | AR44: =IFERROR(SUMIFS('BM MORRO DA CRUZ - VERTICAL'!AV$6:AV$546,'BM MORRO DA CRUZ - VERTICAL'!$O$6:$O$546,'BM MORRO DA CRUZ'!$K44),0) -> 0 | AS44: =ROUND(AR44*$P44,2) -> 0 | AT44: =IFERROR(SUMIFS('BM MORRO DA CRUZ - VERTICAL'!AX$6:AX$546,'BM MORRO DA CRUZ - VERTICAL'!$O$6:$O$546,'BM MORRO DA CRUZ'!$K44),0) -> 0 | AU44: =ROUND(AT44*$P44,2) -> 0 | AV44: =IFERROR(SUMIFS('BM MORRO DA CRUZ - VERTICAL'!AZ$6:AZ$546,'BM MORRO DA CRUZ - VERTICAL'!$O$6:$O$546,'BM MORRO DA CRUZ'!$K44),0) -> 0 | AW44: =ROUND(AV44*$P44,2) -> 0 | AX44: =IFERROR(SUMIFS('BM MORRO DA CRUZ - VERTICAL'!BB$6:BB$546,'BM MORRO DA CRUZ - VERTICAL'!$O$6:$O$546,'BM MORRO DA CRUZ'!$K44),0) -> 0 | AY44: =ROUND(AX44*$P44,2) -> 0 | AZ44: =IFERROR(SUMIFS('BM MORRO DA CRUZ - VERTICAL'!BD$6:BD$546,'BM MORRO DA CRUZ - VERTICAL'!$O$6:$O$546,'BM MORRO DA CRUZ'!$K44),0) -> 0 | BA44: =ROUND(AZ44*$P44,2) -> 0 | BB44: =IFERROR(SUMIFS($R44:$BA44,$R$5:$BA$5,$BB$5),0) -> 0 | BC44: =SUMIFS($R44:$BA44,$R$5:$BA$5,$S$5) -> 0 | BD44: =IFERROR(BB44/O44,0) -> 0 | BE44: =IFERROR((O44-BB44)/O44,0) -> 1
A45: 1.11 | K45: 15120 | M45: PRODUTOS ESPECIAIS PARA TUBULAÇÕES | Q45: =SUM(Q46:Q47) -> 1435737.4 | S45: =SUM(S46:S47) -> 0 | U45: =SUM(U46:U47) -> 0 | W45: =SUM(W46:W47) -> 0 | Y45: =SUM(Y46:Y47) -> 0 | AA45: =SUM(AA46:AA47) -> 0 | AC45: =SUM(AC46:AC47) -> 0 | AE45: =SUM(AE46:AE47) -> 0 | AG45: =SUM(AG46:AG47) -> 0 | AI45: =SUM(AI46:AI47) -> 0 | AK45: =SUM(AK46:AK47) -> 0 | AM45: =SUM(AM46:AM47) -> 0 | AO45: =SUM(AO46:AO47) -> 0 | AQ45: =SUM(AQ46:AQ47) -> 0 | AS45: =SUM(AS46:AS47) -> 0 | AU45: =SUM(AU46:AU47) -> 0 | AW45: =SUM(AW46:AW47) -> 0 | AY45: =SUM(AY46:AY47) -> 0 | BA45: =SUM(BA46:BA47) -> 0 | BC45: =SUM(BC46:BC47) -> 0
A46: 1.11.1 | B46: CAIXA DE PROTEÇÃO PARA 01 HIDRÔMETRO - PADRÃO CAESB | C46: N/A | D46: N/A | E46: CAIXA PROTEÇÃO | F46: N/A | G46: 50X40 | H46: PLÁSTICO | I46: CANTEIRO | J46: CX HIDRÔMETRO | K46: 1512003007001 | L46: MATERIAL | M46: CAIXA DE PROTEÇÃO PARA 01 HIDRÔMETRO - PADRÃO CAESB | N46: UN | O46: 1 | P46: 129.9 | Q46: =ROUND(P46*$O46,2) -> 129.9 | R46: =IFERROR(SUMIFS('BM MORRO DA CRUZ - VERTICAL'!V$6:V$546,'BM MORRO DA CRUZ - VERTICAL'!$O$6:$O$546,'BM MORRO DA CRUZ'!$K46),0) -> 0 | S46: =ROUND(R46*$P46,2) -> 0 | T46: =IFERROR(SUMIFS('BM MORRO DA CRUZ - VERTICAL'!X$6:X$546,'BM MORRO DA CRUZ - VERTICAL'!$O$6:$O$546,'BM MORRO DA CRUZ'!$K46),0) -> 0 | U46: =ROUND(T46*$P46,2) -> 0 | V46: =IFERROR(SUMIFS('BM MORRO DA CRUZ - VERTICAL'!Z$6:Z$546,'BM MORRO DA CRUZ - VERTICAL'!$O$6:$O$546,'BM MORRO DA CRUZ'!$K46),0) -> 0 | W46: =ROUND(V46*$P46,2) -> 0 | X46: =IFERROR(SUMIFS('BM MORRO DA CRUZ - VERTICAL'!AB$6:AB$546,'BM MORRO DA CRUZ - VERTICAL'!$O$6:$O$546,'BM MORRO DA CRUZ'!$K46),0) -> 0 | Y46: =ROUND(X46*$P46,2) -> 0 | Z46: =IFERROR(SUMIFS('BM MORRO DA CRUZ - VERTICAL'!AD$6:AD$546,'BM MORRO DA CRUZ - VERTICAL'!$O$6:$O$546,'BM MORRO DA CRUZ'!$K46),0) -> 0 | AA46: =ROUND(Z46*$P46,2) -> 0 | AB46: =IFERROR(SUMIFS('BM MORRO DA CRUZ - VERTICAL'!AF$6:AF$546,'BM MORRO DA CRUZ - VERTICAL'!$O$6:$O$546,'BM MORRO DA CRUZ'!$K46),0) -> 0 | AC46: =ROUND(AB46*$P46,2) -> 0 | AD46: =IFERROR(SUMIFS('BM MORRO DA CRUZ - VERTICAL'!AH$6:AH$546,'BM MORRO DA CRUZ - VERTICAL'!$O$6:$O$546,'BM MORRO DA CRUZ'!$K46),0) -> 0 | AE46: =ROUND(AD46*$P46,2) -> 0 | AF46: =IFERROR(SUMIFS('BM MORRO DA CRUZ - VERTICAL'!AJ$6:AJ$546,'BM MORRO DA CRUZ - VERTICAL'!$O$6:$O$546,'BM MORRO DA CRUZ'!$K46),0) -> 0 | AG46: =ROUND(AF46*$P46,2) -> 0 | AH46: =IFERROR(SUMIFS('BM MORRO DA CRUZ - VERTICAL'!AL$6:AL$546,'BM MORRO DA CRUZ - VERTICAL'!$O$6:$O$546,'BM MORRO DA CRUZ'!$K46),0) -> 0 | AI46: =ROUND(AH46*$P46,2) -> 0 | AJ46: =IFERROR(SUMIFS('BM MORRO DA CRUZ - VERTICAL'!AN$6:AN$546,'BM MORRO DA CRUZ - VERTICAL'!$O$6:$O$546,'BM MORRO DA CRUZ'!$K46),0) -> 0 | AK46: =ROUND(AJ46*$P46,2) -> 0 | AL46: =IFERROR(SUMIFS('BM MORRO DA CRUZ - VERTICAL'!AP$6:AP$546,'BM MORRO DA CRUZ - VERTICAL'!$O$6:$O$546,'BM MORRO DA CRUZ'!$K46),0) -> 0 | AM46: =ROUND(AL46*$P46,2) -> 0 | AN46: =IFERROR(SUMIFS('BM MORRO DA CRUZ - VERTICAL'!AR$6:AR$546,'BM MORRO DA CRUZ - VERTICAL'!$O$6:$O$546,'BM MORRO DA CRUZ'!$K46),0) -> 0 | AO46: =ROUND(AN46*$P46,2) -> 0 | AP46: =IFERROR(SUMIFS('BM MORRO DA CRUZ - VERTICAL'!AT$6:AT$546,'BM MORRO DA CRUZ - VERTICAL'!$O$6:$O$546,'BM MORRO DA CRUZ'!$K46),0) -> 0 | AQ46: =ROUND(AP46*$P46,2) -> 0 | AR46: =IFERROR(SUMIFS('BM MORRO DA CRUZ - VERTICAL'!AV$6:AV$546,'BM MORRO DA CRUZ - VERTICAL'!$O$6:$O$546,'BM MORRO DA CRUZ'!$K46),0) -> 0 | AS46: =ROUND(AR46*$P46,2) -> 0 | AT46: =IFERROR(SUMIFS('BM MORRO DA CRUZ - VERTICAL'!AX$6:AX$546,'BM MORRO DA CRUZ - VERTICAL'!$O$6:$O$546,'BM MORRO DA CRUZ'!$K46),0) -> 0 | AU46: =ROUND(AT46*$P46,2) -> 0 | AV46: =IFERROR(SUMIFS('BM MORRO DA CRUZ - VERTICAL'!AZ$6:AZ$546,'BM MORRO DA CRUZ - VERTICAL'!$O$6:$O$546,'BM MORRO DA CRUZ'!$K46),0) -> 0 | AW46: =ROUND(AV46*$P46,2) -> 0 | AX46: =IFERROR(SUMIFS('BM MORRO DA CRUZ - VERTICAL'!BB$6:BB$546,'BM MORRO DA CRUZ - VERTICAL'!$O$6:$O$546,'BM MORRO DA CRUZ'!$K46),0) -> 0 | AY46: =ROUND(AX46*$P46,2) -> 0 | AZ46: =IFERROR(SUMIFS('BM MORRO DA CRUZ - VERTICAL'!BD$6:BD$546,'BM MORRO DA CRUZ - VERTICAL'!$O$6:$O$546,'BM MORRO DA CRUZ'!$K46),0) -> 0 | BA46: =ROUND(AZ46*$P46,2) -> 0 | BB46: =IFERROR(SUMIFS($R46:$BA46,$R$5:$BA$5,$BB$5),0) -> 0 | BC46: =SUMIFS($R46:$BA46,$R$5:$BA$5,$S$5) -> 0 | BD46: =IFERROR(BB46/O46,0) -> 0 | BE46: =IFERROR((O46-BB46)/O46,0) -> 1
A47: 1.11.2 | B47: HIDRÔMETRO UNIJATO COM CORPO EM COBRE | C47: N/A | D47: N/A | E47: HIDRÔMETRO | F47: N/A | G47: 3/4" | H47: COBRE | I47: CANTEIRO/LIGAÇÕES | J47: OUTROS | K47: 1512003001034 | L47: MATERIAL | M47: HIDRÔMETRO UNIJATO COM CORPO EM COBRE (CLASSE: B / DIÂMETRO NOMINAL: 3/4" OU 20 MM / VAZÃO MÁXIMA: 1,5 M³/H / COMPRIMENTO: 115 MM) | N47: UN | O47: 11895 | P47: 120.69 | Q47: =ROUND(P47*$O47,2) -> 1435607.6 | R47: =IFERROR(SUMIFS('BM MORRO DA CRUZ - VERTICAL'!V$6:V$546,'BM MORRO DA CRUZ - VERTICAL'!$O$6:$O$546,'BM MORRO DA CRUZ'!$K47),0) -> 0 | S47: =ROUND(R47*$P47,2) -> 0 | T47: =IFERROR(SUMIFS('BM MORRO DA CRUZ - VERTICAL'!X$6:X$546,'BM MORRO DA CRUZ - VERTICAL'!$O$6:$O$546,'BM MORRO DA CRUZ'!$K47),0) -> 0 | U47: =ROUND(T47*$P47,2) -> 0 | V47: =IFERROR(SUMIFS('BM MORRO DA CRUZ - VERTICAL'!Z$6:Z$546,'BM MORRO DA CRUZ - VERTICAL'!$O$6:$O$546,'BM MORRO DA CRUZ'!$K47),0) -> 0 | W47: =ROUND(V47*$P47,2) -> 0 | X47: =IFERROR(SUMIFS('BM MORRO DA CRUZ - VERTICAL'!AB$6:AB$546,'BM MORRO DA CRUZ - VERTICAL'!$O$6:$O$546,'BM MORRO DA CRUZ'!$K47),0) -> 0 | Y47: =ROUND(X47*$P47,2) -> 0 | Z47: =IFERROR(SUMIFS('BM MORRO DA CRUZ - VERTICAL'!AD$6:AD$546,'BM MORRO DA CRUZ - VERTICAL'!$O$6:$O$546,'BM MORRO DA CRUZ'!$K47),0) -> 0 | AA47: =ROUND(Z47*$P47,2) -> 0 | AB47: =IFERROR(SUMIFS('BM MORRO DA CRUZ - VERTICAL'!AF$6:AF$546,'BM MORRO DA CRUZ - VERTICAL'!$O$6:$O$546,'BM MORRO DA CRUZ'!$K47),0) -> 0 | AC47: =ROUND(AB47*$P47,2) -> 0 | AD47: =IFERROR(SUMIFS('BM MORRO DA CRUZ - VERTICAL'!AH$6:AH$546,'BM MORRO DA CRUZ - VERTICAL'!$O$6:$O$546,'BM MORRO DA CRUZ'!$K47),0) -> 0 | AE47: =ROUND(AD47*$P47,2) -> 0 | AF47: =IFERROR(SUMIFS('BM MORRO DA CRUZ - VERTICAL'!AJ$6:AJ$546,'BM MORRO DA CRUZ - VERTICAL'!$O$6:$O$546,'BM MORRO DA CRUZ'!$K47),0) -> 0 | AG47: =ROUND(AF47*$P47,2) -> 0 | AH47: =IFERROR(SUMIFS('BM MORRO DA CRUZ - VERTICAL'!AL$6:AL$546,'BM MORRO DA CRUZ - VERTICAL'!$O$6:$O$546,'BM MORRO DA CRUZ'!$K47),0) -> 0 | AI47: =ROUND(AH47*$P47,2) -> 0 | AJ47: =IFERROR(SUMIFS('BM MORRO DA CRUZ - VERTICAL'!AN$6:AN$546,'BM MORRO DA CRUZ - VERTICAL'!$O$6:$O$546,'BM MORRO DA CRUZ'!$K47),0) -> 0 | AK47: =ROUND(AJ47*$P47,2) -> 0 | AL47: =IFERROR(SUMIFS('BM MORRO DA CRUZ - VERTICAL'!AP$6:AP$546,'BM MORRO DA CRUZ - VERTICAL'!$O$6:$O$546,'BM MORRO DA CRUZ'!$K47),0) -> 0 | AM47: =ROUND(AL47*$P47,2) -> 0 | AN47: =IFERROR(SUMIFS('BM MORRO DA CRUZ - VERTICAL'!AR$6:AR$546,'BM MORRO DA CRUZ - VERTICAL'!$O$6:$O$546,'BM MORRO DA CRUZ'!$K47),0) -> 0 | AO47: =ROUND(AN47*$P47,2) -> 0 | AP47: =IFERROR(SUMIFS('BM MORRO DA CRUZ - VERTICAL'!AT$6:AT$546,'BM MORRO DA CRUZ - VERTICAL'!$O$6:$O$546,'BM MORRO DA CRUZ'!$K47),0) -> 0 | AQ47: =ROUND(AP47*$P47,2) -> 0 | AR47: =IFERROR(SUMIFS('BM MORRO DA CRUZ - VERTICAL'!AV$6:AV$546,'BM MORRO DA CRUZ - VERTICAL'!$O$6:$O$546,'BM MORRO DA CRUZ'!$K47),0) -> 0 | AS47: =ROUND(AR47*$P47,2) -> 0 | AT47: =IFERROR(SUMIFS('BM MORRO DA CRUZ - VERTICAL'!AX$6:AX$546,'BM MORRO DA CRUZ - VERTICAL'!$O$6:$O$546,'BM MORRO DA CRUZ'!$K47),0) -> 0 | AU47: =ROUND(AT47*$P47,2) -> 0 | AV47: =IFERROR(SUMIFS('BM MORRO DA CRUZ - VERTICAL'!AZ$6:AZ$546,'BM MORRO DA CRUZ - VERTICAL'!$O$6:$O$546,'BM MORRO DA CRUZ'!$K47),0) -> 0 | AW47: =ROUND(AV47*$P47,2) -> 0 | AX47: =IFERROR(SUMIFS('BM MORRO DA CRUZ - VERTICAL'!BB$6:BB$546,'BM MORRO DA CRUZ - VERTICAL'!$O$6:$O$546,'BM MORRO DA CRUZ'!$K47),0) -> 0 | AY47: =ROUND(AX47*$P47,2) -> 0 | AZ47: =IFERROR(SUMIFS('BM MORRO DA CRUZ - VERTICAL'!BD$6:BD$546,'BM MORRO DA CRUZ - VERTICAL'!$O$6:$O$546,'BM MORRO DA CRUZ'!$K47),0) -> 0 | BA47: =ROUND(AZ47*$P47,2) -> 0 | BB47: =IFERROR(SUMIFS($R47:$BA47,$R$5:$BA$5,$BB$5),0) -> 0 | BC47: =SUMIFS($R47:$BA47,$R$5:$BA$5,$S$5) -> 0 | BD47: =IFERROR(BB47/O47,0) -> 0 | BE47: =IFERROR((O47-BB47)/O47,0) -> 1
A48: 1.12 | K48: 15139 | M48: TUBOS E CONEXÕES DE AÇO CARBONO - LÍQUIDOS, GASES E VAPORES | Q48: =SUM(Q49:Q56) -> 40620.11 | S48: =SUM(S49:S56) -> 0 | U48: =SUM(U49:U56) -> 0 | W48: =SUM(W49:W56) -> 0 | Y48: =SUM(Y49:Y56) -> 0 | AA48: =SUM(AA49:AA56) -> 0 | AC48: =SUM(AC49:AC56) -> 0 | AE48: =SUM(AE49:AE56) -> 0 | AG48: =SUM(AG49:AG56) -> 0 | AI48: =SUM(AI49:AI56) -> 0 | AK48: =SUM(AK49:AK56) -> 0 | AM48: =SUM(AM49:AM56) -> 0 | AO48: =SUM(AO49:AO56) -> 0 | AQ48: =SUM(AQ49:AQ56) -> 0 | AS48: =SUM(AS49:AS56) -> 0 | AU48: =SUM(AU49:AU56) -> 0 | AW48: =SUM(AW49:AW56) -> 0 | AY48: =SUM(AY49:AY56) -> 0 | BA48: =SUM(BA49:BA56) -> 0 | BC48: =SUM(BC49:BC56) -> 0
A49: 1.12.1 | B49: FLANGE AVULSO P/ COLARINHO | C49: PN10 | D49: PE100 | E49: FLANGE AVULSO | F49: N/A | G49: 110 | H49: PEAD | I49: HIDROMECÂNICO | J49: OUTROS | K49: 1513903021082 | L49: MATERIAL | M49: FLANGE SOLTO, FORNECIDO EM AÇO SAE 1020, CONFORME NORMA NBR 7675/DIN (PARA COLARINHO DE PEAD / DIÂMETRO EXTERNO: 110 MM / CLASSE DE PRESSÃO: 10 KGF/CM²) | N49: UN | O49: 6 | P49: 154.77 | Q49: =ROUND(P49*$O49,2) -> 928.62 | R49: =IFERROR(SUMIFS('BM MORRO DA CRUZ - VERTICAL'!V$6:V$546,'BM MORRO DA CRUZ - VERTICAL'!$O$6:$O$546,'BM MORRO DA CRUZ'!$K49),0) -> 0 | S49: =ROUND(R49*$P49,2) -> 0 | T49: =IFERROR(SUMIFS('BM MORRO DA CRUZ - VERTICAL'!X$6:X$546,'BM MORRO DA CRUZ - VERTICAL'!$O$6:$O$546,'BM MORRO DA CRUZ'!$K49),0) -> 0 | U49: =ROUND(T49*$P49,2) -> 0 | V49: =IFERROR(SUMIFS('BM MORRO DA CRUZ - VERTICAL'!Z$6:Z$546,'BM MORRO DA CRUZ - VERTICAL'!$O$6:$O$546,'BM MORRO DA CRUZ'!$K49),0) -> 0 | W49: =ROUND(V49*$P49,2) -> 0 | X49: =IFERROR(SUMIFS('BM MORRO DA CRUZ - VERTICAL'!AB$6:AB$546,'BM MORRO DA CRUZ - VERTICAL'!$O$6:$O$546,'BM MORRO DA CRUZ'!$K49),0) -> 0 | Y49: =ROUND(X49*$P49,2) -> 0 | Z49: =IFERROR(SUMIFS('BM MORRO DA CRUZ - VERTICAL'!AD$6:AD$546,'BM MORRO DA CRUZ - VERTICAL'!$O$6:$O$546,'BM MORRO DA CRUZ'!$K49),0) -> 0 | AA49: =ROUND(Z49*$P49,2) -> 0 | AB49: =IFERROR(SUMIFS('BM MORRO DA CRUZ - VERTICAL'!AF$6:AF$546,'BM MORRO DA CRUZ - VERTICAL'!$O$6:$O$546,'BM MORRO DA CRUZ'!$K49),0) -> 0 | AC49: =ROUND(AB49*$P49,2) -> 0 | AD49: =IFERROR(SUMIFS('BM MORRO DA CRUZ - VERTICAL'!AH$6:AH$546,'BM MORRO DA CRUZ - VERTICAL'!$O$6:$O$546,'BM MORRO DA CRUZ'!$K49),0) -> 0 | AE49: =ROUND(AD49*$P49,2) -> 0 | AF49: =IFERROR(SUMIFS('BM MORRO DA CRUZ - VERTICAL'!AJ$6:AJ$546,'BM MORRO DA CRUZ - VERTICAL'!$O$6:$O$546,'BM MORRO DA CRUZ'!$K49),0) -> 0 | AG49: =ROUND(AF49*$P49,2) -> 0 | AH49: =IFERROR(SUMIFS('BM MORRO DA CRUZ - VERTICAL'!AL$6:AL$546,'BM MORRO DA CRUZ - VERTICAL'!$O$6:$O$546,'BM MORRO DA CRUZ'!$K49),0) -> 0 | AI49: =ROUND(AH49*$P49,2) -> 0 | AJ49: =IFERROR(SUMIFS('BM MORRO DA CRUZ - VERTICAL'!AN$6:AN$546,'BM MORRO DA CRUZ - VERTICAL'!$O$6:$O$546,'BM MORRO DA CRUZ'!$K49),0) -> 0 | AK49: =ROUND(AJ49*$P49,2) -> 0 | AL49: =IFERROR(SUMIFS('BM MORRO DA CRUZ - VERTICAL'!AP$6:AP$546,'BM MORRO DA CRUZ - VERTICAL'!$O$6:$O$546,'BM MORRO DA CRUZ'!$K49),0) -> 0 | AM49: =ROUND(AL49*$P49,2) -> 0 | AN49: =IFERROR(SUMIFS('BM MORRO DA CRUZ - VERTICAL'!AR$6:AR$546,'BM MORRO DA CRUZ - VERTICAL'!$O$6:$O$546,'BM MORRO DA CRUZ'!$K49),0) -> 0 | AO49: =ROUND(AN49*$P49,2) -> 0 | AP49: =IFERROR(SUMIFS('BM MORRO DA CRUZ - VERTICAL'!AT$6:AT$546,'BM MORRO DA CRUZ - VERTICAL'!$O$6:$O$546,'BM MORRO DA CRUZ'!$K49),0) -> 0 | AQ49: =ROUND(AP49*$P49,2) -> 0 | AR49: =IFERROR(SUMIFS('BM MORRO DA CRUZ - VERTICAL'!AV$6:AV$546,'BM MORRO DA CRUZ - VERTICAL'!$O$6:$O$546,'BM MORRO DA CRUZ'!$K49),0) -> 0 | AS49: =ROUND(AR49*$P49,2) -> 0 | AT49: =IFERROR(SUMIFS('BM MORRO DA CRUZ - VERTICAL'!AX$6:AX$546,'BM MORRO DA CRUZ - VERTICAL'!$O$6:$O$546,'BM MORRO DA CRUZ'!$K49),0) -> 0 | AU49: =ROUND(AT49*$P49,2) -> 0 | AV49: =IFERROR(SUMIFS('BM MORRO DA CRUZ - VERTICAL'!AZ$6:AZ$546,'BM MORRO DA CRUZ - VERTICAL'!$O$6:$O$546,'BM MORRO DA CRUZ'!$K49),0) -> 0 | AW49: =ROUND(AV49*$P49,2) -> 0 | AX49: =IFERROR(SUMIFS('BM MORRO DA CRUZ - VERTICAL'!BB$6:BB$546,'BM MORRO DA CRUZ - VERTICAL'!$O$6:$O$546,'BM MORRO DA CRUZ'!$K49),0) -> 0 | AY49: =ROUND(AX49*$P49,2) -> 0 | AZ49: =IFERROR(SUMIFS('BM MORRO DA CRUZ - VERTICAL'!BD$6:BD$546,'BM MORRO DA CRUZ - VERTICAL'!$O$6:$O$546,'BM MORRO DA CRUZ'!$K49),0) -> 0 | BA49: =ROUND(AZ49*$P49,2) -> 0 | BB49: =IFERROR(SUMIFS($R49:$BA49,$R$5:$BA$5,$BB$5),0) -> 0 | BC49: =SUMIFS($R49:$BA49,$R$5:$BA$5,$S$5) -> 0 | BD49: =IFERROR(BB49/O49,0) -> 0 | BE49: =IFERROR((O49-BB49)/O49,0) -> 1
A50: 1.12.2 | B50: FLANGE AVULSO P/ COLARINHO | C50: PN10 | D50: PE100 | E50: FLANGE AVULSO | F50: N/A | G50: 160 | H50: PEAD | I50: HIDROMECÂNICO | J50: OUTROS | K50: 1513903021091 | L50: MATERIAL | M50: FLANGE SOLTO, FORNECIDO EM AÇO SAE 1020, CONFORME NORMA NBR 7675/DIN (PARA COLARINHO DE PEAD / DIÂMETRO EXTERNO: 160 MM / CLASSE DE PRESSÃO: 10 KGF/CM²) | N50: UN | O50: 48 | P50: 237.19 | Q50: =ROUND(P50*$O50,2) -> 11385.12 | R50: =IFERROR(SUMIFS('BM MORRO DA CRUZ - VERTICAL'!V$6:V$546,'BM MORRO DA CRUZ - VERTICAL'!$O$6:$O$546,'BM MORRO DA CRUZ'!$K50),0) -> 0 | S50: =ROUND(R50*$P50,2) -> 0 | T50: =IFERROR(SUMIFS('BM MORRO DA CRUZ - VERTICAL'!X$6:X$546,'BM MORRO DA CRUZ - VERTICAL'!$O$6:$O$546,'BM MORRO DA CRUZ'!$K50),0) -> 0 | U50: =ROUND(T50*$P50,2) -> 0 | V50: =IFERROR(SUMIFS('BM MORRO DA CRUZ - VERTICAL'!Z$6:Z$546,'BM MORRO DA CRUZ - VERTICAL'!$O$6:$O$546,'BM MORRO DA CRUZ'!$K50),0) -> 0 | W50: =ROUND(V50*$P50,2) -> 0 | X50: =IFERROR(SUMIFS('BM MORRO DA CRUZ - VERTICAL'!AB$6:AB$546,'BM MORRO DA CRUZ - VERTICAL'!$O$6:$O$546,'BM MORRO DA CRUZ'!$K50),0) -> 0 | Y50: =ROUND(X50*$P50,2) -> 0 | Z50: =IFERROR(SUMIFS('BM MORRO DA CRUZ - VERTICAL'!AD$6:AD$546,'BM MORRO DA CRUZ - VERTICAL'!$O$6:$O$546,'BM MORRO DA CRUZ'!$K50),0) -> 0 | AA50: =ROUND(Z50*$P50,2) -> 0 | AB50: =IFERROR(SUMIFS('BM MORRO DA CRUZ - VERTICAL'!AF$6:AF$546,'BM MORRO DA CRUZ - VERTICAL'!$O$6:$O$546,'BM MORRO DA CRUZ'!$K50),0) -> 0 | AC50: =ROUND(AB50*$P50,2) -> 0 | AD50: =IFERROR(SUMIFS('BM MORRO DA CRUZ - VERTICAL'!AH$6:AH$546,'BM MORRO DA CRUZ - VERTICAL'!$O$6:$O$546,'BM MORRO DA CRUZ'!$K50),0) -> 0 | AE50: =ROUND(AD50*$P50,2) -> 0 | AF50: =IFERROR(SUMIFS('BM MORRO DA CRUZ - VERTICAL'!AJ$6:AJ$546,'BM MORRO DA CRUZ - VERTICAL'!$O$6:$O$546,'BM MORRO DA CRUZ'!$K50),0) -> 0 | AG50: =ROUND(AF50*$P50,2) -> 0 | AH50: =IFERROR(SUMIFS('BM MORRO DA CRUZ - VERTICAL'!AL$6:AL$546,'BM MORRO DA CRUZ - VERTICAL'!$O$6:$O$546,'BM MORRO DA CRUZ'!$K50),0) -> 0 | AI50: =ROUND(AH50*$P50,2) -> 0 | AJ50: =IFERROR(SUMIFS('BM MORRO DA CRUZ - VERTICAL'!AN$6:AN$546,'BM MORRO DA CRUZ - VERTICAL'!$O$6:$O$546,'BM MORRO DA CRUZ'!$K50),0) -> 0 | AK50: =ROUND(AJ50*$P50,2) -> 0 | AL50: =IFERROR(SUMIFS('BM MORRO DA CRUZ - VERTICAL'!AP$6:AP$546,'BM MORRO DA CRUZ - VERTICAL'!$O$6:$O$546,'BM MORRO DA CRUZ'!$K50),0) -> 0 | AM50: =ROUND(AL50*$P50,2) -> 0 | AN50: =IFERROR(SUMIFS('BM MORRO DA CRUZ - VERTICAL'!AR$6:AR$546,'BM MORRO DA CRUZ - VERTICAL'!$O$6:$O$546,'BM MORRO DA CRUZ'!$K50),0) -> 0 | AO50: =ROUND(AN50*$P50,2) -> 0 | AP50: =IFERROR(SUMIFS('BM MORRO DA CRUZ - VERTICAL'!AT$6:AT$546,'BM MORRO DA CRUZ - VERTICAL'!$O$6:$O$546,'BM MORRO DA CRUZ'!$K50),0) -> 0 | AQ50: =ROUND(AP50*$P50,2) -> 0 | AR50: =IFERROR(SUMIFS('BM MORRO DA CRUZ - VERTICAL'!AV$6:AV$546,'BM MORRO DA CRUZ - VERTICAL'!$O$6:$O$546,'BM MORRO DA CRUZ'!$K50),0) -> 0 | AS50: =ROUND(AR50*$P50,2) -> 0 | AT50: =IFERROR(SUMIFS('BM MORRO DA CRUZ - VERTICAL'!AX$6:AX$546,'BM MORRO DA CRUZ - VERTICAL'!$O$6:$O$546,'BM MORRO DA CRUZ'!$K50),0) -> 0 | AU50: =ROUND(AT50*$P50,2) -> 0 | AV50: =IFERROR(SUMIFS('BM MORRO DA CRUZ - VERTICAL'!AZ$6:AZ$546,'BM MORRO DA CRUZ - VERTICAL'!$O$6:$O$546,'BM MORRO DA CRUZ'!$K50),0) -> 0 | AW50: =ROUND(AV50*$P50,2) -> 0 | AX50: =IFERROR(SUMIFS('BM MORRO DA CRUZ - VERTICAL'!BB$6:BB$546,'BM MORRO DA CRUZ - VERTICAL'!$O$6:$O$546,'BM MORRO DA CRUZ'!$K50),0) -> 0 | AY50: =ROUND(AX50*$P50,2) -> 0 | AZ50: =IFERROR(SUMIFS('BM MORRO DA CRUZ - VERTICAL'!BD$6:BD$546,'BM MORRO DA CRUZ - VERTICAL'!$O$6:$O$546,'BM MORRO DA CRUZ'!$K50),0) -> 0 | BA50: =ROUND(AZ50*$P50,2) -> 0 | BB50: =IFERROR(SUMIFS($R50:$BA50,$R$5:$BA$5,$BB$5),0) -> 0 | BC50: =SUMIFS($R50:$BA50,$R$5:$BA$5,$S$5) -> 0 | BD50: =IFERROR(BB50/O50,0) -> 0 | BE50: =IFERROR((O50-BB50)/O50,0) -> 1
A51: 1.12.3 | B51: FLANGE AVULSO P/ COLARINHO | C51: PN10 | D51: PE100 | E51: FLANGE AVULSO | F51: N/A | G51: 200 | H51: PEAD | I51: HIDROMECÂNICO | J51: OUTROS | K51: 1513903021097 | L51: MATERIAL | M51: FLANGE SOLTO, FORNECIDO EM AÇO SAE 1020, CONFORME NORMA NBR 7675/DIN (PARA COLARINHO DE PEAD / DIÂMETRO EXTERNO: 200 MM / CLASSE DE PRESSÃO: 10 KGF/CM²) | N51: UN | O51: 12 | P51: 343.59 | Q51: =ROUND(P51*$O51,2) -> 4123.08 | R51: =IFERROR(SUMIFS('BM MORRO DA CRUZ - VERTICAL'!V$6:V$546,'BM MORRO DA CRUZ - VERTICAL'!$O$6:$O$546,'BM MORRO DA CRUZ'!$K51),0) -> 0 | S51: =ROUND(R51*$P51,2) -> 0 | T51: =IFERROR(SUMIFS('BM MORRO DA CRUZ - VERTICAL'!X$6:X$546,'BM MORRO DA CRUZ - VERTICAL'!$O$6:$O$546,'BM MORRO DA CRUZ'!$K51),0) -> 0 | U51: =ROUND(T51*$P51,2) -> 0 | V51: =IFERROR(SUMIFS('BM MORRO DA CRUZ - VERTICAL'!Z$6:Z$546,'BM MORRO DA CRUZ - VERTICAL'!$O$6:$O$546,'BM MORRO DA CRUZ'!$K51),0) -> 0 | W51: =ROUND(V51*$P51,2) -> 0 | X51: =IFERROR(SUMIFS('BM MORRO DA CRUZ - VERTICAL'!AB$6:AB$546,'BM MORRO DA CRUZ - VERTICAL'!$O$6:$O$546,'BM MORRO DA CRUZ'!$K51),0) -> 0 | Y51: =ROUND(X51*$P51,2) -> 0 | Z51: =IFERROR(SUMIFS('BM MORRO DA CRUZ - VERTICAL'!AD$6:AD$546,'BM MORRO DA CRUZ - VERTICAL'!$O$6:$O$546,'BM MORRO DA CRUZ'!$K51),0) -> 0 | AA51: =ROUND(Z51*$P51,2) -> 0 | AB51: =IFERROR(SUMIFS('BM MORRO DA CRUZ - VERTICAL'!AF$6:AF$546,'BM MORRO DA CRUZ - VERTICAL'!$O$6:$O$546,'BM MORRO DA CRUZ'!$K51),0) -> 0 | AC51: =ROUND(AB51*$P51,2) -> 0 | AD51: =IFERROR(SUMIFS('BM MORRO DA CRUZ - VERTICAL'!AH$6:AH$546,'BM MORRO DA CRUZ - VERTICAL'!$O$6:$O$546,'BM MORRO DA CRUZ'!$K51),0) -> 0 | AE51: =ROUND(AD51*$P51,2) -> 0 | AF51: =IFERROR(SUMIFS('BM MORRO DA CRUZ - VERTICAL'!AJ$6:AJ$546,'BM MORRO DA CRUZ - VERTICAL'!$O$6:$O$546,'BM MORRO DA CRUZ'!$K51),0) -> 0 | AG51: =ROUND(AF51*$P51,2) -> 0 | AH51: =IFERROR(SUMIFS('BM MORRO DA CRUZ - VERTICAL'!AL$6:AL$546,'BM MORRO DA CRUZ - VERTICAL'!$O$6:$O$546,'BM MORRO DA CRUZ'!$K51),0) -> 0 | AI51: =ROUND(AH51*$P51,2) -> 0 | AJ51: =IFERROR(SUMIFS('BM MORRO DA CRUZ - VERTICAL'!AN$6:AN$546,'BM MORRO DA CRUZ - VERTICAL'!$O$6:$O$546,'BM MORRO DA CRUZ'!$K51),0) -> 0 | AK51: =ROUND(AJ51*$P51,2) -> 0 | AL51: =IFERROR(SUMIFS('BM MORRO DA CRUZ - VERTICAL'!AP$6:AP$546,'BM MORRO DA CRUZ - VERTICAL'!$O$6:$O$546,'BM MORRO DA CRUZ'!$K51),0) -> 0 | AM51: =ROUND(AL51*$P51,2) -> 0 | AN51: =IFERROR(SUMIFS('BM MORRO DA CRUZ - VERTICAL'!AR$6:AR$546,'BM MORRO DA CRUZ - VERTICAL'!$O$6:$O$546,'BM MORRO DA CRUZ'!$K51),0) -> 0 | AO51: =ROUND(AN51*$P51,2) -> 0 | AP51: =IFERROR(SUMIFS('BM MORRO DA CRUZ - VERTICAL'!AT$6:AT$546,'BM MORRO DA CRUZ - VERTICAL'!$O$6:$O$546,'BM MORRO DA CRUZ'!$K51),0) -> 0 | AQ51: =ROUND(AP51*$P51,2) -> 0 | AR51: =IFERROR(SUMIFS('BM MORRO DA CRUZ - VERTICAL'!AV$6:AV$546,'BM MORRO DA CRUZ - VERTICAL'!$O$6:$O$546,'BM MORRO DA CRUZ'!$K51),0) -> 0 | AS51: =ROUND(AR51*$P51,2) -> 0 | AT51: =IFERROR(SUMIFS('BM MORRO DA CRUZ - VERTICAL'!AX$6:AX$546,'BM MORRO DA CRUZ - VERTICAL'!$O$6:$O$546,'BM MORRO DA CRUZ'!$K51),0) -> 0 | AU51: =ROUND(AT51*$P51,2) -> 0 | AV51: =IFERROR(SUMIFS('BM MORRO DA CRUZ - VERTICAL'!AZ$6:AZ$546,'BM MORRO DA CRUZ - VERTICAL'!$O$6:$O$546,'BM MORRO DA CRUZ'!$K51),0) -> 0 | AW51: =ROUND(AV51*$P51,2) -> 0 | AX51: =IFERROR(SUMIFS('BM MORRO DA CRUZ - VERTICAL'!BB$6:BB$546,'BM MORRO DA CRUZ - VERTICAL'!$O$6:$O$546,'BM MORRO DA CRUZ'!$K51),0) -> 0 | AY51: =ROUND(AX51*$P51,2) -> 0 | AZ51: =IFERROR(SUMIFS('BM MORRO DA CRUZ - VERTICAL'!BD$6:BD$546,'BM MORRO DA CRUZ - VERTICAL'!$O$6:$O$546,'BM MORRO DA CRUZ'!$K51),0) -> 0 | BA51: =ROUND(AZ51*$P51,2) -> 0 | BB51: =IFERROR(SUMIFS($R51:$BA51,$R$5:$BA$5,$BB$5),0) -> 0 | BC51: =SUMIFS($R51:$BA51,$R$5:$BA$5,$S$5) -> 0 | BD51: =IFERROR(BB51/O51,0) -> 0 | BE51: =IFERROR((O51-BB51)/O51,0) -> 1
A52: 1.12.4 | B52: FLANGE AVULSO P/ COLARINHO | C52: PN10 | D52: PE100 | E52: FLANGE AVULSO | F52: N/A | G52: 225 | H52: PEAD | I52: HIDROMECÂNICO | J52: OUTROS | K52: 1513903021100 | L52: MATERIAL | M52: FLANGE SOLTO, FORNECIDO EM AÇO SAE 1020, CONFORME NORMA NBR 7675/DIN (PARA COLARINHO DE PEAD / DIÂMETRO EXTERNO: 225 MM / CLASSE DE PRESSÃO: 10 KGF/CM²) | N52: UN | O52: 7 | P52: 343.59 | Q52: =ROUND(P52*$O52,2) -> 2405.13 | R52: =IFERROR(SUMIFS('BM MORRO DA CRUZ - VERTICAL'!V$6:V$546,'BM MORRO DA CRUZ - VERTICAL'!$O$6:$O$546,'BM MORRO DA CRUZ'!$K52),0) -> 0 | S52: =ROUND(R52*$P52,2) -> 0 | T52: =IFERROR(SUMIFS('BM MORRO DA CRUZ - VERTICAL'!X$6:X$546,'BM MORRO DA CRUZ - VERTICAL'!$O$6:$O$546,'BM MORRO DA CRUZ'!$K52),0) -> 0 | U52: =ROUND(T52*$P52,2) -> 0 | V52: =IFERROR(SUMIFS('BM MORRO DA CRUZ - VERTICAL'!Z$6:Z$546,'BM MORRO DA CRUZ - VERTICAL'!$O$6:$O$546,'BM MORRO DA CRUZ'!$K52),0) -> 0 | W52: =ROUND(V52*$P52,2) -> 0 | X52: =IFERROR(SUMIFS('BM MORRO DA CRUZ - VERTICAL'!AB$6:AB$546,'BM MORRO DA CRUZ - VERTICAL'!$O$6:$O$546,'BM MORRO DA CRUZ'!$K52),0) -> 0 | Y52: =ROUND(X52*$P52,2) -> 0 | Z52: =IFERROR(SUMIFS('BM MORRO DA CRUZ - VERTICAL'!AD$6:AD$546,'BM MORRO DA CRUZ - VERTICAL'!$O$6:$O$546,'BM MORRO DA CRUZ'!$K52),0) -> 0 | AA52: =ROUND(Z52*$P52,2) -> 0 | AB52: =IFERROR(SUMIFS('BM MORRO DA CRUZ - VERTICAL'!AF$6:AF$546,'BM MORRO DA CRUZ - VERTICAL'!$O$6:$O$546,'BM MORRO DA CRUZ'!$K52),0) -> 0 | AC52: =ROUND(AB52*$P52,2) -> 0 | AD52: =IFERROR(SUMIFS('BM MORRO DA CRUZ - VERTICAL'!AH$6:AH$546,'BM MORRO DA CRUZ - VERTICAL'!$O$6:$O$546,'BM MORRO DA CRUZ'!$K52),0) -> 0 | AE52: =ROUND(AD52*$P52,2) -> 0 | AF52: =IFERROR(SUMIFS('BM MORRO DA CRUZ - VERTICAL'!AJ$6:AJ$546,'BM MORRO DA CRUZ - VERTICAL'!$O$6:$O$546,'BM MORRO DA CRUZ'!$K52),0) -> 0 | AG52: =ROUND(AF52*$P52,2) -> 0 | AH52: =IFERROR(SUMIFS('BM MORRO DA CRUZ - VERTICAL'!AL$6:AL$546,'BM MORRO DA CRUZ - VERTICAL'!$O$6:$O$546,'BM MORRO DA CRUZ'!$K52),0) -> 0 | AI52: =ROUND(AH52*$P52,2) -> 0 | AJ52: =IFERROR(SUMIFS('BM MORRO DA CRUZ - VERTICAL'!AN$6:AN$546,'BM MORRO DA CRUZ - VERTICAL'!$O$6:$O$546,'BM MORRO DA CRUZ'!$K52),0) -> 0 | AK52: =ROUND(AJ52*$P52,2) -> 0 | AL52: =IFERROR(SUMIFS('BM MORRO DA CRUZ - VERTICAL'!AP$6:AP$546,'BM MORRO DA CRUZ - VERTICAL'!$O$6:$O$546,'BM MORRO DA CRUZ'!$K52),0) -> 0 | AM52: =ROUND(AL52*$P52,2) -> 0 | AN52: =IFERROR(SUMIFS('BM MORRO DA CRUZ - VERTICAL'!AR$6:AR$546,'BM MORRO DA CRUZ - VERTICAL'!$O$6:$O$546,'BM MORRO DA CRUZ'!$K52),0) -> 0 | AO52: =ROUND(AN52*$P52,2) -> 0 | AP52: =IFERROR(SUMIFS('BM MORRO DA CRUZ - VERTICAL'!AT$6:AT$546,'BM MORRO DA CRUZ - VERTICAL'!$O$6:$O$546,'BM MORRO DA CRUZ'!$K52),0) -> 0 | AQ52: =ROUND(AP52*$P52,2) -> 0 | AR52: =IFERROR(SUMIFS('BM MORRO DA CRUZ - VERTICAL'!AV$6:AV$546,'BM MORRO DA CRUZ - VERTICAL'!$O$6:$O$546,'BM MORRO DA CRUZ'!$K52),0) -> 0 | AS52: =ROUND(AR52*$P52,2) -> 0 | AT52: =IFERROR(SUMIFS('BM MORRO DA CRUZ - VERTICAL'!AX$6:AX$546,'BM MORRO DA CRUZ - VERTICAL'!$O$6:$O$546,'BM MORRO DA CRUZ'!$K52),0) -> 0 | AU52: =ROUND(AT52*$P52,2) -> 0 | AV52: =IFERROR(SUMIFS('BM MORRO DA CRUZ - VERTICAL'!AZ$6:AZ$546,'BM MORRO DA CRUZ - VERTICAL'!$O$6:$O$546,'BM MORRO DA CRUZ'!$K52),0) -> 0 | AW52: =ROUND(AV52*$P52,2) -> 0 | AX52: =IFERROR(SUMIFS('BM MORRO DA CRUZ - VERTICAL'!BB$6:BB$546,'BM MORRO DA CRUZ - VERTICAL'!$O$6:$O$546,'BM MORRO DA CRUZ'!$K52),0) -> 0 | AY52: =ROUND(AX52*$P52,2) -> 0 | AZ52: =IFERROR(SUMIFS('BM MORRO DA CRUZ - VERTICAL'!BD$6:BD$546,'BM MORRO DA CRUZ - VERTICAL'!$O$6:$O$546,'BM MORRO DA CRUZ'!$K52),0) -> 0 | BA52: =ROUND(AZ52*$P52,2) -> 0 | BB52: =IFERROR(SUMIFS($R52:$BA52,$R$5:$BA$5,$BB$5),0) -> 0 | BC52: =SUMIFS($R52:$BA52,$R$5:$BA$5,$S$5) -> 0 | BD52: =IFERROR(BB52/O52,0) -> 0 | BE52: =IFERROR((O52-BB52)/O52,0) -> 1
A53: 1.12.5 | B53: FLANGE AVULSO P/ COLARINHO | C53: PN10 | D53: PE100 | E53: FLANGE AVULSO | F53: N/A | G53: 250 | H53: PEAD | I53: HIDROMECÂNICO | J53: OUTROS | K53: 1513903021103 | L53: MATERIAL | M53: FLANGE SOLTO, FORNECIDO EM AÇO SAE 1020, CONFORME NORMA NBR 7675/DIN (PARA COLARINHO DE PEAD / DIÂMETRO EXTERNO: 250 MM / CLASSE DE PRESSÃO: 10 KGF/CM²) | N53: UN | O53: 10 | P53: 444.96 | Q53: =ROUND(P53*$O53,2) -> 4449.6 | R53: =IFERROR(SUMIFS('BM MORRO DA CRUZ - VERTICAL'!V$6:V$546,'BM MORRO DA CRUZ - VERTICAL'!$O$6:$O$546,'BM MORRO DA CRUZ'!$K53),0) -> 0 | S53: =ROUND(R53*$P53,2) -> 0 | T53: =IFERROR(SUMIFS('BM MORRO DA CRUZ - VERTICAL'!X$6:X$546,'BM MORRO DA CRUZ - VERTICAL'!$O$6:$O$546,'BM MORRO DA CRUZ'!$K53),0) -> 0 | U53: =ROUND(T53*$P53,2) -> 0 | V53: =IFERROR(SUMIFS('BM MORRO DA CRUZ - VERTICAL'!Z$6:Z$546,'BM MORRO DA CRUZ - VERTICAL'!$O$6:$O$546,'BM MORRO DA CRUZ'!$K53),0) -> 0 | W53: =ROUND(V53*$P53,2) -> 0 | X53: =IFERROR(SUMIFS('BM MORRO DA CRUZ - VERTICAL'!AB$6:AB$546,'BM MORRO DA CRUZ - VERTICAL'!$O$6:$O$546,'BM MORRO DA CRUZ'!$K53),0) -> 0 | Y53: =ROUND(X53*$P53,2) -> 0 | Z53: =IFERROR(SUMIFS('BM MORRO DA CRUZ - VERTICAL'!AD$6:AD$546,'BM MORRO DA CRUZ - VERTICAL'!$O$6:$O$546,'BM MORRO DA CRUZ'!$K53),0) -> 0 | AA53: =ROUND(Z53*$P53,2) -> 0 | AB53: =IFERROR(SUMIFS('BM MORRO DA CRUZ - VERTICAL'!AF$6:AF$546,'BM MORRO DA CRUZ - VERTICAL'!$O$6:$O$546,'BM MORRO DA CRUZ'!$K53),0) -> 0 | AC53: =ROUND(AB53*$P53,2) -> 0 | AD53: =IFERROR(SUMIFS('BM MORRO DA CRUZ - VERTICAL'!AH$6:AH$546,'BM MORRO DA CRUZ - VERTICAL'!$O$6:$O$546,'BM MORRO DA CRUZ'!$K53),0) -> 0 | AE53: =ROUND(AD53*$P53,2) -> 0 | AF53: =IFERROR(SUMIFS('BM MORRO DA CRUZ - VERTICAL'!AJ$6:AJ$546,'BM MORRO DA CRUZ - VERTICAL'!$O$6:$O$546,'BM MORRO DA CRUZ'!$K53),0) -> 0 | AG53: =ROUND(AF53*$P53,2) -> 0 | AH53: =IFERROR(SUMIFS('BM MORRO DA CRUZ - VERTICAL'!AL$6:AL$546,'BM MORRO DA CRUZ - VERTICAL'!$O$6:$O$546,'BM MORRO DA CRUZ'!$K53),0) -> 0 | AI53: =ROUND(AH53*$P53,2) -> 0 | AJ53: =IFERROR(SUMIFS('BM MORRO DA CRUZ - VERTICAL'!AN$6:AN$546,'BM MORRO DA CRUZ - VERTICAL'!$O$6:$O$546,'BM MORRO DA CRUZ'!$K53),0) -> 0 | AK53: =ROUND(AJ53*$P53,2) -> 0 | AL53: =IFERROR(SUMIFS('BM MORRO DA CRUZ - VERTICAL'!AP$6:AP$546,'BM MORRO DA CRUZ - VERTICAL'!$O$6:$O$546,'BM MORRO DA CRUZ'!$K53),0) -> 0 | AM53: =ROUND(AL53*$P53,2) -> 0 | AN53: =IFERROR(SUMIFS('BM MORRO DA CRUZ - VERTICAL'!AR$6:AR$546,'BM MORRO DA CRUZ - VERTICAL'!$O$6:$O$546,'BM MORRO DA CRUZ'!$K53),0) -> 0 | AO53: =ROUND(AN53*$P53,2) -> 0 | AP53: =IFERROR(SUMIFS('BM MORRO DA CRUZ - VERTICAL'!AT$6:AT$546,'BM MORRO DA CRUZ - VERTICAL'!$O$6:$O$546,'BM MORRO DA CRUZ'!$K53),0) -> 0 | AQ53: =ROUND(AP53*$P53,2) -> 0 | AR53: =IFERROR(SUMIFS('BM MORRO DA CRUZ - VERTICAL'!AV$6:AV$546,'BM MORRO DA CRUZ - VERTICAL'!$O$6:$O$546,'BM MORRO DA CRUZ'!$K53),0) -> 0 | AS53: =ROUND(AR53*$P53,2) -> 0 | AT53: =IFERROR(SUMIFS('BM MORRO DA CRUZ - VERTICAL'!AX$6:AX$546,'BM MORRO DA CRUZ - VERTICAL'!$O$6:$O$546,'BM MORRO DA CRUZ'!$K53),0) -> 0 | AU53: =ROUND(AT53*$P53,2) -> 0 | AV53: =IFERROR(SUMIFS('BM MORRO DA CRUZ - VERTICAL'!AZ$6:AZ$546,'BM MORRO DA CRUZ - VERTICAL'!$O$6:$O$546,'BM MORRO DA CRUZ'!$K53),0) -> 0 | AW53: =ROUND(AV53*$P53,2) -> 0 | AX53: =IFERROR(SUMIFS('BM MORRO DA CRUZ - VERTICAL'!BB$6:BB$546,'BM MORRO DA CRUZ - VERTICAL'!$O$6:$O$546,'BM MORRO DA CRUZ'!$K53),0) -> 0 | AY53: =ROUND(AX53*$P53,2) -> 0 | AZ53: =IFERROR(SUMIFS('BM MORRO DA CRUZ - VERTICAL'!BD$6:BD$546,'BM MORRO DA CRUZ - VERTICAL'!$O$6:$O$546,'BM MORRO DA CRUZ'!$K53),0) -> 0 | BA53: =ROUND(AZ53*$P53,2) -> 0 | BB53: =IFERROR(SUMIFS($R53:$BA53,$R$5:$BA$5,$BB$5),0) -> 0 | BC53: =SUMIFS($R53:$BA53,$R$5:$BA$5,$S$5) -> 0 | BD53: =IFERROR(BB53/O53,0) -> 0 | BE53: =IFERROR((O53-BB53)/O53,0) -> 1
A54: 1.12.6 | B54: FLANGE AVULSO P/ COLARINHO | C54: PN10 | D54: PE100 | E54: FLANGE AVULSO | F54: N/A | G54: 500 | H54: PEAD | I54: HIDROMECÂNICO | J54: OUTROS | K54: 1513903021121 | L54: MATERIAL | M54: FLANGE SOLTO, FORNECIDO EM AÇO SAE 1020, CONFORME NORMA NBR 7675/DIN (PARA COLARINHO DE PEAD / DIÂMETRO EXTERNO: 500 MM / CLASSE DE PRESSÃO: 10 KGF/CM²) | N54: UN | O54: 2 | P54: 1281.88 | Q54: =ROUND(P54*$O54,2) -> 2563.76 | R54: =IFERROR(SUMIFS('BM MORRO DA CRUZ - VERTICAL'!V$6:V$546,'BM MORRO DA CRUZ - VERTICAL'!$O$6:$O$546,'BM MORRO DA CRUZ'!$K54),0) -> 0 | S54: =ROUND(R54*$P54,2) -> 0 | T54: =IFERROR(SUMIFS('BM MORRO DA CRUZ - VERTICAL'!X$6:X$546,'BM MORRO DA CRUZ - VERTICAL'!$O$6:$O$546,'BM MORRO DA CRUZ'!$K54),0) -> 0 | U54: =ROUND(T54*$P54,2) -> 0 | V54: =IFERROR(SUMIFS('BM MORRO DA CRUZ - VERTICAL'!Z$6:Z$546,'BM MORRO DA CRUZ - VERTICAL'!$O$6:$O$546,'BM MORRO DA CRUZ'!$K54),0) -> 0 | W54: =ROUND(V54*$P54,2) -> 0 | X54: =IFERROR(SUMIFS('BM MORRO DA CRUZ - VERTICAL'!AB$6:AB$546,'BM MORRO DA CRUZ - VERTICAL'!$O$6:$O$546,'BM MORRO DA CRUZ'!$K54),0) -> 0 | Y54: =ROUND(X54*$P54,2) -> 0 | Z54: =IFERROR(SUMIFS('BM MORRO DA CRUZ - VERTICAL'!AD$6:AD$546,'BM MORRO DA CRUZ - VERTICAL'!$O$6:$O$546,'BM MORRO DA CRUZ'!$K54),0) -> 0 | AA54: =ROUND(Z54*$P54,2) -> 0 | AB54: =IFERROR(SUMIFS('BM MORRO DA CRUZ - VERTICAL'!AF$6:AF$546,'BM MORRO DA CRUZ - VERTICAL'!$O$6:$O$546,'BM MORRO DA CRUZ'!$K54),0) -> 0 | AC54: =ROUND(AB54*$P54,2) -> 0 | AD54: =IFERROR(SUMIFS('BM MORRO DA CRUZ - VERTICAL'!AH$6:AH$546,'BM MORRO DA CRUZ - VERTICAL'!$O$6:$O$546,'BM MORRO DA CRUZ'!$K54),0) -> 0 | AE54: =ROUND(AD54*$P54,2) -> 0 | AF54: =IFERROR(SUMIFS('BM MORRO DA CRUZ - VERTICAL'!AJ$6:AJ$546,'BM MORRO DA CRUZ - VERTICAL'!$O$6:$O$546,'BM MORRO DA CRUZ'!$K54),0) -> 0 | AG54: =ROUND(AF54*$P54,2) -> 0 | AH54: =IFERROR(SUMIFS('BM MORRO DA CRUZ - VERTICAL'!AL$6:AL$546,'BM MORRO DA CRUZ - VERTICAL'!$O$6:$O$546,'BM MORRO DA CRUZ'!$K54),0) -> 0 | AI54: =ROUND(AH54*$P54,2) -> 0 | AJ54: =IFERROR(SUMIFS('BM MORRO DA CRUZ - VERTICAL'!AN$6:AN$546,'BM MORRO DA CRUZ - VERTICAL'!$O$6:$O$546,'BM MORRO DA CRUZ'!$K54),0) -> 0 | AK54: =ROUND(AJ54*$P54,2) -> 0 | AL54: =IFERROR(SUMIFS('BM MORRO DA CRUZ - VERTICAL'!AP$6:AP$546,'BM MORRO DA CRUZ - VERTICAL'!$O$6:$O$546,'BM MORRO DA CRUZ'!$K54),0) -> 0 | AM54: =ROUND(AL54*$P54,2) -> 0 | AN54: =IFERROR(SUMIFS('BM MORRO DA CRUZ - VERTICAL'!AR$6:AR$546,'BM MORRO DA CRUZ - VERTICAL'!$O$6:$O$546,'BM MORRO DA CRUZ'!$K54),0) -> 0 | AO54: =ROUND(AN54*$P54,2) -> 0 | AP54: =IFERROR(SUMIFS('BM MORRO DA CRUZ - VERTICAL'!AT$6:AT$546,'BM MORRO DA CRUZ - VERTICAL'!$O$6:$O$546,'BM MORRO DA CRUZ'!$K54),0) -> 0 | AQ54: =ROUND(AP54*$P54,2) -> 0 | AR54: =IFERROR(SUMIFS('BM MORRO DA CRUZ - VERTICAL'!AV$6:AV$546,'BM MORRO DA CRUZ - VERTICAL'!$O$6:$O$546,'BM MORRO DA CRUZ'!$K54),0) -> 0 | AS54: =ROUND(AR54*$P54,2) -> 0 | AT54: =IFERROR(SUMIFS('BM MORRO DA CRUZ - VERTICAL'!AX$6:AX$546,'BM MORRO DA CRUZ - VERTICAL'!$O$6:$O$546,'BM MORRO DA CRUZ'!$K54),0) -> 0 | AU54: =ROUND(AT54*$P54,2) -> 0 | AV54: =IFERROR(SUMIFS('BM MORRO DA CRUZ - VERTICAL'!AZ$6:AZ$546,'BM MORRO DA CRUZ - VERTICAL'!$O$6:$O$546,'BM MORRO DA CRUZ'!$K54),0) -> 0 | AW54: =ROUND(AV54*$P54,2) -> 0 | AX54: =IFERROR(SUMIFS('BM MORRO DA CRUZ - VERTICAL'!BB$6:BB$546,'BM MORRO DA CRUZ - VERTICAL'!$O$6:$O$546,'BM MORRO DA CRUZ'!$K54),0) -> 0 | AY54: =ROUND(AX54*$P54,2) -> 0 | AZ54: =IFERROR(SUMIFS('BM MORRO DA CRUZ - VERTICAL'!BD$6:BD$546,'BM MORRO DA CRUZ - VERTICAL'!$O$6:$O$546,'BM MORRO DA CRUZ'!$K54),0) -> 0 | BA54: =ROUND(AZ54*$P54,2) -> 0 | BB54: =IFERROR(SUMIFS($R54:$BA54,$R$5:$BA$5,$BB$5),0) -> 0 | BC54: =SUMIFS($R54:$BA54,$R$5:$BA$5,$S$5) -> 0 | BD54: =IFERROR(BB54/O54,0) -> 0 | BE54: =IFERROR((O54-BB54)/O54,0) -> 1
A55: 1.12.7 | B55: FLANGE AVULSO P/ COLARINHO | C55: PN10 | D55: PE100 | E55: FLANGE AVULSO | F55: N/A | G55: 63 | H55: PEAD | I55: HIDROMECÂNICO | J55: OUTROS | K55: 1513903021073 | L55: MATERIAL | M55: FLANGE SOLTO, FORNECIDO EM AÇO SAE 1020, CONFORME NORMA NBR 7675/DIN (PARA COLARINHO DE PEAD / DIÂMETRO EXTERNO: 63 MM / CLASSE DE PRESSÃO: 10 KGF/CM²) | N55: UN | O55: 120 | P55: 94.02 | Q55: =ROUND(P55*$O55,2) -> 11282.4 | R55: =IFERROR(SUMIFS('BM MORRO DA CRUZ - VERTICAL'!V$6:V$546,'BM MORRO DA CRUZ - VERTICAL'!$O$6:$O$546,'BM MORRO DA CRUZ'!$K55),0) -> 0 | S55: =ROUND(R55*$P55,2) -> 0 | T55: =IFERROR(SUMIFS('BM MORRO DA CRUZ - VERTICAL'!X$6:X$546,'BM MORRO DA CRUZ - VERTICAL'!$O$6:$O$546,'BM MORRO DA CRUZ'!$K55),0) -> 0 | U55: =ROUND(T55*$P55,2) -> 0 | V55: =IFERROR(SUMIFS('BM MORRO DA CRUZ - VERTICAL'!Z$6:Z$546,'BM MORRO DA CRUZ - VERTICAL'!$O$6:$O$546,'BM MORRO DA CRUZ'!$K55),0) -> 0 | W55: =ROUND(V55*$P55,2) -> 0 | X55: =IFERROR(SUMIFS('BM MORRO DA CRUZ - VERTICAL'!AB$6:AB$546,'BM MORRO DA CRUZ - VERTICAL'!$O$6:$O$546,'BM MORRO DA CRUZ'!$K55),0) -> 0 | Y55: =ROUND(X55*$P55,2) -> 0 | Z55: =IFERROR(SUMIFS('BM MORRO DA CRUZ - VERTICAL'!AD$6:AD$546,'BM MORRO DA CRUZ - VERTICAL'!$O$6:$O$546,'BM MORRO DA CRUZ'!$K55),0) -> 0 | AA55: =ROUND(Z55*$P55,2) -> 0 | AB55: =IFERROR(SUMIFS('BM MORRO DA CRUZ - VERTICAL'!AF$6:AF$546,'BM MORRO DA CRUZ - VERTICAL'!$O$6:$O$546,'BM MORRO DA CRUZ'!$K55),0) -> 0 | AC55: =ROUND(AB55*$P55,2) -> 0 | AD55: =IFERROR(SUMIFS('BM MORRO DA CRUZ - VERTICAL'!AH$6:AH$546,'BM MORRO DA CRUZ - VERTICAL'!$O$6:$O$546,'BM MORRO DA CRUZ'!$K55),0) -> 0 | AE55: =ROUND(AD55*$P55,2) -> 0 | AF55: =IFERROR(SUMIFS('BM MORRO DA CRUZ - VERTICAL'!AJ$6:AJ$546,'BM MORRO DA CRUZ - VERTICAL'!$O$6:$O$546,'BM MORRO DA CRUZ'!$K55),0) -> 0 | AG55: =ROUND(AF55*$P55,2) -> 0 | AH55: =IFERROR(SUMIFS('BM MORRO DA CRUZ - VERTICAL'!AL$6:AL$546,'BM MORRO DA CRUZ - VERTICAL'!$O$6:$O$546,'BM MORRO DA CRUZ'!$K55),0) -> 0 | AI55: =ROUND(AH55*$P55,2) -> 0 | AJ55: =IFERROR(SUMIFS('BM MORRO DA CRUZ - VERTICAL'!AN$6:AN$546,'BM MORRO DA CRUZ - VERTICAL'!$O$6:$O$546,'BM MORRO DA CRUZ'!$K55),0) -> 0 | AK55: =ROUND(AJ55*$P55,2) -> 0 | AL55: =IFERROR(SUMIFS('BM MORRO DA CRUZ - VERTICAL'!AP$6:AP$546,'BM MORRO DA CRUZ - VERTICAL'!$O$6:$O$546,'BM MORRO DA CRUZ'!$K55),0) -> 0 | AM55: =ROUND(AL55*$P55,2) -> 0 | AN55: =IFERROR(SUMIFS('BM MORRO DA CRUZ - VERTICAL'!AR$6:AR$546,'BM MORRO DA CRUZ - VERTICAL'!$O$6:$O$546,'BM MORRO DA CRUZ'!$K55),0) -> 0 | AO55: =ROUND(AN55*$P55,2) -> 0 | AP55: =IFERROR(SUMIFS('BM MORRO DA CRUZ - VERTICAL'!AT$6:AT$546,'BM MORRO DA CRUZ - VERTICAL'!$O$6:$O$546,'BM MORRO DA CRUZ'!$K55),0) -> 0 | AQ55: =ROUND(AP55*$P55,2) -> 0 | AR55: =IFERROR(SUMIFS('BM MORRO DA CRUZ - VERTICAL'!AV$6:AV$546,'BM MORRO DA CRUZ - VERTICAL'!$O$6:$O$546,'BM MORRO DA CRUZ'!$K55),0) -> 0 | AS55: =ROUND(AR55*$P55,2) -> 0 | AT55: =IFERROR(SUMIFS('BM MORRO DA CRUZ - VERTICAL'!AX$6:AX$546,'BM MORRO DA CRUZ - VERTICAL'!$O$6:$O$546,'BM MORRO DA CRUZ'!$K55),0) -> 0 | AU55: =ROUND(AT55*$P55,2) -> 0 | AV55: =IFERROR(SUMIFS('BM MORRO DA CRUZ - VERTICAL'!AZ$6:AZ$546,'BM MORRO DA CRUZ - VERTICAL'!$O$6:$O$546,'BM MORRO DA CRUZ'!$K55),0) -> 0 | AW55: =ROUND(AV55*$P55,2) -> 0 | AX55: =IFERROR(SUMIFS('BM MORRO DA CRUZ - VERTICAL'!BB$6:BB$546,'BM MORRO DA CRUZ - VERTICAL'!$O$6:$O$546,'BM MORRO DA CRUZ'!$K55),0) -> 0 | AY55: =ROUND(AX55*$P55,2) -> 0 | AZ55: =IFERROR(SUMIFS('BM MORRO DA CRUZ - VERTICAL'!BD$6:BD$546,'BM MORRO DA CRUZ - VERTICAL'!$O$6:$O$546,'BM MORRO DA CRUZ'!$K55),0) -> 0 | BA55: =ROUND(AZ55*$P55,2) -> 0 | BB55: =IFERROR(SUMIFS($R55:$BA55,$R$5:$BA$5,$BB$5),0) -> 0 | BC55: =SUMIFS($R55:$BA55,$R$5:$BA$5,$S$5) -> 0 | BD55: =IFERROR(BB55/O55,0) -> 0 | BE55: =IFERROR((O55-BB55)/O55,0) -> 1
A56: 1.12.8 | B56: FLANGE AVULSO P/ COLARINHO | C56: PN10 | D56: PE100 | E56: FLANGE AVULSO | F56: N/A | G56: 90 | H56: PEAD | I56: HIDROMECÂNICO | J56: OUTROS | K56: 1513903021079 | L56: MATERIAL | M56: FLANGE SOLTO, FORNECIDO EM AÇO SAE 1020, CONFORME NORMA NBR 7675/DIN (PARA COLARINHO DE PEAD / DIÂMETRO EXTERNO: 90 MM / CLASSE DE PRESSÃO: 10 KGF/CM²) | N56: UN | O56: 30 | P56: 116.08 | Q56: =ROUND(P56*$O56,2) -> 3482.4 | R56: =IFERROR(SUMIFS('BM MORRO DA CRUZ - VERTICAL'!V$6:V$546,'BM MORRO DA CRUZ - VERTICAL'!$O$6:$O$546,'BM MORRO DA CRUZ'!$K56),0) -> 0 | S56: =ROUND(R56*$P56,2) -> 0 | T56: =IFERROR(SUMIFS('BM MORRO DA CRUZ - VERTICAL'!X$6:X$546,'BM MORRO DA CRUZ - VERTICAL'!$O$6:$O$546,'BM MORRO DA CRUZ'!$K56),0) -> 0 | U56: =ROUND(T56*$P56,2) -> 0 | V56: =IFERROR(SUMIFS('BM MORRO DA CRUZ - VERTICAL'!Z$6:Z$546,'BM MORRO DA CRUZ - VERTICAL'!$O$6:$O$546,'BM MORRO DA CRUZ'!$K56),0) -> 0 | W56: =ROUND(V56*$P56,2) -> 0 | X56: =IFERROR(SUMIFS('BM MORRO DA CRUZ - VERTICAL'!AB$6:AB$546,'BM MORRO DA CRUZ - VERTICAL'!$O$6:$O$546,'BM MORRO DA CRUZ'!$K56),0) -> 0 | Y56: =ROUND(X56*$P56,2) -> 0 | Z56: =IFERROR(SUMIFS('BM MORRO DA CRUZ - VERTICAL'!AD$6:AD$546,'BM MORRO DA CRUZ - VERTICAL'!$O$6:$O$546,'BM MORRO DA CRUZ'!$K56),0) -> 0 | AA56: =ROUND(Z56*$P56,2) -> 0 | AB56: =IFERROR(SUMIFS('BM MORRO DA CRUZ - VERTICAL'!AF$6:AF$546,'BM MORRO DA CRUZ - VERTICAL'!$O$6:$O$546,'BM MORRO DA CRUZ'!$K56),0) -> 0 | AC56: =ROUND(AB56*$P56,2) -> 0 | AD56: =IFERROR(SUMIFS('BM MORRO DA CRUZ - VERTICAL'!AH$6:AH$546,'BM MORRO DA CRUZ - VERTICAL'!$O$6:$O$546,'BM MORRO DA CRUZ'!$K56),0) -> 0 | AE56: =ROUND(AD56*$P56,2) -> 0 | AF56: =IFERROR(SUMIFS('BM MORRO DA CRUZ - VERTICAL'!AJ$6:AJ$546,'BM MORRO DA CRUZ - VERTICAL'!$O$6:$O$546,'BM MORRO DA CRUZ'!$K56),0) -> 0 | AG56: =ROUND(AF56*$P56,2) -> 0 | AH56: =IFERROR(SUMIFS('BM MORRO DA CRUZ - VERTICAL'!AL$6:AL$546,'BM MORRO DA CRUZ - VERTICAL'!$O$6:$O$546,'BM MORRO DA CRUZ'!$K56),0) -> 0 | AI56: =ROUND(AH56*$P56,2) -> 0 | AJ56: =IFERROR(SUMIFS('BM MORRO DA CRUZ - VERTICAL'!AN$6:AN$546,'BM MORRO DA CRUZ - VERTICAL'!$O$6:$O$546,'BM MORRO DA CRUZ'!$K56),0) -> 0 | AK56: =ROUND(AJ56*$P56,2) -> 0 | AL56: =IFERROR(SUMIFS('BM MORRO DA CRUZ - VERTICAL'!AP$6:AP$546,'BM MORRO DA CRUZ - VERTICAL'!$O$6:$O$546,'BM MORRO DA CRUZ'!$K56),0) -> 0 | AM56: =ROUND(AL56*$P56,2) -> 0 | AN56: =IFERROR(SUMIFS('BM MORRO DA CRUZ - VERTICAL'!AR$6:AR$546,'BM MORRO DA CRUZ - VERTICAL'!$O$6:$O$546,'BM MORRO DA CRUZ'!$K56),0) -> 0 | AO56: =ROUND(AN56*$P56,2) -> 0 | AP56: =IFERROR(SUMIFS('BM MORRO DA CRUZ - VERTICAL'!AT$6:AT$546,'BM MORRO DA CRUZ - VERTICAL'!$O$6:$O$546,'BM MORRO DA CRUZ'!$K56),0) -> 0 | AQ56: =ROUND(AP56*$P56,2) -> 0 | AR56: =IFERROR(SUMIFS('BM MORRO DA CRUZ - VERTICAL'!AV$6:AV$546,'BM MORRO DA CRUZ - VERTICAL'!$O$6:$O$546,'BM MORRO DA CRUZ'!$K56),0) -> 0 | AS56: =ROUND(AR56*$P56,2) -> 0 | AT56: =IFERROR(SUMIFS('BM MORRO DA CRUZ - VERTICAL'!AX$6:AX$546,'BM MORRO DA CRUZ - VERTICAL'!$O$6:$O$546,'BM MORRO DA CRUZ'!$K56),0) -> 0 | AU56: =ROUND(AT56*$P56,2) -> 0 | AV56: =IFERROR(SUMIFS('BM MORRO DA CRUZ - VERTICAL'!AZ$6:AZ$546,'BM MORRO DA CRUZ - VERTICAL'!$O$6:$O$546,'BM MORRO DA CRUZ'!$K56),0) -> 0 | AW56: =ROUND(AV56*$P56,2) -> 0 | AX56: =IFERROR(SUMIFS('BM MORRO DA CRUZ - VERTICAL'!BB$6:BB$546,'BM MORRO DA CRUZ - VERTICAL'!$O$6:$O$546,'BM MORRO DA CRUZ'!$K56),0) -> 0 | AY56: =ROUND(AX56*$P56,2) -> 0 | AZ56: =IFERROR(SUMIFS('BM MORRO DA CRUZ - VERTICAL'!BD$6:BD$546,'BM MORRO DA CRUZ - VERTICAL'!$O$6:$O$546,'BM MORRO DA CRUZ'!$K56),0) -> 0 | BA56: =ROUND(AZ56*$P56,2) -> 0 | BB56: =IFERROR(SUMIFS($R56:$BA56,$R$5:$BA$5,$BB$5),0) -> 0 | BC56: =SUMIFS($R56:$BA56,$R$5:$BA$5,$S$5) -> 0 | BD56: =IFERROR(BB56/O56,0) -> 0 | BE56: =IFERROR((O56-BB56)/O56,0) -> 1
A57: 1.13 | K57: 15143 | M57: TUBOS E CONEXÕES DE PVC - ÁGUA FRIA (ROSCÁVEL) | Q57: =SUM(Q58:Q58) -> 39.56 | S57: =SUM(S58:S58) -> 0 | U57: =SUM(U58:U58) -> 0 | W57: =SUM(W58:W58) -> 0 | Y57: =SUM(Y58:Y58) -> 0 | AA57: =SUM(AA58:AA58) -> 0 | AC57: =SUM(AC58:AC58) -> 0 | AE57: =SUM(AE58:AE58) -> 0 | AG57: =SUM(AG58:AG58) -> 0 | AI57: =SUM(AI58:AI58) -> 0 | AK57: =SUM(AK58:AK58) -> 0 | AM57: =SUM(AM58:AM58) -> 0 | AO57: =SUM(AO58:AO58) -> 0 | AQ57: =SUM(AQ58:AQ58) -> 0 | AS57: =SUM(AS58:AS58) -> 0 | AU57: =SUM(AU58:AU58) -> 0 | AW57: =SUM(AW58:AW58) -> 0 | AY57: =SUM(AY58:AY58) -> 0 | BA57: =SUM(BA58:BA58) -> 0 | BC57: =SUM(BC58:BC58) -> 0
A58: 1.13.1 | B58: ADAPTADOR DE PVC BRANCO ROSCÁVEL COM ANEL PARA CAIXA D'ÁGUA | C58: N/A | D58: N/A | E58: ADAPTADOR | F58: N/A | G58: 1.1/2" | H58: PVC | I58: CANTEIRO | J58: OUTROS | K58: 1514303022006 | L58: MATERIAL | M58: ADAPTADOR DE PVC BRANCO ROSCÁVEL COM ANEL PARA CAIXA D'ÁGUA (DIÂMETRO DA SEÇÃO: 1 1/2 ") | N58: UN | O58: 1 | P58: 39.56 | Q58: =ROUND(P58*$O58,2) -> 39.56 | R58: =IFERROR(SUMIFS('BM MORRO DA CRUZ - VERTICAL'!V$6:V$546,'BM MORRO DA CRUZ - VERTICAL'!$O$6:$O$546,'BM MORRO DA CRUZ'!$K58),0) -> 0 | S58: =ROUND(R58*$P58,2) -> 0 | T58: =IFERROR(SUMIFS('BM MORRO DA CRUZ - VERTICAL'!X$6:X$546,'BM MORRO DA CRUZ - VERTICAL'!$O$6:$O$546,'BM MORRO DA CRUZ'!$K58),0) -> 0 | U58: =ROUND(T58*$P58,2) -> 0 | V58: =IFERROR(SUMIFS('BM MORRO DA CRUZ - VERTICAL'!Z$6:Z$546,'BM MORRO DA CRUZ - VERTICAL'!$O$6:$O$546,'BM MORRO DA CRUZ'!$K58),0) -> 0 | W58: =ROUND(V58*$P58,2) -> 0 | X58: =IFERROR(SUMIFS('BM MORRO DA CRUZ - VERTICAL'!AB$6:AB$546,'BM MORRO DA CRUZ - VERTICAL'!$O$6:$O$546,'BM MORRO DA CRUZ'!$K58),0) -> 0 | Y58: =ROUND(X58*$P58,2) -> 0 | Z58: =IFERROR(SUMIFS('BM MORRO DA CRUZ - VERTICAL'!AD$6:AD$546,'BM MORRO DA CRUZ - VERTICAL'!$O$6:$O$546,'BM MORRO DA CRUZ'!$K58),0) -> 0 | AA58: =ROUND(Z58*$P58,2) -> 0 | AB58: =IFERROR(SUMIFS('BM MORRO DA CRUZ - VERTICAL'!AF$6:AF$546,'BM MORRO DA CRUZ - VERTICAL'!$O$6:$O$546,'BM MORRO DA CRUZ'!$K58),0) -> 0 | AC58: =ROUND(AB58*$P58,2) -> 0 | AD58: =IFERROR(SUMIFS('BM MORRO DA CRUZ - VERTICAL'!AH$6:AH$546,'BM MORRO DA CRUZ - VERTICAL'!$O$6:$O$546,'BM MORRO DA CRUZ'!$K58),0) -> 0 | AE58: =ROUND(AD58*$P58,2) -> 0 | AF58: =IFERROR(SUMIFS('BM MORRO DA CRUZ - VERTICAL'!AJ$6:AJ$546,'BM MORRO DA CRUZ - VERTICAL'!$O$6:$O$546,'BM MORRO DA CRUZ'!$K58),0) -> 0 | AG58: =ROUND(AF58*$P58,2) -> 0 | AH58: =IFERROR(SUMIFS('BM MORRO DA CRUZ - VERTICAL'!AL$6:AL$546,'BM MORRO DA CRUZ - VERTICAL'!$O$6:$O$546,'BM MORRO DA CRUZ'!$K58),0) -> 0 | AI58: =ROUND(AH58*$P58,2) -> 0 | AJ58: =IFERROR(SUMIFS('BM MORRO DA CRUZ - VERTICAL'!AN$6:AN$546,'BM MORRO DA CRUZ - VERTICAL'!$O$6:$O$546,'BM MORRO DA CRUZ'!$K58),0) -> 0 | AK58: =ROUND(AJ58*$P58,2) -> 0 | AL58: =IFERROR(SUMIFS('BM MORRO DA CRUZ - VERTICAL'!AP$6:AP$546,'BM MORRO DA CRUZ - VERTICAL'!$O$6:$O$546,'BM MORRO DA CRUZ'!$K58),0) -> 0 | AM58: =ROUND(AL58*$P58,2) -> 0 | AN58: =IFERROR(SUMIFS('BM MORRO DA CRUZ - VERTICAL'!AR$6:AR$546,'BM MORRO DA CRUZ - VERTICAL'!$O$6:$O$546,'BM MORRO DA CRUZ'!$K58),0) -> 0 | AO58: =ROUND(AN58*$P58,2) -> 0 | AP58: =IFERROR(SUMIFS('BM MORRO DA CRUZ - VERTICAL'!AT$6:AT$546,'BM MORRO DA CRUZ - VERTICAL'!$O$6:$O$546,'BM MORRO DA CRUZ'!$K58),0) -> 0 | AQ58: =ROUND(AP58*$P58,2) -> 0 | AR58: =IFERROR(SUMIFS('BM MORRO DA CRUZ - VERTICAL'!AV$6:AV$546,'BM MORRO DA CRUZ - VERTICAL'!$O$6:$O$546,'BM MORRO DA CRUZ'!$K58),0) -> 0 | AS58: =ROUND(AR58*$P58,2) -> 0 | AT58: =IFERROR(SUMIFS('BM MORRO DA CRUZ - VERTICAL'!AX$6:AX$546,'BM MORRO DA CRUZ - VERTICAL'!$O$6:$O$546,'BM MORRO DA CRUZ'!$K58),0) -> 0 | AU58: =ROUND(AT58*$P58,2) -> 0 | AV58: =IFERROR(SUMIFS('BM MORRO DA CRUZ - VERTICAL'!AZ$6:AZ$546,'BM MORRO DA CRUZ - VERTICAL'!$O$6:$O$546,'BM MORRO DA CRUZ'!$K58),0) -> 0 | AW58: =ROUND(AV58*$P58,2) -> 0 | AX58: =IFERROR(SUMIFS('BM MORRO DA CRUZ - VERTICAL'!BB$6:BB$546,'BM MORRO DA CRUZ - VERTICAL'!$O$6:$O$546,'BM MORRO DA CRUZ'!$K58),0) -> 0 | AY58: =ROUND(AX58*$P58,2) -> 0 | AZ58: =IFERROR(SUMIFS('BM MORRO DA CRUZ - VERTICAL'!BD$6:BD$546,'BM MORRO DA CRUZ - VERTICAL'!$O$6:$O$546,'BM MORRO DA CRUZ'!$K58),0) -> 0 | BA58: =ROUND(AZ58*$P58,2) -> 0 | BB58: =IFERROR(SUMIFS($R58:$BA58,$R$5:$BA$5,$BB$5),0) -> 0 | BC58: =SUMIFS($R58:$BA58,$R$5:$BA$5,$S$5) -> 0 | BD58: =IFERROR(BB58/O58,0) -> 0 | BE58: =IFERROR((O58-BB58)/O58,0) -> 1
A59: 1.14 | K59: 15146 | M59: TUBOS E CONEXÕES DE POLIETILENO DE ALTA DENSIDADE | Q59: =SUM(Q60:Q136) -> 1006599.8 | S59: =SUM(S60:S136) -> 0 | U59: =SUM(U60:U136) -> 0 | W59: =SUM(W60:W136) -> 0 | Y59: =SUM(Y60:Y136) -> 0 | AA59: =SUM(AA60:AA136) -> 0 | AC59: =SUM(AC60:AC136) -> 0 | AE59: =SUM(AE60:AE136) -> 0 | AG59: =SUM(AG60:AG136) -> 0 | AI59: =SUM(AI60:AI136) -> 0 | AK59: =SUM(AK60:AK136) -> 0 | AM59: =SUM(AM60:AM136) -> 0 | AO59: =SUM(AO60:AO136) -> 0 | AQ59: =SUM(AQ60:AQ136) -> 0 | AS59: =SUM(AS60:AS136) -> 0 | AU59: =SUM(AU60:AU136) -> 0 | AW59: =SUM(AW60:AW136) -> 0 | AY59: =SUM(AY60:AY136) -> 0 | BA59: =SUM(BA60:BA136) -> 0 | BC59: =SUM(BC60:BC136) -> 0
A60: 1.14.1 | B60: LUVA ELETROFUSÃO | C60: PN10/16 | D60: PE100 | E60: LUVA | F60: ELETROFUSÃO | G60: 250 | H60: PEAD | I60: HIDROMECÂNICO | J60: PEAD | K60: 1514603060XX11 | L60: MATERIAL | M60: LUVA DE POLIETILENO DE ALTA DENSIDADE ELETROFUSÃO (CLASSE DE PRESSÃO: 10/16 KGF/CM² / DIÂMETRO DA SEÇÃO: 250 MM / TIPO DE RESINA: PE100) | N60: UN | O60: 25 | P60: 426.08 | Q60: =ROUND(P60*$O60,2) -> 10652 | R60: =IFERROR(SUMIFS('BM MORRO DA CRUZ - VERTICAL'!V$6:V$546,'BM MORRO DA CRUZ - VERTICAL'!$O$6:$O$546,'BM MORRO DA CRUZ'!$K60),0) -> 0 | S60: =ROUND(R60*$P60,2) -> 0 | T60: =IFERROR(SUMIFS('BM MORRO DA CRUZ - VERTICAL'!X$6:X$546,'BM MORRO DA CRUZ - VERTICAL'!$O$6:$O$546,'BM MORRO DA CRUZ'!$K60),0) -> 0 | U60: =ROUND(T60*$P60,2) -> 0 | V60: =IFERROR(SUMIFS('BM MORRO DA CRUZ - VERTICAL'!Z$6:Z$546,'BM MORRO DA CRUZ - VERTICAL'!$O$6:$O$546,'BM MORRO DA CRUZ'!$K60),0) -> 0 | W60: =ROUND(V60*$P60,2) -> 0 | X60: =IFERROR(SUMIFS('BM MORRO DA CRUZ - VERTICAL'!AB$6:AB$546,'BM MORRO DA CRUZ - VERTICAL'!$O$6:$O$546,'BM MORRO DA CRUZ'!$K60),0) -> 0 | Y60: =ROUND(X60*$P60,2) -> 0 | Z60: =IFERROR(SUMIFS('BM MORRO DA CRUZ - VERTICAL'!AD$6:AD$546,'BM MORRO DA CRUZ - VERTICAL'!$O$6:$O$546,'BM MORRO DA CRUZ'!$K60),0) -> 0 | AA60: =ROUND(Z60*$P60,2) -> 0 | AB60: =IFERROR(SUMIFS('BM MORRO DA CRUZ - VERTICAL'!AF$6:AF$546,'BM MORRO DA CRUZ - VERTICAL'!$O$6:$O$546,'BM MORRO DA CRUZ'!$K60),0) -> 0 | AC60: =ROUND(AB60*$P60,2) -> 0 | AD60: =IFERROR(SUMIFS('BM MORRO DA CRUZ - VERTICAL'!AH$6:AH$546,'BM MORRO DA CRUZ - VERTICAL'!$O$6:$O$546,'BM MORRO DA CRUZ'!$K60),0) -> 0 | AE60: =ROUND(AD60*$P60,2) -> 0 | AF60: =IFERROR(SUMIFS('BM MORRO DA CRUZ - VERTICAL'!AJ$6:AJ$546,'BM MORRO DA CRUZ - VERTICAL'!$O$6:$O$546,'BM MORRO DA CRUZ'!$K60),0) -> 0 | AG60: =ROUND(AF60*$P60,2) -> 0 | AH60: =IFERROR(SUMIFS('BM MORRO DA CRUZ - VERTICAL'!AL$6:AL$546,'BM MORRO DA CRUZ - VERTICAL'!$O$6:$O$546,'BM MORRO DA CRUZ'!$K60),0) -> 0 | AI60: =ROUND(AH60*$P60,2) -> 0 | AJ60: =IFERROR(SUMIFS('BM MORRO DA CRUZ - VERTICAL'!AN$6:AN$546,'BM MORRO DA CRUZ - VERTICAL'!$O$6:$O$546,'BM MORRO DA CRUZ'!$K60),0) -> 0 | AK60: =ROUND(AJ60*$P60,2) -> 0 | AL60: =IFERROR(SUMIFS('BM MORRO DA CRUZ - VERTICAL'!AP$6:AP$546,'BM MORRO DA CRUZ - VERTICAL'!$O$6:$O$546,'BM MORRO DA CRUZ'!$K60),0) -> 0 | AM60: =ROUND(AL60*$P60,2) -> 0 | AN60: =IFERROR(SUMIFS('BM MORRO DA CRUZ - VERTICAL'!AR$6:AR$546,'BM MORRO DA CRUZ - VERTICAL'!$O$6:$O$546,'BM MORRO DA CRUZ'!$K60),0) -> 0 | AO60: =ROUND(AN60*$P60,2) -> 0 | AP60: =IFERROR(SUMIFS('BM MORRO DA CRUZ - VERTICAL'!AT$6:AT$546,'BM MORRO DA CRUZ - VERTICAL'!$O$6:$O$546,'BM MORRO DA CRUZ'!$K60),0) -> 0 | AQ60: =ROUND(AP60*$P60,2) -> 0 | AR60: =IFERROR(SUMIFS('BM MORRO DA CRUZ - VERTICAL'!AV$6:AV$546,'BM MORRO DA CRUZ - VERTICAL'!$O$6:$O$546,'BM MORRO DA CRUZ'!$K60),0) -> 0 | AS60: =ROUND(AR60*$P60,2) -> 0 | AT60: =IFERROR(SUMIFS('BM MORRO DA CRUZ - VERTICAL'!AX$6:AX$546,'BM MORRO DA CRUZ - VERTICAL'!$O$6:$O$546,'BM MORRO DA CRUZ'!$K60),0) -> 0 | AU60: =ROUND(AT60*$P60,2) -> 0 | AV60: =IFERROR(SUMIFS('BM MORRO DA CRUZ - VERTICAL'!AZ$6:AZ$546,'BM MORRO DA CRUZ - VERTICAL'!$O$6:$O$546,'BM MORRO DA CRUZ'!$K60),0) -> 0 | AW60: =ROUND(AV60*$P60,2) -> 0 | AX60: =IFERROR(SUMIFS('BM MORRO DA CRUZ - VERTICAL'!BB$6:BB$546,'BM MORRO DA CRUZ - VERTICAL'!$O$6:$O$546,'BM MORRO DA CRUZ'!$K60),0) -> 0 | AY60: =ROUND(AX60*$P60,2) -> 0 | AZ60: =IFERROR(SUMIFS('BM MORRO DA CRUZ - VERTICAL'!BD$6:BD$546,'BM MORRO DA CRUZ - VERTICAL'!$O$6:$O$546,'BM MORRO DA CRUZ'!$K60),0) -> 0 | BA60: =ROUND(AZ60*$P60,2) -> 0 | BB60: =IFERROR(SUMIFS($R60:$BA60,$R$5:$BA$5,$BB$5),0) -> 0 | BC60: =SUMIFS($R60:$BA60,$R$5:$BA$5,$S$5) -> 0 | BD60: =IFERROR(BB60/O60,0) -> 0 | BE60: =IFERROR((O60-BB60)/O60,0) -> 1
A61: 1.14.2 | B61: COLARINHO INJETADO PONTA LONGA | C61: PN10 | D61: PE100 | E61: COLARINHO | F61: TERMOFUSÃO | G61: 110 | H61: PEAD | I61: HIDROMECÂNICO | J61: PEAD | K61: 1514603025022 | L61: MATERIAL | M61: COLARINHO DE POLIETILENO DE ALTA DENSIDADE (PEAD), DN 110, PN-10 (10 KGF/CM²), INJETADA PE-100 SDR-17; PONTA LONGA; PARA ÁGUA OU ESGOTO; NBR 15593 | N61: UN | O61: 2 | P61: 75.57 | Q61: =ROUND(P61*$O61,2) -> 151.14 | R61: =IFERROR(SUMIFS('BM MORRO DA CRUZ - VERTICAL'!V$6:V$546,'BM MORRO DA CRUZ - VERTICAL'!$O$6:$O$546,'BM MORRO DA CRUZ'!$K61),0) -> 0 | S61: =ROUND(R61*$P61,2) -> 0 | T61: =IFERROR(SUMIFS('BM MORRO DA CRUZ - VERTICAL'!X$6:X$546,'BM MORRO DA CRUZ - VERTICAL'!$O$6:$O$546,'BM MORRO DA CRUZ'!$K61),0) -> 0 | U61: =ROUND(T61*$P61,2) -> 0 | V61: =IFERROR(SUMIFS('BM MORRO DA CRUZ - VERTICAL'!Z$6:Z$546,'BM MORRO DA CRUZ - VERTICAL'!$O$6:$O$546,'BM MORRO DA CRUZ'!$K61),0) -> 0 | W61: =ROUND(V61*$P61,2) -> 0 | X61: =IFERROR(SUMIFS('BM MORRO DA CRUZ - VERTICAL'!AB$6:AB$546,'BM MORRO DA CRUZ - VERTICAL'!$O$6:$O$546,'BM MORRO DA CRUZ'!$K61),0) -> 0 | Y61: =ROUND(X61*$P61,2) -> 0 | Z61: =IFERROR(SUMIFS('BM MORRO DA CRUZ - VERTICAL'!AD$6:AD$546,'BM MORRO DA CRUZ - VERTICAL'!$O$6:$O$546,'BM MORRO DA CRUZ'!$K61),0) -> 0 | AA61: =ROUND(Z61*$P61,2) -> 0 | AB61: =IFERROR(SUMIFS('BM MORRO DA CRUZ - VERTICAL'!AF$6:AF$546,'BM MORRO DA CRUZ - VERTICAL'!$O$6:$O$546,'BM MORRO DA CRUZ'!$K61),0) -> 0 | AC61: =ROUND(AB61*$P61,2) -> 0 | AD61: =IFERROR(SUMIFS('BM MORRO DA CRUZ - VERTICAL'!AH$6:AH$546,'BM MORRO DA CRUZ - VERTICAL'!$O$6:$O$546,'BM MORRO DA CRUZ'!$K61),0) -> 0 | AE61: =ROUND(AD61*$P61,2) -> 0 | AF61: =IFERROR(SUMIFS('BM MORRO DA CRUZ - VERTICAL'!AJ$6:AJ$546,'BM MORRO DA CRUZ - VERTICAL'!$O$6:$O$546,'BM MORRO DA CRUZ'!$K61),0) -> 0 | AG61: =ROUND(AF61*$P61,2) -> 0 | AH61: =IFERROR(SUMIFS('BM MORRO DA CRUZ - VERTICAL'!AL$6:AL$546,'BM MORRO DA CRUZ - VERTICAL'!$O$6:$O$546,'BM MORRO DA CRUZ'!$K61),0) -> 0 | AI61: =ROUND(AH61*$P61,2) -> 0 | AJ61: =IFERROR(SUMIFS('BM MORRO DA CRUZ - VERTICAL'!AN$6:AN$546,'BM MORRO DA CRUZ - VERTICAL'!$O$6:$O$546,'BM MORRO DA CRUZ'!$K61),0) -> 0 | AK61: =ROUND(AJ61*$P61,2) -> 0 | AL61: =IFERROR(SUMIFS('BM MORRO DA CRUZ - VERTICAL'!AP$6:AP$546,'BM MORRO DA CRUZ - VERTICAL'!$O$6:$O$546,'BM MORRO DA CRUZ'!$K61),0) -> 0 | AM61: =ROUND(AL61*$P61,2) -> 0 | AN61: =IFERROR(SUMIFS('BM MORRO DA CRUZ - VERTICAL'!AR$6:AR$546,'BM MORRO DA CRUZ - VERTICAL'!$O$6:$O$546,'BM MORRO DA CRUZ'!$K61),0) -> 0 | AO61: =ROUND(AN61*$P61,2) -> 0 | AP61: =IFERROR(SUMIFS('BM MORRO DA CRUZ - VERTICAL'!AT$6:AT$546,'BM MORRO DA CRUZ - VERTICAL'!$O$6:$O$546,'BM MORRO DA CRUZ'!$K61),0) -> 0 | AQ61: =ROUND(AP61*$P61,2) -> 0 | AR61: =IFERROR(SUMIFS('BM MORRO DA CRUZ - VERTICAL'!AV$6:AV$546,'BM MORRO DA CRUZ - VERTICAL'!$O$6:$O$546,'BM MORRO DA CRUZ'!$K61),0) -> 0 | AS61: =ROUND(AR61*$P61,2) -> 0 | AT61: =IFERROR(SUMIFS('BM MORRO DA CRUZ - VERTICAL'!AX$6:AX$546,'BM MORRO DA CRUZ - VERTICAL'!$O$6:$O$546,'BM MORRO DA CRUZ'!$K61),0) -> 0 | AU61: =ROUND(AT61*$P61,2) -> 0 | AV61: =IFERROR(SUMIFS('BM MORRO DA CRUZ - VERTICAL'!AZ$6:AZ$546,'BM MORRO DA CRUZ - VERTICAL'!$O$6:$O$546,'BM MORRO DA CRUZ'!$K61),0) -> 0 | AW61: =ROUND(AV61*$P61,2) -> 0 | AX61: =IFERROR(SUMIFS('BM MORRO DA CRUZ - VERTICAL'!BB$6:BB$546,'BM MORRO DA CRUZ - VERTICAL'!$O$6:$O$546,'BM MORRO DA CRUZ'!$K61),0) -> 0 | AY61: =ROUND(AX61*$P61,2) -> 0 | AZ61: =IFERROR(SUMIFS('BM MORRO DA CRUZ - VERTICAL'!BD$6:BD$546,'BM MORRO DA CRUZ - VERTICAL'!$O$6:$O$546,'BM MORRO DA CRUZ'!$K61),0) -> 0 | BA61: =ROUND(AZ61*$P61,2) -> 0 | BB61: =IFERROR(SUMIFS($R61:$BA61,$R$5:$BA$5,$BB$5),0) -> 0 | BC61: =SUMIFS($R61:$BA61,$R$5:$BA$5,$S$5) -> 0 | BD61: =IFERROR(BB61/O61,0) -> 0 | BE61: =IFERROR((O61-BB61)/O61,0) -> 1
A62: 1.14.3 | B62: COLARINHO INJETADO PONTA LONGA | C62: PN10 | D62: PE100 | E62: COLARINHO | F62: TERMOFUSÃO | G62: 125 | H62: PEAD | I62: HIDROMECÂNICO | J62: PEAD | K62: 1514603025023 | L62: MATERIAL | M62: COLARINHO DE POLIETILENO DE ALTA DENSIDADE (PEAD), DN 125, PN-10 (10 KGF/CM²), INJETADA PE-100 SDR-17; PONTA LONGA; PARA ÁGUA OU ESGOTO; NBR 15593 | N62: UN | O62: 4 | P62: 92.19 | Q62: =ROUND(P62*$O62,2) -> 368.76 | R62: =IFERROR(SUMIFS('BM MORRO DA CRUZ - VERTICAL'!V$6:V$546,'BM MORRO DA CRUZ - VERTICAL'!$O$6:$O$546,'BM MORRO DA CRUZ'!$K62),0) -> 0 | S62: =ROUND(R62*$P62,2) -> 0 | T62: =IFERROR(SUMIFS('BM MORRO DA CRUZ - VERTICAL'!X$6:X$546,'BM MORRO DA CRUZ - VERTICAL'!$O$6:$O$546,'BM MORRO DA CRUZ'!$K62),0) -> 0 | U62: =ROUND(T62*$P62,2) -> 0 | V62: =IFERROR(SUMIFS('BM MORRO DA CRUZ - VERTICAL'!Z$6:Z$546,'BM MORRO DA CRUZ - VERTICAL'!$O$6:$O$546,'BM MORRO DA CRUZ'!$K62),0) -> 0 | W62: =ROUND(V62*$P62,2) -> 0 | X62: =IFERROR(SUMIFS('BM MORRO DA CRUZ - VERTICAL'!AB$6:AB$546,'BM MORRO DA CRUZ - VERTICAL'!$O$6:$O$546,'BM MORRO DA CRUZ'!$K62),0) -> 0 | Y62: =ROUND(X62*$P62,2) -> 0 | Z62: =IFERROR(SUMIFS('BM MORRO DA CRUZ - VERTICAL'!AD$6:AD$546,'BM MORRO DA CRUZ - VERTICAL'!$O$6:$O$546,'BM MORRO DA CRUZ'!$K62),0) -> 0 | AA62: =ROUND(Z62*$P62,2) -> 0 | AB62: =IFERROR(SUMIFS('BM MORRO DA CRUZ - VERTICAL'!AF$6:AF$546,'BM MORRO DA CRUZ - VERTICAL'!$O$6:$O$546,'BM MORRO DA CRUZ'!$K62),0) -> 0 | AC62: =ROUND(AB62*$P62,2) -> 0 | AD62: =IFERROR(SUMIFS('BM MORRO DA CRUZ - VERTICAL'!AH$6:AH$546,'BM MORRO DA CRUZ - VERTICAL'!$O$6:$O$546,'BM MORRO DA CRUZ'!$K62),0) -> 0 | AE62: =ROUND(AD62*$P62,2) -> 0 | AF62: =IFERROR(SUMIFS('BM MORRO DA CRUZ - VERTICAL'!AJ$6:AJ$546,'BM MORRO DA CRUZ - VERTICAL'!$O$6:$O$546,'BM MORRO DA CRUZ'!$K62),0) -> 0 | AG62: =ROUND(AF62*$P62,2) -> 0 | AH62: =IFERROR(SUMIFS('BM MORRO DA CRUZ - VERTICAL'!AL$6:AL$546,'BM MORRO DA CRUZ - VERTICAL'!$O$6:$O$546,'BM MORRO DA CRUZ'!$K62),0) -> 0 | AI62: =ROUND(AH62*$P62,2) -> 0 | AJ62: =IFERROR(SUMIFS('BM MORRO DA CRUZ - VERTICAL'!AN$6:AN$546,'BM MORRO DA CRUZ - VERTICAL'!$O$6:$O$546,'BM MORRO DA CRUZ'!$K62),0) -> 0 | AK62: =ROUND(AJ62*$P62,2) -> 0 | AL62: =IFERROR(SUMIFS('BM MORRO DA CRUZ - VERTICAL'!AP$6:AP$546,'BM MORRO DA CRUZ - VERTICAL'!$O$6:$O$546,'BM MORRO DA CRUZ'!$K62),0) -> 0 | AM62: =ROUND(AL62*$P62,2) -> 0 | AN62: =IFERROR(SUMIFS('BM MORRO DA CRUZ - VERTICAL'!AR$6:AR$546,'BM MORRO DA CRUZ - VERTICAL'!$O$6:$O$546,'BM MORRO DA CRUZ'!$K62),0) -> 0 | AO62: =ROUND(AN62*$P62,2) -> 0 | AP62: =IFERROR(SUMIFS('BM MORRO DA CRUZ - VERTICAL'!AT$6:AT$546,'BM MORRO DA CRUZ - VERTICAL'!$O$6:$O$546,'BM MORRO DA CRUZ'!$K62),0) -> 0 | AQ62: =ROUND(AP62*$P62,2) -> 0 | AR62: =IFERROR(SUMIFS('BM MORRO DA CRUZ - VERTICAL'!AV$6:AV$546,'BM MORRO DA CRUZ - VERTICAL'!$O$6:$O$546,'BM MORRO DA CRUZ'!$K62),0) -> 0 | AS62: =ROUND(AR62*$P62,2) -> 0 | AT62: =IFERROR(SUMIFS('BM MORRO DA CRUZ - VERTICAL'!AX$6:AX$546,'BM MORRO DA CRUZ - VERTICAL'!$O$6:$O$546,'BM MORRO DA CRUZ'!$K62),0) -> 0 | AU62: =ROUND(AT62*$P62,2) -> 0 | AV62: =IFERROR(SUMIFS('BM MORRO DA CRUZ - VERTICAL'!AZ$6:AZ$546,'BM MORRO DA CRUZ - VERTICAL'!$O$6:$O$546,'BM MORRO DA CRUZ'!$K62),0) -> 0 | AW62: =ROUND(AV62*$P62,2) -> 0 | AX62: =IFERROR(SUMIFS('BM MORRO DA CRUZ - VERTICAL'!BB$6:BB$546,'BM MORRO DA CRUZ - VERTICAL'!$O$6:$O$546,'BM MORRO DA CRUZ'!$K62),0) -> 0 | AY62: =ROUND(AX62*$P62,2) -> 0 | AZ62: =IFERROR(SUMIFS('BM MORRO DA CRUZ - VERTICAL'!BD$6:BD$546,'BM MORRO DA CRUZ - VERTICAL'!$O$6:$O$546,'BM MORRO DA CRUZ'!$K62),0) -> 0 | BA62: =ROUND(AZ62*$P62,2) -> 0 | BB62: =IFERROR(SUMIFS($R62:$BA62,$R$5:$BA$5,$BB$5),0) -> 0 | BC62: =SUMIFS($R62:$BA62,$R$5:$BA$5,$S$5) -> 0 | BD62: =IFERROR(BB62/O62,0) -> 0 | BE62: =IFERROR((O62-BB62)/O62,0) -> 1
A63: 1.14.4 | B63: COLARINHO INJETADO PONTA LONGA | C63: PN10 | D63: PE100 | E63: COLARINHO | F63: TERMOFUSÃO | G63: 160 | H63: PEAD | I63: HIDROMECÂNICO | J63: PEAD | K63: 1514603025025 | L63: MATERIAL | M63: COLARINHO DE POLIETILENO DE ALTA DENSIDADE (PEAD), DN 160, PN-10 (10 KGF/CM²), INJETADA PE-100 SDR-17; PONTA LONGA; PARA ÁGUA OU ESGOTO; NBR 15593 | N63: UN | O63: 48 | P63: 149.07 | Q63: =ROUND(P63*$O63,2) -> 7155.36 | R63: =IFERROR(SUMIFS('BM MORRO DA CRUZ - VERTICAL'!V$6:V$546,'BM MORRO DA CRUZ - VERTICAL'!$O$6:$O$546,'BM MORRO DA CRUZ'!$K63),0) -> 0 | S63: =ROUND(R63*$P63,2) -> 0 | T63: =IFERROR(SUMIFS('BM MORRO DA CRUZ - VERTICAL'!X$6:X$546,'BM MORRO DA CRUZ - VERTICAL'!$O$6:$O$546,'BM MORRO DA CRUZ'!$K63),0) -> 0 | U63: =ROUND(T63*$P63,2) -> 0 | V63: =IFERROR(SUMIFS('BM MORRO DA CRUZ - VERTICAL'!Z$6:Z$546,'BM MORRO DA CRUZ - VERTICAL'!$O$6:$O$546,'BM MORRO DA CRUZ'!$K63),0) -> 0 | W63: =ROUND(V63*$P63,2) -> 0 | X63: =IFERROR(SUMIFS('BM MORRO DA CRUZ - VERTICAL'!AB$6:AB$546,'BM MORRO DA CRUZ - VERTICAL'!$O$6:$O$546,'BM MORRO DA CRUZ'!$K63),0) -> 0 | Y63: =ROUND(X63*$P63,2) -> 0 | Z63: =IFERROR(SUMIFS('BM MORRO DA CRUZ - VERTICAL'!AD$6:AD$546,'BM MORRO DA CRUZ - VERTICAL'!$O$6:$O$546,'BM MORRO DA CRUZ'!$K63),0) -> 0 | AA63: =ROUND(Z63*$P63,2) -> 0 | AB63: =IFERROR(SUMIFS('BM MORRO DA CRUZ - VERTICAL'!AF$6:AF$546,'BM MORRO DA CRUZ - VERTICAL'!$O$6:$O$546,'BM MORRO DA CRUZ'!$K63),0) -> 0 | AC63: =ROUND(AB63*$P63,2) -> 0 | AD63: =IFERROR(SUMIFS('BM MORRO DA CRUZ - VERTICAL'!AH$6:AH$546,'BM MORRO DA CRUZ - VERTICAL'!$O$6:$O$546,'BM MORRO DA CRUZ'!$K63),0) -> 0 | AE63: =ROUND(AD63*$P63,2) -> 0 | AF63: =IFERROR(SUMIFS('BM MORRO DA CRUZ - VERTICAL'!AJ$6:AJ$546,'BM MORRO DA CRUZ - VERTICAL'!$O$6:$O$546,'BM MORRO DA CRUZ'!$K63),0) -> 0 | AG63: =ROUND(AF63*$P63,2) -> 0 | AH63: =IFERROR(SUMIFS('BM MORRO DA CRUZ - VERTICAL'!AL$6:AL$546,'BM MORRO DA CRUZ - VERTICAL'!$O$6:$O$546,'BM MORRO DA CRUZ'!$K63),0) -> 0 | AI63: =ROUND(AH63*$P63,2) -> 0 | AJ63: =IFERROR(SUMIFS('BM MORRO DA CRUZ - VERTICAL'!AN$6:AN$546,'BM MORRO DA CRUZ - VERTICAL'!$O$6:$O$546,'BM MORRO DA CRUZ'!$K63),0) -> 0 | AK63: =ROUND(AJ63*$P63,2) -> 0 | AL63: =IFERROR(SUMIFS('BM MORRO DA CRUZ - VERTICAL'!AP$6:AP$546,'BM MORRO DA CRUZ - VERTICAL'!$O$6:$O$546,'BM MORRO DA CRUZ'!$K63),0) -> 0 | AM63: =ROUND(AL63*$P63,2) -> 0 | AN63: =IFERROR(SUMIFS('BM MORRO DA CRUZ - VERTICAL'!AR$6:AR$546,'BM MORRO DA CRUZ - VERTICAL'!$O$6:$O$546,'BM MORRO DA CRUZ'!$K63),0) -> 0 | AO63: =ROUND(AN63*$P63,2) -> 0 | AP63: =IFERROR(SUMIFS('BM MORRO DA CRUZ - VERTICAL'!AT$6:AT$546,'BM MORRO DA CRUZ - VERTICAL'!$O$6:$O$546,'BM MORRO DA CRUZ'!$K63),0) -> 0 | AQ63: =ROUND(AP63*$P63,2) -> 0 | AR63: =IFERROR(SUMIFS('BM MORRO DA CRUZ - VERTICAL'!AV$6:AV$546,'BM MORRO DA CRUZ - VERTICAL'!$O$6:$O$546,'BM MORRO DA CRUZ'!$K63),0) -> 0 | AS63: =ROUND(AR63*$P63,2) -> 0 | AT63: =IFERROR(SUMIFS('BM MORRO DA CRUZ - VERTICAL'!AX$6:AX$546,'BM MORRO DA CRUZ - VERTICAL'!$O$6:$O$546,'BM MORRO DA CRUZ'!$K63),0) -> 0 | AU63: =ROUND(AT63*$P63,2) -> 0 | AV63: =IFERROR(SUMIFS('BM MORRO DA CRUZ - VERTICAL'!AZ$6:AZ$546,'BM MORRO DA CRUZ - VERTICAL'!$O$6:$O$546,'BM MORRO DA CRUZ'!$K63),0) -> 0 | AW63: =ROUND(AV63*$P63,2) -> 0 | AX63: =IFERROR(SUMIFS('BM MORRO DA CRUZ - VERTICAL'!BB$6:BB$546,'BM MORRO DA CRUZ - VERTICAL'!$O$6:$O$546,'BM MORRO DA CRUZ'!$K63),0) -> 0 | AY63: =ROUND(AX63*$P63,2) -> 0 | AZ63: =IFERROR(SUMIFS('BM MORRO DA CRUZ - VERTICAL'!BD$6:BD$546,'BM MORRO DA CRUZ - VERTICAL'!$O$6:$O$546,'BM MORRO DA CRUZ'!$K63),0) -> 0 | BA63: =ROUND(AZ63*$P63,2) -> 0 | BB63: =IFERROR(SUMIFS($R63:$BA63,$R$5:$BA$5,$BB$5),0) -> 0 | BC63: =SUMIFS($R63:$BA63,$R$5:$BA$5,$S$5) -> 0 | BD63: =IFERROR(BB63/O63,0) -> 0 | BE63: =IFERROR((O63-BB63)/O63,0) -> 1
A64: 1.14.5 | B64: COLARINHO INJETADO PONTA LONGA | C64: PN10 | D64: PE100 | E64: COLARINHO | F64: TERMOFUSÃO | G64: 200 | H64: PEAD | I64: HIDROMECÂNICO | J64: PEAD | K64: 1514603025027 | L64: MATERIAL | M64: COLARINHO DE POLIETILENO DE ALTA DENSIDADE (PEAD), DN 200, PN-10 (10 KGF/CM²), INJETADA PE-100 SDR-17; PONTA LONGA; PARA ÁGUA OU ESGOTO; NBR 15593; PARA ÁGUA OU ESGOTO; NBR 15593 | N64: UN | O64: 2 | P64: 262.24 | Q64: =ROUND(P64*$O64,2) -> 524.48 | R64: =IFERROR(SUMIFS('BM MORRO DA CRUZ - VERTICAL'!V$6:V$546,'BM MORRO DA CRUZ - VERTICAL'!$O$6:$O$546,'BM MORRO DA CRUZ'!$K64),0) -> 0 | S64: =ROUND(R64*$P64,2) -> 0 | T64: =IFERROR(SUMIFS('BM MORRO DA CRUZ - VERTICAL'!X$6:X$546,'BM MORRO DA CRUZ - VERTICAL'!$O$6:$O$546,'BM MORRO DA CRUZ'!$K64),0) -> 0 | U64: =ROUND(T64*$P64,2) -> 0 | V64: =IFERROR(SUMIFS('BM MORRO DA CRUZ - VERTICAL'!Z$6:Z$546,'BM MORRO DA CRUZ - VERTICAL'!$O$6:$O$546,'BM MORRO DA CRUZ'!$K64),0) -> 0 | W64: =ROUND(V64*$P64,2) -> 0 | X64: =IFERROR(SUMIFS('BM MORRO DA CRUZ - VERTICAL'!AB$6:AB$546,'BM MORRO DA CRUZ - VERTICAL'!$O$6:$O$546,'BM MORRO DA CRUZ'!$K64),0) -> 0 | Y64: =ROUND(X64*$P64,2) -> 0 | Z64: =IFERROR(SUMIFS('BM MORRO DA CRUZ - VERTICAL'!AD$6:AD$546,'BM MORRO DA CRUZ - VERTICAL'!$O$6:$O$546,'BM MORRO DA CRUZ'!$K64),0) -> 0 | AA64: =ROUND(Z64*$P64,2) -> 0 | AB64: =IFERROR(SUMIFS('BM MORRO DA CRUZ - VERTICAL'!AF$6:AF$546,'BM MORRO DA CRUZ - VERTICAL'!$O$6:$O$546,'BM MORRO DA CRUZ'!$K64),0) -> 0 | AC64: =ROUND(AB64*$P64,2) -> 0 | AD64: =IFERROR(SUMIFS('BM MORRO DA CRUZ - VERTICAL'!AH$6:AH$546,'BM MORRO DA CRUZ - VERTICAL'!$O$6:$O$546,'BM MORRO DA CRUZ'!$K64),0) -> 0 | AE64: =ROUND(AD64*$P64,2) -> 0 | AF64: =IFERROR(SUMIFS('BM MORRO DA CRUZ - VERTICAL'!AJ$6:AJ$546,'BM MORRO DA CRUZ - VERTICAL'!$O$6:$O$546,'BM MORRO DA CRUZ'!$K64),0) -> 0 | AG64: =ROUND(AF64*$P64,2) -> 0 | AH64: =IFERROR(SUMIFS('BM MORRO DA CRUZ - VERTICAL'!AL$6:AL$546,'BM MORRO DA CRUZ - VERTICAL'!$O$6:$O$546,'BM MORRO DA CRUZ'!$K64),0) -> 0 | AI64: =ROUND(AH64*$P64,2) -> 0 | AJ64: =IFERROR(SUMIFS('BM MORRO DA CRUZ - VERTICAL'!AN$6:AN$546,'BM MORRO DA CRUZ - VERTICAL'!$O$6:$O$546,'BM MORRO DA CRUZ'!$K64),0) -> 0 | AK64: =ROUND(AJ64*$P64,2) -> 0 | AL64: =IFERROR(SUMIFS('BM MORRO DA CRUZ - VERTICAL'!AP$6:AP$546,'BM MORRO DA CRUZ - VERTICAL'!$O$6:$O$546,'BM MORRO DA CRUZ'!$K64),0) -> 0 | AM64: =ROUND(AL64*$P64,2) -> 0 | AN64: =IFERROR(SUMIFS('BM MORRO DA CRUZ - VERTICAL'!AR$6:AR$546,'BM MORRO DA CRUZ - VERTICAL'!$O$6:$O$546,'BM MORRO DA CRUZ'!$K64),0) -> 0 | AO64: =ROUND(AN64*$P64,2) -> 0 | AP64: =IFERROR(SUMIFS('BM MORRO DA CRUZ - VERTICAL'!AT$6:AT$546,'BM MORRO DA CRUZ - VERTICAL'!$O$6:$O$546,'BM MORRO DA CRUZ'!$K64),0) -> 0 | AQ64: =ROUND(AP64*$P64,2) -> 0 | AR64: =IFERROR(SUMIFS('BM MORRO DA CRUZ - VERTICAL'!AV$6:AV$546,'BM MORRO DA CRUZ - VERTICAL'!$O$6:$O$546,'BM MORRO DA CRUZ'!$K64),0) -> 0 | AS64: =ROUND(AR64*$P64,2) -> 0 | AT64: =IFERROR(SUMIFS('BM MORRO DA CRUZ - VERTICAL'!AX$6:AX$546,'BM MORRO DA CRUZ - VERTICAL'!$O$6:$O$546,'BM MORRO DA CRUZ'!$K64),0) -> 0 | AU64: =ROUND(AT64*$P64,2) -> 0 | AV64: =IFERROR(SUMIFS('BM MORRO DA CRUZ - VERTICAL'!AZ$6:AZ$546,'BM MORRO DA CRUZ - VERTICAL'!$O$6:$O$546,'BM MORRO DA CRUZ'!$K64),0) -> 0 | AW64: =ROUND(AV64*$P64,2) -> 0 | AX64: =IFERROR(SUMIFS('BM MORRO DA CRUZ - VERTICAL'!BB$6:BB$546,'BM MORRO DA CRUZ - VERTICAL'!$O$6:$O$546,'BM MORRO DA CRUZ'!$K64),0) -> 0 | AY64: =ROUND(AX64*$P64,2) -> 0 | AZ64: =IFERROR(SUMIFS('BM MORRO DA CRUZ - VERTICAL'!BD$6:BD$546,'BM MORRO DA CRUZ - VERTICAL'!$O$6:$O$546,'BM MORRO DA CRUZ'!$K64),0) -> 0 | BA64: =ROUND(AZ64*$P64,2) -> 0 | BB64: =IFERROR(SUMIFS($R64:$BA64,$R$5:$BA$5,$BB$5),0) -> 0 | BC64: =SUMIFS($R64:$BA64,$R$5:$BA$5,$S$5) -> 0 | BD64: =IFERROR(BB64/O64,0) -> 0 | BE64: =IFERROR((O64-BB64)/O64,0) -> 1
A65: 1.14.6 | B65: COLARINHO INJETADO PONTA LONGA | C65: PN10 | D65: PE100 | E65: COLARINHO | F65: TERMOFUSÃO | G65: 225 | H65: PEAD | I65: HIDROMECÂNICO | J65: PEAD | K65: 1514603025028 | L65: MATERIAL | M65: COLARINHO DE POLIETILENO DE ALTA DENSIDADE (PEAD), DN 225, PN-10 (10 KGF/CM²), INJETADA PE-100 SDR-17; PONTA LONGA; PARA ÁGUA OU ESGOTO; NBR 15593 | N65: UN | O65: 17 | P65: 282.82 | Q65: =ROUND(P65*$O65,2) -> 4807.94 | R65: =IFERROR(SUMIFS('BM MORRO DA CRUZ - VERTICAL'!V$6:V$546,'BM MORRO DA CRUZ - VERTICAL'!$O$6:$O$546,'BM MORRO DA CRUZ'!$K65),0) -> 0 | S65: =ROUND(R65*$P65,2) -> 0 | T65: =IFERROR(SUMIFS('BM MORRO DA CRUZ - VERTICAL'!X$6:X$546,'BM MORRO DA CRUZ - VERTICAL'!$O$6:$O$546,'BM MORRO DA CRUZ'!$K65),0) -> 0 | U65: =ROUND(T65*$P65,2) -> 0 | V65: =IFERROR(SUMIFS('BM MORRO DA CRUZ - VERTICAL'!Z$6:Z$546,'BM MORRO DA CRUZ - VERTICAL'!$O$6:$O$546,'BM MORRO DA CRUZ'!$K65),0) -> 0 | W65: =ROUND(V65*$P65,2) -> 0 | X65: =IFERROR(SUMIFS('BM MORRO DA CRUZ - VERTICAL'!AB$6:AB$546,'BM MORRO DA CRUZ - VERTICAL'!$O$6:$O$546,'BM MORRO DA CRUZ'!$K65),0) -> 0 | Y65: =ROUND(X65*$P65,2) -> 0 | Z65: =IFERROR(SUMIFS('BM MORRO DA CRUZ - VERTICAL'!AD$6:AD$546,'BM MORRO DA CRUZ - VERTICAL'!$O$6:$O$546,'BM MORRO DA CRUZ'!$K65),0) -> 0 | AA65: =ROUND(Z65*$P65,2) -> 0 | AB65: =IFERROR(SUMIFS('BM MORRO DA CRUZ - VERTICAL'!AF$6:AF$546,'BM MORRO DA CRUZ - VERTICAL'!$O$6:$O$546,'BM MORRO DA CRUZ'!$K65),0) -> 0 | AC65: =ROUND(AB65*$P65,2) -> 0 | AD65: =IFERROR(SUMIFS('BM MORRO DA CRUZ - VERTICAL'!AH$6:AH$546,'BM MORRO DA CRUZ - VERTICAL'!$O$6:$O$546,'BM MORRO DA CRUZ'!$K65),0) -> 0 | AE65: =ROUND(AD65*$P65,2) -> 0 | AF65: =IFERROR(SUMIFS('BM MORRO DA CRUZ - VERTICAL'!AJ$6:AJ$546,'BM MORRO DA CRUZ - VERTICAL'!$O$6:$O$546,'BM MORRO DA CRUZ'!$K65),0) -> 0 | AG65: =ROUND(AF65*$P65,2) -> 0 | AH65: =IFERROR(SUMIFS('BM MORRO DA CRUZ - VERTICAL'!AL$6:AL$546,'BM MORRO DA CRUZ - VERTICAL'!$O$6:$O$546,'BM MORRO DA CRUZ'!$K65),0) -> 0 | AI65: =ROUND(AH65*$P65,2) -> 0 | AJ65: =IFERROR(SUMIFS('BM MORRO DA CRUZ - VERTICAL'!AN$6:AN$546,'BM MORRO DA CRUZ - VERTICAL'!$O$6:$O$546,'BM MORRO DA CRUZ'!$K65),0) -> 0 | AK65: =ROUND(AJ65*$P65,2) -> 0 | AL65: =IFERROR(SUMIFS('BM MORRO DA CRUZ - VERTICAL'!AP$6:AP$546,'BM MORRO DA CRUZ - VERTICAL'!$O$6:$O$546,'BM MORRO DA CRUZ'!$K65),0) -> 0 | AM65: =ROUND(AL65*$P65,2) -> 0 | AN65: =IFERROR(SUMIFS('BM MORRO DA CRUZ - VERTICAL'!AR$6:AR$546,'BM MORRO DA CRUZ - VERTICAL'!$O$6:$O$546,'BM MORRO DA CRUZ'!$K65),0) -> 0 | AO65: =ROUND(AN65*$P65,2) -> 0 | AP65: =IFERROR(SUMIFS('BM MORRO DA CRUZ - VERTICAL'!AT$6:AT$546,'BM MORRO DA CRUZ - VERTICAL'!$O$6:$O$546,'BM MORRO DA CRUZ'!$K65),0) -> 0 | AQ65: =ROUND(AP65*$P65,2) -> 0 | AR65: =IFERROR(SUMIFS('BM MORRO DA CRUZ - VERTICAL'!AV$6:AV$546,'BM MORRO DA CRUZ - VERTICAL'!$O$6:$O$546,'BM MORRO DA CRUZ'!$K65),0) -> 0 | AS65: =ROUND(AR65*$P65,2) -> 0 | AT65: =IFERROR(SUMIFS('BM MORRO DA CRUZ - VERTICAL'!AX$6:AX$546,'BM MORRO DA CRUZ - VERTICAL'!$O$6:$O$546,'BM MORRO DA CRUZ'!$K65),0) -> 0 | AU65: =ROUND(AT65*$P65,2) -> 0 | AV65: =IFERROR(SUMIFS('BM MORRO DA CRUZ - VERTICAL'!AZ$6:AZ$546,'BM MORRO DA CRUZ - VERTICAL'!$O$6:$O$546,'BM MORRO DA CRUZ'!$K65),0) -> 0 | AW65: =ROUND(AV65*$P65,2) -> 0 | AX65: =IFERROR(SUMIFS('BM MORRO DA CRUZ - VERTICAL'!BB$6:BB$546,'BM MORRO DA CRUZ - VERTICAL'!$O$6:$O$546,'BM MORRO DA CRUZ'!$K65),0) -> 0 | AY65: =ROUND(AX65*$P65,2) -> 0 | AZ65: =IFERROR(SUMIFS('BM MORRO DA CRUZ - VERTICAL'!BD$6:BD$546,'BM MORRO DA CRUZ - VERTICAL'!$O$6:$O$546,'BM MORRO DA CRUZ'!$K65),0) -> 0 | BA65: =ROUND(AZ65*$P65,2) -> 0 | BB65: =IFERROR(SUMIFS($R65:$BA65,$R$5:$BA$5,$BB$5),0) -> 0 | BC65: =SUMIFS($R65:$BA65,$R$5:$BA$5,$S$5) -> 0 | BD65: =IFERROR(BB65/O65,0) -> 0 | BE65: =IFERROR((O65-BB65)/O65,0) -> 1
A66: 1.14.7 | B66: COLARINHO INJETADO PONTA LONGA | C66: PN10 | D66: PE100 | E66: COLARINHO | F66: TERMOFUSÃO | G66: 250 | H66: PEAD | I66: HIDROMECÂNICO | J66: PEAD | K66: 1514603025029 | L66: MATERIAL | M66: COLARINHO DE POLIETILENO DE ALTA DENSIDADE (PEAD), DN 250, PN-10 (10 KGF/CM²), INJETADA PE-100 SDR-17; PONTA LONGA; PARA ÁGUA OU ESGOTO; NBR 15593 | N66: UN | O66: 10 | P66: 459.3 | Q66: =ROUND(P66*$O66,2) -> 4593 | R66: =IFERROR(SUMIFS('BM MORRO DA CRUZ - VERTICAL'!V$6:V$546,'BM MORRO DA CRUZ - VERTICAL'!$O$6:$O$546,'BM MORRO DA CRUZ'!$K66),0) -> 0 | S66: =ROUND(R66*$P66,2) -> 0 | T66: =IFERROR(SUMIFS('BM MORRO DA CRUZ - VERTICAL'!X$6:X$546,'BM MORRO DA CRUZ - VERTICAL'!$O$6:$O$546,'BM MORRO DA CRUZ'!$K66),0) -> 0 | U66: =ROUND(T66*$P66,2) -> 0 | V66: =IFERROR(SUMIFS('BM MORRO DA CRUZ - VERTICAL'!Z$6:Z$546,'BM MORRO DA CRUZ - VERTICAL'!$O$6:$O$546,'BM MORRO DA CRUZ'!$K66),0) -> 0 | W66: =ROUND(V66*$P66,2) -> 0 | X66: =IFERROR(SUMIFS('BM MORRO DA CRUZ - VERTICAL'!AB$6:AB$546,'BM MORRO DA CRUZ - VERTICAL'!$O$6:$O$546,'BM MORRO DA CRUZ'!$K66),0) -> 0 | Y66: =ROUND(X66*$P66,2) -> 0 | Z66: =IFERROR(SUMIFS('BM MORRO DA CRUZ - VERTICAL'!AD$6:AD$546,'BM MORRO DA CRUZ - VERTICAL'!$O$6:$O$546,'BM MORRO DA CRUZ'!$K66),0) -> 0 | AA66: =ROUND(Z66*$P66,2) -> 0 | AB66: =IFERROR(SUMIFS('BM MORRO DA CRUZ - VERTICAL'!AF$6:AF$546,'BM MORRO DA CRUZ - VERTICAL'!$O$6:$O$546,'BM MORRO DA CRUZ'!$K66),0) -> 0 | AC66: =ROUND(AB66*$P66,2) -> 0 | AD66: =IFERROR(SUMIFS('BM MORRO DA CRUZ - VERTICAL'!AH$6:AH$546,'BM MORRO DA CRUZ - VERTICAL'!$O$6:$O$546,'BM MORRO DA CRUZ'!$K66),0) -> 0 | AE66: =ROUND(AD66*$P66,2) -> 0 | AF66: =IFERROR(SUMIFS('BM MORRO DA CRUZ - VERTICAL'!AJ$6:AJ$546,'BM MORRO DA CRUZ - VERTICAL'!$O$6:$O$546,'BM MORRO DA CRUZ'!$K66),0) -> 0 | AG66: =ROUND(AF66*$P66,2) -> 0 | AH66: =IFERROR(SUMIFS('BM MORRO DA CRUZ - VERTICAL'!AL$6:AL$546,'BM MORRO DA CRUZ - VERTICAL'!$O$6:$O$546,'BM MORRO DA CRUZ'!$K66),0) -> 0 | AI66: =ROUND(AH66*$P66,2) -> 0 | AJ66: =IFERROR(SUMIFS('BM MORRO DA CRUZ - VERTICAL'!AN$6:AN$546,'BM MORRO DA CRUZ - VERTICAL'!$O$6:$O$546,'BM MORRO DA CRUZ'!$K66),0) -> 0 | AK66: =ROUND(AJ66*$P66,2) -> 0 | AL66: =IFERROR(SUMIFS('BM MORRO DA CRUZ - VERTICAL'!AP$6:AP$546,'BM MORRO DA CRUZ - VERTICAL'!$O$6:$O$546,'BM MORRO DA CRUZ'!$K66),0) -> 0 | AM66: =ROUND(AL66*$P66,2) -> 0 | AN66: =IFERROR(SUMIFS('BM MORRO DA CRUZ - VERTICAL'!AR$6:AR$546,'BM MORRO DA CRUZ - VERTICAL'!$O$6:$O$546,'BM MORRO DA CRUZ'!$K66),0) -> 0 | AO66: =ROUND(AN66*$P66,2) -> 0 | AP66: =IFERROR(SUMIFS('BM MORRO DA CRUZ - VERTICAL'!AT$6:AT$546,'BM MORRO DA CRUZ - VERTICAL'!$O$6:$O$546,'BM MORRO DA CRUZ'!$K66),0) -> 0 | AQ66: =ROUND(AP66*$P66,2) -> 0 | AR66: =IFERROR(SUMIFS('BM MORRO DA CRUZ - VERTICAL'!AV$6:AV$546,'BM MORRO DA CRUZ - VERTICAL'!$O$6:$O$546,'BM MORRO DA CRUZ'!$K66),0) -> 0 | AS66: =ROUND(AR66*$P66,2) -> 0 | AT66: =IFERROR(SUMIFS('BM MORRO DA CRUZ - VERTICAL'!AX$6:AX$546,'BM MORRO DA CRUZ - VERTICAL'!$O$6:$O$546,'BM MORRO DA CRUZ'!$K66),0) -> 0 | AU66: =ROUND(AT66*$P66,2) -> 0 | AV66: =IFERROR(SUMIFS('BM MORRO DA CRUZ - VERTICAL'!AZ$6:AZ$546,'BM MORRO DA CRUZ - VERTICAL'!$O$6:$O$546,'BM MORRO DA CRUZ'!$K66),0) -> 0 | AW66: =ROUND(AV66*$P66,2) -> 0 | AX66: =IFERROR(SUMIFS('BM MORRO DA CRUZ - VERTICAL'!BB$6:BB$546,'BM MORRO DA CRUZ - VERTICAL'!$O$6:$O$546,'BM MORRO DA CRUZ'!$K66),0) -> 0 | AY66: =ROUND(AX66*$P66,2) -> 0 | AZ66: =IFERROR(SUMIFS('BM MORRO DA CRUZ - VERTICAL'!BD$6:BD$546,'BM MORRO DA CRUZ - VERTICAL'!$O$6:$O$546,'BM MORRO DA CRUZ'!$K66),0) -> 0 | BA66: =ROUND(AZ66*$P66,2) -> 0 | BB66: =IFERROR(SUMIFS($R66:$BA66,$R$5:$BA$5,$BB$5),0) -> 0 | BC66: =SUMIFS($R66:$BA66,$R$5:$BA$5,$S$5) -> 0 | BD66: =IFERROR(BB66/O66,0) -> 0 | BE66: =IFERROR((O66-BB66)/O66,0) -> 1
A67: 1.14.8 | B67: COLARINHO INJETADO PONTA LONGA | C67: PN10 | D67: PE100 | E67: COLARINHO | F67: TERMOFUSÃO | G67: 500 | H67: PEAD | I67: HIDROMECÂNICO | J67: PEAD | K67: 1514603025035 | L67: MATERIAL | M67: COLARINHO DE POLIETILENO DE ALTA DENSIDADE (PEAD), DN 500, PN-10 (10 KGF/CM²), INJETADA PE-100 SDR-17; PONTA LONGA; PARA ÁGUA OU ESGOTO; NBR 15593 | N67: UN | O67: 2 | P67: 2629.23 | Q67: =ROUND(P67*$O67,2) -> 5258.46 | R67: =IFERROR(SUMIFS('BM MORRO DA CRUZ - VERTICAL'!V$6:V$546,'BM MORRO DA CRUZ - VERTICAL'!$O$6:$O$546,'BM MORRO DA CRUZ'!$K67),0) -> 0 | S67: =ROUND(R67*$P67,2) -> 0 | T67: =IFERROR(SUMIFS('BM MORRO DA CRUZ - VERTICAL'!X$6:X$546,'BM MORRO DA CRUZ - VERTICAL'!$O$6:$O$546,'BM MORRO DA CRUZ'!$K67),0) -> 0 | U67: =ROUND(T67*$P67,2) -> 0 | V67: =IFERROR(SUMIFS('BM MORRO DA CRUZ - VERTICAL'!Z$6:Z$546,'BM MORRO DA CRUZ - VERTICAL'!$O$6:$O$546,'BM MORRO DA CRUZ'!$K67),0) -> 0 | W67: =ROUND(V67*$P67,2) -> 0 | X67: =IFERROR(SUMIFS('BM MORRO DA CRUZ - VERTICAL'!AB$6:AB$546,'BM MORRO DA CRUZ - VERTICAL'!$O$6:$O$546,'BM MORRO DA CRUZ'!$K67),0) -> 0 | Y67: =ROUND(X67*$P67,2) -> 0 | Z67: =IFERROR(SUMIFS('BM MORRO DA CRUZ - VERTICAL'!AD$6:AD$546,'BM MORRO DA CRUZ - VERTICAL'!$O$6:$O$546,'BM MORRO DA CRUZ'!$K67),0) -> 0 | AA67: =ROUND(Z67*$P67,2) -> 0 | AB67: =IFERROR(SUMIFS('BM MORRO DA CRUZ - VERTICAL'!AF$6:AF$546,'BM MORRO DA CRUZ - VERTICAL'!$O$6:$O$546,'BM MORRO DA CRUZ'!$K67),0) -> 0 | AC67: =ROUND(AB67*$P67,2) -> 0 | AD67: =IFERROR(SUMIFS('BM MORRO DA CRUZ - VERTICAL'!AH$6:AH$546,'BM MORRO DA CRUZ - VERTICAL'!$O$6:$O$546,'BM MORRO DA CRUZ'!$K67),0) -> 0 | AE67: =ROUND(AD67*$P67,2) -> 0 | AF67: =IFERROR(SUMIFS('BM MORRO DA CRUZ - VERTICAL'!AJ$6:AJ$546,'BM MORRO DA CRUZ - VERTICAL'!$O$6:$O$546,'BM MORRO DA CRUZ'!$K67),0) -> 0 | AG67: =ROUND(AF67*$P67,2) -> 0 | AH67: =IFERROR(SUMIFS('BM MORRO DA CRUZ - VERTICAL'!AL$6:AL$546,'BM MORRO DA CRUZ - VERTICAL'!$O$6:$O$546,'BM MORRO DA CRUZ'!$K67),0) -> 0 | AI67: =ROUND(AH67*$P67,2) -> 0 | AJ67: =IFERROR(SUMIFS('BM MORRO DA CRUZ - VERTICAL'!AN$6:AN$546,'BM MORRO DA CRUZ - VERTICAL'!$O$6:$O$546,'BM MORRO DA CRUZ'!$K67),0) -> 0 | AK67: =ROUND(AJ67*$P67,2) -> 0 | AL67: =IFERROR(SUMIFS('BM MORRO DA CRUZ - VERTICAL'!AP$6:AP$546,'BM MORRO DA CRUZ - VERTICAL'!$O$6:$O$546,'BM MORRO DA CRUZ'!$K67),0) -> 0 | AM67: =ROUND(AL67*$P67,2) -> 0 | AN67: =IFERROR(SUMIFS('BM MORRO DA CRUZ - VERTICAL'!AR$6:AR$546,'BM MORRO DA CRUZ - VERTICAL'!$O$6:$O$546,'BM MORRO DA CRUZ'!$K67),0) -> 0 | AO67: =ROUND(AN67*$P67,2) -> 0 | AP67: =IFERROR(SUMIFS('BM MORRO DA CRUZ - VERTICAL'!AT$6:AT$546,'BM MORRO DA CRUZ - VERTICAL'!$O$6:$O$546,'BM MORRO DA CRUZ'!$K67),0) -> 0 | AQ67: =ROUND(AP67*$P67,2) -> 0 | AR67: =IFERROR(SUMIFS('BM MORRO DA CRUZ - VERTICAL'!AV$6:AV$546,'BM MORRO DA CRUZ - VERTICAL'!$O$6:$O$546,'BM MORRO DA CRUZ'!$K67),0) -> 0 | AS67: =ROUND(AR67*$P67,2) -> 0 | AT67: =IFERROR(SUMIFS('BM MORRO DA CRUZ - VERTICAL'!AX$6:AX$546,'BM MORRO DA CRUZ - VERTICAL'!$O$6:$O$546,'BM MORRO DA CRUZ'!$K67),0) -> 0 | AU67: =ROUND(AT67*$P67,2) -> 0 | AV67: =IFERROR(SUMIFS('BM MORRO DA CRUZ - VERTICAL'!AZ$6:AZ$546,'BM MORRO DA CRUZ - VERTICAL'!$O$6:$O$546,'BM MORRO DA CRUZ'!$K67),0) -> 0 | AW67: =ROUND(AV67*$P67,2) -> 0 | AX67: =IFERROR(SUMIFS('BM MORRO DA CRUZ - VERTICAL'!BB$6:BB$546,'BM MORRO DA CRUZ - VERTICAL'!$O$6:$O$546,'BM MORRO DA CRUZ'!$K67),0) -> 0 | AY67: =ROUND(AX67*$P67,2) -> 0 | AZ67: =IFERROR(SUMIFS('BM MORRO DA CRUZ - VERTICAL'!BD$6:BD$546,'BM MORRO DA CRUZ - VERTICAL'!$O$6:$O$546,'BM MORRO DA CRUZ'!$K67),0) -> 0 | BA67: =ROUND(AZ67*$P67,2) -> 0 | BB67: =IFERROR(SUMIFS($R67:$BA67,$R$5:$BA$5,$BB$5),0) -> 0 | BC67: =SUMIFS($R67:$BA67,$R$5:$BA$5,$S$5) -> 0 | BD67: =IFERROR(BB67/O67,0) -> 0 | BE67: =IFERROR((O67-BB67)/O67,0) -> 1
A68: 1.14.9 | B68: COLARINHO INJETADO PONTA LONGA | C68: PN10 | D68: PE100 | E68: COLARINHO | F68: TERMOFUSÃO | G68: 63 | H68: PEAD | I68: HIDROMECÂNICO | J68: PEAD | K68: 1514603025019 | L68: MATERIAL | M68: COLARINHO DE POLIETILENO DE ALTA DENSIDADE (PEAD), DN 63, PN-10 (10 KGF/CM²), INJETADA PE-100 SDR-17; PONTA LONGA; PARA ÁGUA OU ESGOTO; NBR 15593 | N68: UN | O68: 120 | P68: 35.14 | Q68: =ROUND(P68*$O68,2) -> 4216.8 | R68: =IFERROR(SUMIFS('BM MORRO DA CRUZ - VERTICAL'!V$6:V$546,'BM MORRO DA CRUZ - VERTICAL'!$O$6:$O$546,'BM MORRO DA CRUZ'!$K68),0) -> 0 | S68: =ROUND(R68*$P68,2) -> 0 | T68: =IFERROR(SUMIFS('BM MORRO DA CRUZ - VERTICAL'!X$6:X$546,'BM MORRO DA CRUZ - VERTICAL'!$O$6:$O$546,'BM MORRO DA CRUZ'!$K68),0) -> 0 | U68: =ROUND(T68*$P68,2) -> 0 | V68: =IFERROR(SUMIFS('BM MORRO DA CRUZ - VERTICAL'!Z$6:Z$546,'BM MORRO DA CRUZ - VERTICAL'!$O$6:$O$546,'BM MORRO DA CRUZ'!$K68),0) -> 0 | W68: =ROUND(V68*$P68,2) -> 0 | X68: =IFERROR(SUMIFS('BM MORRO DA CRUZ - VERTICAL'!AB$6:AB$546,'BM MORRO DA CRUZ - VERTICAL'!$O$6:$O$546,'BM MORRO DA CRUZ'!$K68),0) -> 0 | Y68: =ROUND(X68*$P68,2) -> 0 | Z68: =IFERROR(SUMIFS('BM MORRO DA CRUZ - VERTICAL'!AD$6:AD$546,'BM MORRO DA CRUZ - VERTICAL'!$O$6:$O$546,'BM MORRO DA CRUZ'!$K68),0) -> 0 | AA68: =ROUND(Z68*$P68,2) -> 0 | AB68: =IFERROR(SUMIFS('BM MORRO DA CRUZ - VERTICAL'!AF$6:AF$546,'BM MORRO DA CRUZ - VERTICAL'!$O$6:$O$546,'BM MORRO DA CRUZ'!$K68),0) -> 0 | AC68: =ROUND(AB68*$P68,2) -> 0 | AD68: =IFERROR(SUMIFS('BM MORRO DA CRUZ - VERTICAL'!AH$6:AH$546,'BM MORRO DA CRUZ - VERTICAL'!$O$6:$O$546,'BM MORRO DA CRUZ'!$K68),0) -> 0 | AE68: =ROUND(AD68*$P68,2) -> 0 | AF68: =IFERROR(SUMIFS('BM MORRO DA CRUZ - VERTICAL'!AJ$6:AJ$546,'BM MORRO DA CRUZ - VERTICAL'!$O$6:$O$546,'BM MORRO DA CRUZ'!$K68),0) -> 0 | AG68: =ROUND(AF68*$P68,2) -> 0 | AH68: =IFERROR(SUMIFS('BM MORRO DA CRUZ - VERTICAL'!AL$6:AL$546,'BM MORRO DA CRUZ - VERTICAL'!$O$6:$O$546,'BM MORRO DA CRUZ'!$K68),0) -> 0 | AI68: =ROUND(AH68*$P68,2) -> 0 | AJ68: =IFERROR(SUMIFS('BM MORRO DA CRUZ - VERTICAL'!AN$6:AN$546,'BM MORRO DA CRUZ - VERTICAL'!$O$6:$O$546,'BM MORRO DA CRUZ'!$K68),0) -> 0 | AK68: =ROUND(AJ68*$P68,2) -> 0 | AL68: =IFERROR(SUMIFS('BM MORRO DA CRUZ - VERTICAL'!AP$6:AP$546,'BM MORRO DA CRUZ - VERTICAL'!$O$6:$O$546,'BM MORRO DA CRUZ'!$K68),0) -> 0 | AM68: =ROUND(AL68*$P68,2) -> 0 | AN68: =IFERROR(SUMIFS('BM MORRO DA CRUZ - VERTICAL'!AR$6:AR$546,'BM MORRO DA CRUZ - VERTICAL'!$O$6:$O$546,'BM MORRO DA CRUZ'!$K68),0) -> 0 | AO68: =ROUND(AN68*$P68,2) -> 0 | AP68: =IFERROR(SUMIFS('BM MORRO DA CRUZ - VERTICAL'!AT$6:AT$546,'BM MORRO DA CRUZ - VERTICAL'!$O$6:$O$546,'BM MORRO DA CRUZ'!$K68),0) -> 0 | AQ68: =ROUND(AP68*$P68,2) -> 0 | AR68: =IFERROR(SUMIFS('BM MORRO DA CRUZ - VERTICAL'!AV$6:AV$546,'BM MORRO DA CRUZ - VERTICAL'!$O$6:$O$546,'BM MORRO DA CRUZ'!$K68),0) -> 0 | AS68: =ROUND(AR68*$P68,2) -> 0 | AT68: =IFERROR(SUMIFS('BM MORRO DA CRUZ - VERTICAL'!AX$6:AX$546,'BM MORRO DA CRUZ - VERTICAL'!$O$6:$O$546,'BM MORRO DA CRUZ'!$K68),0) -> 0 | AU68: =ROUND(AT68*$P68,2) -> 0 | AV68: =IFERROR(SUMIFS('BM MORRO DA CRUZ - VERTICAL'!AZ$6:AZ$546,'BM MORRO DA CRUZ - VERTICAL'!$O$6:$O$546,'BM MORRO DA CRUZ'!$K68),0) -> 0 | AW68: =ROUND(AV68*$P68,2) -> 0 | AX68: =IFERROR(SUMIFS('BM MORRO DA CRUZ - VERTICAL'!BB$6:BB$546,'BM MORRO DA CRUZ - VERTICAL'!$O$6:$O$546,'BM MORRO DA CRUZ'!$K68),0) -> 0 | AY68: =ROUND(AX68*$P68,2) -> 0 | AZ68: =IFERROR(SUMIFS('BM MORRO DA CRUZ - VERTICAL'!BD$6:BD$546,'BM MORRO DA CRUZ - VERTICAL'!$O$6:$O$546,'BM MORRO DA CRUZ'!$K68),0) -> 0 | BA68: =ROUND(AZ68*$P68,2) -> 0 | BB68: =IFERROR(SUMIFS($R68:$BA68,$R$5:$BA$5,$BB$5),0) -> 0 | BC68: =SUMIFS($R68:$BA68,$R$5:$BA$5,$S$5) -> 0 | BD68: =IFERROR(BB68/O68,0) -> 0 | BE68: =IFERROR((O68-BB68)/O68,0) -> 1
A69: 1.14.10 | B69: COLARINHO INJETADO PONTA LONGA | C69: PN10 | D69: PE100 | E69: COLARINHO | F69: TERMOFUSÃO | G69: 90 | H69: PEAD | I69: HIDROMECÂNICO | J69: PEAD | K69: 1514603025021 | L69: MATERIAL | M69: COLARINHO DE POLIETILENO DE ALTA DENSIDADE (PEAD), DN 90, PN-10 (10 KGF/CM²), INJETADA PE-100 SDR-17; PONTA LONGA; PARA ÁGUA OU ESGOTO; NBR 15593 | N69: UN | O69: 30 | P69: 59.13 | Q69: =ROUND(P69*$O69,2) -> 1773.9 | R69: =IFERROR(SUMIFS('BM MORRO DA CRUZ - VERTICAL'!V$6:V$546,'BM MORRO DA CRUZ - VERTICAL'!$O$6:$O$546,'BM MORRO DA CRUZ'!$K69),0) -> 0 | S69: =ROUND(R69*$P69,2) -> 0 | T69: =IFERROR(SUMIFS('BM MORRO DA CRUZ - VERTICAL'!X$6:X$546,'BM MORRO DA CRUZ - VERTICAL'!$O$6:$O$546,'BM MORRO DA CRUZ'!$K69),0) -> 0 | U69: =ROUND(T69*$P69,2) -> 0 | V69: =IFERROR(SUMIFS('BM MORRO DA CRUZ - VERTICAL'!Z$6:Z$546,'BM MORRO DA CRUZ - VERTICAL'!$O$6:$O$546,'BM MORRO DA CRUZ'!$K69),0) -> 0 | W69: =ROUND(V69*$P69,2) -> 0 | X69: =IFERROR(SUMIFS('BM MORRO DA CRUZ - VERTICAL'!AB$6:AB$546,'BM MORRO DA CRUZ - VERTICAL'!$O$6:$O$546,'BM MORRO DA CRUZ'!$K69),0) -> 0 | Y69: =ROUND(X69*$P69,2) -> 0 | Z69: =IFERROR(SUMIFS('BM MORRO DA CRUZ - VERTICAL'!AD$6:AD$546,'BM MORRO DA CRUZ - VERTICAL'!$O$6:$O$546,'BM MORRO DA CRUZ'!$K69),0) -> 0 | AA69: =ROUND(Z69*$P69,2) -> 0 | AB69: =IFERROR(SUMIFS('BM MORRO DA CRUZ - VERTICAL'!AF$6:AF$546,'BM MORRO DA CRUZ - VERTICAL'!$O$6:$O$546,'BM MORRO DA CRUZ'!$K69),0) -> 0 | AC69: =ROUND(AB69*$P69,2) -> 0 | AD69: =IFERROR(SUMIFS('BM MORRO DA CRUZ - VERTICAL'!AH$6:AH$546,'BM MORRO DA CRUZ - VERTICAL'!$O$6:$O$546,'BM MORRO DA CRUZ'!$K69),0) -> 0 | AE69: =ROUND(AD69*$P69,2) -> 0 | AF69: =IFERROR(SUMIFS('BM MORRO DA CRUZ - VERTICAL'!AJ$6:AJ$546,'BM MORRO DA CRUZ - VERTICAL'!$O$6:$O$546,'BM MORRO DA CRUZ'!$K69),0) -> 0 | AG69: =ROUND(AF69*$P69,2) -> 0 | AH69: =IFERROR(SUMIFS('BM MORRO DA CRUZ - VERTICAL'!AL$6:AL$546,'BM MORRO DA CRUZ - VERTICAL'!$O$6:$O$546,'BM MORRO DA CRUZ'!$K69),0) -> 0 | AI69: =ROUND(AH69*$P69,2) -> 0 | AJ69: =IFERROR(SUMIFS('BM MORRO DA CRUZ - VERTICAL'!AN$6:AN$546,'BM MORRO DA CRUZ - VERTICAL'!$O$6:$O$546,'BM MORRO DA CRUZ'!$K69),0) -> 0 | AK69: =ROUND(AJ69*$P69,2) -> 0 | AL69: =IFERROR(SUMIFS('BM MORRO DA CRUZ - VERTICAL'!AP$6:AP$546,'BM MORRO DA CRUZ - VERTICAL'!$O$6:$O$546,'BM MORRO DA CRUZ'!$K69),0) -> 0 | AM69: =ROUND(AL69*$P69,2) -> 0 | AN69: =IFERROR(SUMIFS('BM MORRO DA CRUZ - VERTICAL'!AR$6:AR$546,'BM MORRO DA CRUZ - VERTICAL'!$O$6:$O$546,'BM MORRO DA CRUZ'!$K69),0) -> 0 | AO69: =ROUND(AN69*$P69,2) -> 0 | AP69: =IFERROR(SUMIFS('BM MORRO DA CRUZ - VERTICAL'!AT$6:AT$546,'BM MORRO DA CRUZ - VERTICAL'!$O$6:$O$546,'BM MORRO DA CRUZ'!$K69),0) -> 0 | AQ69: =ROUND(AP69*$P69,2) -> 0 | AR69: =IFERROR(SUMIFS('BM MORRO DA CRUZ - VERTICAL'!AV$6:AV$546,'BM MORRO DA CRUZ - VERTICAL'!$O$6:$O$546,'BM MORRO DA CRUZ'!$K69),0) -> 0 | AS69: =ROUND(AR69*$P69,2) -> 0 | AT69: =IFERROR(SUMIFS('BM MORRO DA CRUZ - VERTICAL'!AX$6:AX$546,'BM MORRO DA CRUZ - VERTICAL'!$O$6:$O$546,'BM MORRO DA CRUZ'!$K69),0) -> 0 | AU69: =ROUND(AT69*$P69,2) -> 0 | AV69: =IFERROR(SUMIFS('BM MORRO DA CRUZ - VERTICAL'!AZ$6:AZ$546,'BM MORRO DA CRUZ - VERTICAL'!$O$6:$O$546,'BM MORRO DA CRUZ'!$K69),0) -> 0 | AW69: =ROUND(AV69*$P69,2) -> 0 | AX69: =IFERROR(SUMIFS('BM MORRO DA CRUZ - VERTICAL'!BB$6:BB$546,'BM MORRO DA CRUZ - VERTICAL'!$O$6:$O$546,'BM MORRO DA CRUZ'!$K69),0) -> 0 | AY69: =ROUND(AX69*$P69,2) -> 0 | AZ69: =IFERROR(SUMIFS('BM MORRO DA CRUZ - VERTICAL'!BD$6:BD$546,'BM MORRO DA CRUZ - VERTICAL'!$O$6:$O$546,'BM MORRO DA CRUZ'!$K69),0) -> 0 | BA69: =ROUND(AZ69*$P69,2) -> 0 | BB69: =IFERROR(SUMIFS($R69:$BA69,$R$5:$BA$5,$BB$5),0) -> 0 | BC69: =SUMIFS($R69:$BA69,$R$5:$BA$5,$S$5) -> 0 | BD69: =IFERROR(BB69/O69,0) -> 0 | BE69: =IFERROR((O69-BB69)/O69,0) -> 1
